Workbook

Sheet RIEPILOGO_RIMBORSO_SPESE
K1: Doc Nota Spese rev.06
K2: Riassunto spese trasferta - modulo
A4: RIASSUNTO SPESE TRASFERTA
F6: Rif EBS:
F7: Autore:
F8: ATTENZIONE!!! ERRORE COMPILAZIONE ELENCO_SPESE
A9: DATI TRASFERTA | D9: GESTIONE CONTANTI | G9: SPESE FATTURATE PAGATE DA CONTO BS | AC9: Traf. Commerciale IT | AD9: =RIMBORSO_SPESE!BL9+RIMBORSO_SPESE!BM9+RIMBORSO_SPESE!BN9 -> 0
A10: Data Inizio : | D10: Euro anticipati | E10: 0 | G10: Causale | J10: Importo | AC10: Traf. Commerciale EXT
A11: Data Fine : | D11: Euro prelevati CC | E11: =RIMBORSO_SPESE!AQ9 -> 0 | G11: Confort Viaggi rif: | J11: 0 | AC11: Fiera
A12: Cliente : | D12: Euro contanti spesi | E12: =RIMBORSO_SPESE!AV9+E18 -> 0 | G12: TAXI EMMEPI, | J12: 0 | L12: NB: In mancanza del dettaglio costi utilizzare costi indicativi in nota | AC12: Visita Fornitori
A13: Luogo : | D13: Euro resi | E13: 0 | G13: AVIS | J13: 0 | AC13: Altro (vedi causale)
A14: Tipo : | D14: Rimanenza Euro | E14: =E10+E11-E12-E13 -> 0 | AC14: AST-Installazione
A15: Causale: | D15: VALUTA ESTERA | AC15: AST-In Garanzia
D16: Tipo Valuta | E16: --- | AC16: AST-Fuori Garanzia
A17: Centro Costo/PRG : | D17: Valuta anticipata | E17: 0 | G17: RIMBORSO CHILOMETRICO PER USO AUTO PRORPIA | AC17: AST-A Contratto
A18: Dip. Esecutore : | D18: Tot € Cambiati | E18: =RIMBORSO_SPESE!AM9-RIMBORSO_SPESE!AO9 -> 0 | G18: Tot km da Rimborsare: | I18: ='RIMBORSO KM'!G57 -> 0 | J18: Importo | K18: =I18*0.3 -> 0 | AC18: AST-Promozionale
A19: Altro Personale BS 1 : | D19: Tot Valuta da Cambi | E19: =RIMBORSO_SPESE!AN9-RIMBORSO_SPESE!AP9 -> 0 | G19: RIASSUNTO DATI CONTABILI
A20: Altro Personale BS 2 : | D20: Valuta Prelevata CC | E20: =RIMBORSO_SPESE!AR9 -> 0 | G20: Causale | I20: Tot (in Euro) | J20: Tot (in Valuta)
A21: Altro Personale BS 3 : | D21: Tot Valuta Spesa (contanti) | E21: =RIMBORSO_SPESE!AW9 -> 0 | G21: Tot Pagamenti CC | I21: =RIMBORSO_SPESE!AT9 -> 0 | J21: =IF($E$25<>0,((RIMBORSO_SPESE!AU9)/$E$25),0) -> 0
A22: Targa Auto EBS : | D22: Valuta da rendere | E22: =E17+E19+E20-E21 -> 0 | G22: Pagamenti in Contanti | I22: =RIMBORSO_SPESE!AV9 -> 0 | J22: =IF($E$25<>0,((RIMBORSO_SPESE!AW9)/$E$25),0) -> 0
D23: Valuta Resa | E23: 0 | G23: Non Giustificate | I23: =RIMBORSO_SPESE!AY9+RIMBORSO_SPESE!AZ9 -> 0 | J23: =IF($E$25<>0,((RIMBORSO_SPESE!BA9+RIMBORSO_SPESE!BB9)/$E$25),0) -> 0
A24: N° Notti Italia : | D24: Differenza ricevuta-resa | E24: =(E22-E23) -> 0 | G24: Rifornimenti IT | I24: =RIMBORSO_SPESE!AK9 -> 0
A25: N° Notti Estero : | D25: Tasso di cambio di rif. | E25: 1 | G25: Fiera | I25: =RIMBORSO_SPESE!BG9+RIMBORSO_SPESE!BH9 -> 0 | J25: =IF($E$25<>0,((RIMBORSO_SPESE!BI9+RIMBORSO_SPESE!BJ9)/$E$25),0) -> 0
A27: TOTALI PER SINGOLE CAUSALI | H27: TOTALI CONTABILI
A28: Causale | C28: Euro | D28: Valuta | E28: Tot € | H28: € Tot Contabile (Cont. + CC) | J28: =SUM(I21:J22) -> 0
A29: Vitto/Alloggio | C29: =RIMBORSO_SPESE!AE9 -> 0 | D29: =RIMBORSO_SPESE!AF9 -> 0 | E29: =C29+IF($E$25<>0,(D29/$E$25),0) -> 0 | H29: € Tot Trasferta | J29: =J28+SUM(J11:K16)+K18 -> 0
A30: Varie | C30: =RIMBORSO_SPESE!AG9 -> 0 | D30: =RIMBORSO_SPESE!AH9 -> 0 | E30: =C30+IF($E$25<>0,(D30/$E$25),0) -> 0 | H30: Costo medio giornaliero | J30: =IF(C24+C25>0,J29/(C24+C25+1),"")
A31: Spostamenti | C31: =RIMBORSO_SPESE!AI9+RIMBORSO_SPESE!AK9 -> 0 | D31: =RIMBORSO_SPESE!AJ9+RIMBORSO_SPESE!AL9 -> 0 | E31: =C31+IF($E$25<>0,(D31/$E$25),0) -> 0 | H31: € Tot da Restituire | J31: =(E14* -1) +K18 -> 0
A33: FIRMA DIPENDENTE | G33: APPROVAZIONE

Sheet RIMBORSO_SPESE
K1: Doc. Rimborso spese rev.06
K2: Elenco spese uscita/trasferta - modulo
A4: ELENCO SPESE USCITA/TRASFERTA
E5: Causale:
E6: Autore:
E7: Firma:
A8: N° Ric. | B8: Data | C8: Tipo | D8: Causale | E8: Importo | G8: Mod. Pagamento | H8: Con Fattura | I8: NON Giustific. | J8: Rappresentanza | K8: Fiera | AE8: Euro | AF8: Valuta | AG8: Euro | AH8: Valuta | AI8: Euro | AJ8: Valuta | AK8: Euro | AL8: Valuta | AM8: Euro | AN8: Valuta | AO8: Euro | AP8: Valuta | AQ8: Euro | AR8: Valuta | AT8: Euro | AU8: Valuta | AV8: Euro | AW8: Valuta | AY8: Contanti | AZ8: CC | BA8: Contanti | BB8: CC | BC8: Contanti | BD8: CC | BE8: Contanti | BF8: CC | BG8: Contanti | BH8: CC | BI8: Contanti | BJ8: CC
E9: € | F9: Valuta Estera | Z9: CAUSALI SPESE | AA9: CAUSALI PAGAMENTI | AB9: ON/OFF | AD9: TOT | AE9: =SUM(AE11:AE140) -> 0 | AF9: =SUM(AF11:AF140) -> 0 | AG9: =SUM(AG11:AG140) -> 0 | AH9: =SUM(AH11:AH140) -> 0 | AI9: =SUM(AI11:AI140) -> 0 | AJ9: =SUM(AJ11:AJ140) -> 0 | AK9: =SUM(AK11:AK140) -> 0 | AL9: =SUM(AL11:AL140) -> 0 | ... AR9: =SUM(AR11:AR140) -> 0 | AT9: =SUM(AT11:AT140) -> 0 | AU9: =SUM(AU11:AU140) -> 0 | AV9: =SUM(AV11:AV140) -> 0 | AW9: =SUM(AW11:AW140) -> 0 | AY9: =SUM(AY11:AY140) -> 0 | AZ9: =SUM(AZ11:AZ140) -> 0 | BA9: =SUM(BA11:BA140) -> 0 | BB9: =SUM(BB11:BB140) -> 0 | BC9: =SUM(BC11:BC140) -> 0 | BD9: =SUM(BD11:BD140) -> 0 | BE9: =SUM(BE11:BE140) -> 0 | BF9: =SUM(BF11:BF140) -> 0 | ... BJ9: =SUM(BJ11:BJ140) -> 0 | BL9: =SUM(BL10:BL139) -> 0 | BM9: =SUM(BM10:BM139) -> 0 | BN9: =SUM(BN10:BN139) -> 0
D10: TOTALE | E10: =SUM(E11:E140) -> 0 | F10: =SUM(F11:F140) -> 0 | G10: ATTENZIONE!!! ERRORE DI COMPILAZIONE
A11: 1 | Z11: Vitto/Alloggio | AA11: CC-Personale | AE11: =IF($C11=$Z$11,$E11,0) -> 0 | AF11: =IF($C11=$Z$11,$F11,0) -> 0 | AG11: =IF($C11=$Z$12,$E11,0) -> 0 | AH11: =IF($C11=$Z$12,$F11,0) -> 0 | AI11: =IF($C11=$Z$13,$E11,0) -> 0 | AJ11: =IF($C11=$Z$13,$F11,0) -> 0 | AK11: =IF($C11=$Z$14,$E11,0) -> 0 | AL11: =IF($C11=$Z$14,$F11,0) -> 0 | AM11: =IF($C11=$Z$15,$E11,0) -> 0 | AN11: =IF($C11=$Z$15,$F11,0) -> 0 | AO11: =IF($C11=$Z$16,$E11,0) -> 0 | AP11: =IF($C11=$Z$16,$F11,0) -> 0 | AQ11: =IF($C11=$Z$17,$E11,0) -> 0 | AR11: =IF($C11=$Z$17,$F11,0) -> 0 | AT11: =IF(OR($G11=$AA$11,$G11=$AA$13,($G11=$AA$14),$G11=$AA$15),$AE11+$AG11+$AI11+$AK11+$AQ11,0) -> 0 | AU11: =IF(OR($G11=$AA$11,$G11=$AA$13,($G11=$AA$14),$G11=$AA$15),$AF11+$AH11+$AJ11+AL11+AR11,0) -> 0 | AV11: =IF($G11=$AA$12,$AE11+$AG11+$AI11+$AK11+$AQ11,0) -> 0 | AW11: =IF($G11=$AA$12,$AF11+$AH11+$AJ11+$AL11+$AR11,0) -> 0 | AY11: =IF(UPPER($I11) =$AB$12,IF($G11=$AA$12,$AV11,0),0) -> 0 | AZ11: =IF(UPPER($I11) =$AB$12,IF($G11<>$AA$12,$AT11,0),0) -> 0 | BA11: =IF(UPPER($I11) =$AB$12,IF($G11=$AA$12,$AW11,0),0) -> 0 | BB11: =IF(UPPER($I11) =$AB$12,IF($G11<>$AA$12,$AU11,0),0) -> 0 | BC11: =IF(UPPER($J11) =$AB$12,IF($G11=$AA$12,$AV11,0),0) -> 0 | BD11: =IF(UPPER($J11) =$AB$12,IF($G11<>$AA$12,$AT11,0),0) -> 0 | BE11: =IF(UPPER($J11) =$AB$12,IF($G11=$AA$12,$AW11,0),0) -> 0 | BF11: =IF(UPPER($J11) =$AB$12,IF($G11<>$AA$12,$AU11,0),0) -> 0 | BG11: =IF(UPPER($K11) =$AB$12,IF($G11=$AA$12,$AV11,0),0) -> 0 | BH11: =IF(UPPER($K11) =$AB$12,IF($G11<>$AA$12,$AT11,0),0) -> 0 | BI11: =IF(UPPER($K11) =$AB$12,IF($G11=$AA$12,$AW11,0),0) -> 0 | BJ11: =IF(UPPER($K11) =$AB$12,IF($G11<>$AA$12,$AU11,0),0) -> 0 | BL11: =IF(($E11+$F11>0), IF($G11=$AA$10,1,0),0) -> 0 | BM11: =IF(($E11+$F11<=0), IF($G11<>$AA$10,1,0),0) -> 0 | BN11: =IF(($E11+$F11>0), IF($C11=$AA$10,1,0),0) -> 0
A12: 2 | Z12: Varie | AA12: Contante | AB12: X | AE12: =IF($C12=$Z$11,$E12,0) -> 0 | AF12: =IF($C12=$Z$11,$F12,0) -> 0 | AG12: =IF($C12=$Z$12,$E12,0) -> 0 | AH12: =IF($C12=$Z$12,$F12,0) -> 0 | AI12: =IF($C12=$Z$13,$E12,0) -> 0 | AJ12: =IF($C12=$Z$13,$F12,0) -> 0 | AK12: =IF($C12=$Z$14,$E12,0) -> 0 | AL12: =IF($C12=$Z$14,$F12,0) -> 0 | AM12: =IF($C12=$Z$15,$E12,0) -> 0 | AN12: =IF($C12=$Z$15,$F12,0) -> 0 | AO12: =IF($C12=$Z$16,$E12,0) -> 0 | AP12: =IF($C12=$Z$16,$F12,0) -> 0 | AQ12: =IF($C12=$Z$17,$E12,0) -> 0 | AR12: =IF($C12=$Z$17,$F12,0) -> 0 | AT12: =IF(OR($G12=$AA$11,$G12=$AA$13,($G12=$AA$14),$G12=$AA$15),$AE12+$AG12+$AI12+$AK12+$AQ12,0) -> 0 | AU12: =IF(OR($G12=$AA$11,$G12=$AA$13,($G12=$AA$14),$G12=$AA$15),$AF12+$AH12+$AJ12+AL12+AR12,0) -> 0 | AV12: =IF($G12=$AA$12,$AE12+$AG12+$AI12+AK12+AQ12,0) -> 0 | AW12: =IF($G12=$AA$12,$AF12+$AH12+$AJ12+AL12+AR12,0) -> 0 | AY12: =IF(UPPER($I12) =$AB$12,IF($G12=$AA$12,$AV12,0),0) -> 0 | AZ12: =IF(UPPER($I12) =$AB$12,IF($G12<>$AA$12,$AT12,0),0) -> 0 | BA12: =IF(UPPER($I12) =$AB$12,IF($G12=$AA$12,$AW12,0),0) -> 0 | BB12: =IF(UPPER($I12) =$AB$12,IF($G12<>$AA$12,$AU12,0),0) -> 0 | BC12: =IF(UPPER($J12) =$AB$12,IF($G12=$AA$12,$AV12,0),0) -> 0 | BD12: =IF(UPPER($J12) =$AB$12,IF($G12<>$AA$12,$AT12,0),0) -> 0 | BE12: =IF(UPPER($J12) =$AB$12,IF($G12=$AA$12,$AW12,0),0) -> 0 | BF12: =IF(UPPER($J12) =$AB$12,IF($G12<>$AA$12,$AU12,0),0) -> 0 | BG12: =IF(UPPER($K12) =$AB$12,IF($G12=$AA$12,$AV12,0),0) -> 0 | BH12: =IF(UPPER($K12) =$AB$12,IF($G12<>$AA$12,$AT12,0),0) -> 0 | BI12: =IF(UPPER($K12) =$AB$12,IF($G12=$AA$12,$AW12,0),0) -> 0 | BJ12: =IF(UPPER($K12) =$AB$12,IF($G12<>$AA$12,$AU12,0),0) -> 0 | BL12: =IF(($E12+$F12>0), IF($G12=$AA$10,1,0),0) -> 0 | BM12: =IF(($E12+$F12<=0), IF($G12<>$AA$10,1,0),0) -> 0 | BN12: =IF(($E12+$F12>0), IF($C12=$AA$10,1,0),0) -> 0
A13: 3 | Z13: Spostamenti | AA13: CC-Visa | AE13: =IF($C13=$Z$11,$E13,0) -> 0 | AF13: =IF($C13=$Z$11,$F13,0) -> 0 | AG13: =IF($C13=$Z$12,$E13,0) -> 0 | AH13: =IF($C13=$Z$12,$F13,0) -> 0 | AI13: =IF($C13=$Z$13,$E13,0) -> 0 | AJ13: =IF($C13=$Z$13,$F13,0) -> 0 | AK13: =IF($C13=$Z$14,$E13,0) -> 0 | AL13: =IF($C13=$Z$14,$F13,0) -> 0 | AM13: =IF($C13=$Z$15,$E13,0) -> 0 | AN13: =IF($C13=$Z$15,$F13,0) -> 0 | AO13: =IF($C13=$Z$16,$E13,0) -> 0 | AP13: =IF($C13=$Z$16,$F13,0) -> 0 | AQ13: =IF($C13=$Z$17,$E13,0) -> 0 | AR13: =IF($C13=$Z$17,$F13,0) -> 0 | AT13: =IF(OR($G13=$AA$11,$G13=$AA$13,($G13=$AA$14),$G13=$AA$15),$AE13+$AG13+$AI13+$AK13+$AQ13,0) -> 0 | AU13: =IF(OR($G13=$AA$11,$G13=$AA$13,($G13=$AA$14),$G13=$AA$15),$AF13+$AH13+$AJ13+AL13+AR13,0) -> 0 | AV13: =IF($G13=$AA$12,$AE13+$AG13+$AI13+AK13+AQ13,0) -> 0 | AW13: =IF($G13=$AA$12,$AF13+$AH13+$AJ13+AL13+AR13,0) -> 0 | AY13: =IF(UPPER($I13) =$AB$12,IF($G13=$AA$12,$AV13,0),0) -> 0 | AZ13: =IF(UPPER($I13) =$AB$12,IF($G13<>$AA$12,$AT13,0),0) -> 0 | BA13: =IF(UPPER($I13) =$AB$12,IF($G13=$AA$12,$AW13,0),0) -> 0 | BB13: =IF(UPPER($I13) =$AB$12,IF($G13<>$AA$12,$AU13,0),0) -> 0 | BC13: =IF(UPPER($J13) =$AB$12,IF($G13=$AA$12,$AV13,0),0) -> 0 | BD13: =IF(UPPER($J13) =$AB$12,IF($G13<>$AA$12,$AT13,0),0) -> 0 | BE13: =IF(UPPER($J13) =$AB$12,IF($G13=$AA$12,$AW13,0),0) -> 0 | BF13: =IF(UPPER($J13) =$AB$12,IF($G13<>$AA$12,$AU13,0),0) -> 0 | BG13: =IF(UPPER($K13) =$AB$12,IF($G13=$AA$12,$AV13,0),0) -> 0 | BH13: =IF(UPPER($K13) =$AB$12,IF($G13<>$AA$12,$AT13,0),0) -> 0 | BI13: =IF(UPPER($K13) =$AB$12,IF($G13=$AA$12,$AW13,0),0) -> 0 | BJ13: =IF(UPPER($K13) =$AB$12,IF($G13<>$AA$12,$AU13,0),0) -> 0 | BL13: =IF(($E13+$F13>0), IF($G13=$AA$10,1,0),0) -> 0 | BM13: =IF(($E13+$F13<=0), IF($G13<>$AA$10,1,0),0) -> 0 | BN13: =IF(($E13+$F13>0), IF($C13=$AA$10,1,0),0) -> 0
A14: 4 | Z14: Carburante IT | AA14: CC-Master | AE14: =IF($C14=$Z$11,$E14,0) -> 0 | AF14: =IF($C14=$Z$11,$F14,0) -> 0 | AG14: =IF($C14=$Z$12,$E14,0) -> 0 | AH14: =IF($C14=$Z$12,$F14,0) -> 0 | AI14: =IF($C14=$Z$13,$E14,0) -> 0 | AJ14: =IF($C14=$Z$13,$F14,0) -> 0 | AK14: =IF($C14=$Z$14,$E14,0) -> 0 | AL14: =IF($C14=$Z$14,$F14,0) -> 0 | AM14: =IF($C14=$Z$15,$E14,0) -> 0 | AN14: =IF($C14=$Z$15,$F14,0) -> 0 | AO14: =IF($C14=$Z$16,$E14,0) -> 0 | AP14: =IF($C14=$Z$16,$F14,0) -> 0 | AQ14: =IF($C14=$Z$17,$E14,0) -> 0 | AR14: =IF($C14=$Z$17,$F14,0) -> 0 | AT14: =IF(OR($G14=$AA$11,$G14=$AA$13,($G14=$AA$14),$G14=$AA$15),$AE14+$AG14+$AI14+$AK14+$AQ14,0) -> 0 | AU14: =IF(OR($G14=$AA$11,$G14=$AA$13,($G14=$AA$14),$G14=$AA$15),$AF14+$AH14+$AJ14+AL14+AR14,0) -> 0 | AV14: =IF($G14=$AA$12,$AE14+$AG14+$AI14+AK14+AQ14,0) -> 0 | AW14: =IF($G14=$AA$12,$AF14+$AH14+$AJ14+AL14+AR14,0) -> 0 | AY14: =IF(UPPER($I14) =$AB$12,IF($G14=$AA$12,$AV14,0),0) -> 0 | AZ14: =IF(UPPER($I14) =$AB$12,IF($G14<>$AA$12,$AT14,0),0) -> 0 | BA14: =IF(UPPER($I14) =$AB$12,IF($G14=$AA$12,$AW14,0),0) -> 0 | BB14: =IF(UPPER($I14) =$AB$12,IF($G14<>$AA$12,$AU14,0),0) -> 0 | BC14: =IF(UPPER($J14) =$AB$12,IF($G14=$AA$12,$AV14,0),0) -> 0 | BD14: =IF(UPPER($J14) =$AB$12,IF($G14<>$AA$12,$AT14,0),0) -> 0 | BE14: =IF(UPPER($J14) =$AB$12,IF($G14=$AA$12,$AW14,0),0) -> 0 | BF14: =IF(UPPER($J14) =$AB$12,IF($G14<>$AA$12,$AU14,0),0) -> 0 | BG14: =IF(UPPER($K14) =$AB$12,IF($G14=$AA$12,$AV14,0),0) -> 0 | BH14: =IF(UPPER($K14) =$AB$12,IF($G14<>$AA$12,$AT14,0),0) -> 0 | BI14: =IF(UPPER($K14) =$AB$12,IF($G14=$AA$12,$AW14,0),0) -> 0 | BJ14: =IF(UPPER($K14) =$AB$12,IF($G14<>$AA$12,$AU14,0),0) -> 0 | BL14: =IF(($E14+$F14>0), IF($G14=$AA$10,1,0),0) -> 0 | BM14: =IF(($E14+$F14<=0), IF($G14<>$AA$10,1,0),0) -> 0 | BN14: =IF(($E14+$F14>0), IF($C14=$AA$10,1,0),0) -> 0
A15: 5 | Z15: Cambio € -> Valuta | AA15: DKV | AE15: =IF($C15=$Z$11,$E15,0) -> 0 | AF15: =IF($C15=$Z$11,$F15,0) -> 0 | AG15: =IF($C15=$Z$12,$E15,0) -> 0 | AH15: =IF($C15=$Z$12,$F15,0) -> 0 | AI15: =IF($C15=$Z$13,$E15,0) -> 0 | AJ15: =IF($C15=$Z$13,$F15,0) -> 0 | AK15: =IF($C15=$Z$14,$E15,0) -> 0 | AL15: =IF($C15=$Z$14,$F15,0) -> 0 | AM15: =IF($C15=$Z$15,$E15,0) -> 0 | AN15: =IF($C15=$Z$15,$F15,0) -> 0 | AO15: =IF($C15=$Z$16,$E15,0) -> 0 | AP15: =IF($C15=$Z$16,$F15,0) -> 0 | AQ15: =IF($C15=$Z$17,$E15,0) -> 0 | AR15: =IF($C15=$Z$17,$F15,0) -> 0 | AT15: =IF(OR($G15=$AA$11,$G15=$AA$13,($G15=$AA$14),$G15=$AA$15),$AE15+$AG15+$AI15+$AK15+$AQ15,0) -> 0 | AU15: =IF(OR($G15=$AA$11,$G15=$AA$13,($G15=$AA$14),$G15=$AA$15),$AF15+$AH15+$AJ15+AL15+AR15,0) -> 0 | AV15: =IF($G15=$AA$12,$AE15+$AG15+$AI15+AK15+AQ15,0) -> 0 | AW15: =IF($G15=$AA$12,$AF15+$AH15+$AJ15+AL15+AR15,0) -> 0 | AY15: =IF(UPPER($I15) =$AB$12,IF($G15=$AA$12,$AV15,0),0) -> 0 | AZ15: =IF(UPPER($I15) =$AB$12,IF($G15<>$AA$12,$AT15,0),0) -> 0 | BA15: =IF(UPPER($I15) =$AB$12,IF($G15=$AA$12,$AW15,0),0) -> 0 | BB15: =IF(UPPER($I15) =$AB$12,IF($G15<>$AA$12,$AU15,0),0) -> 0 | BC15: =IF(UPPER($J15) =$AB$12,IF($G15=$AA$12,$AV15,0),0) -> 0 | BD15: =IF(UPPER($J15) =$AB$12,IF($G15<>$AA$12,$AT15,0),0) -> 0 | BE15: =IF(UPPER($J15) =$AB$12,IF($G15=$AA$12,$AW15,0),0) -> 0 | BF15: =IF(UPPER($J15) =$AB$12,IF($G15<>$AA$12,$AU15,0),0) -> 0 | BG15: =IF(UPPER($K15) =$AB$12,IF($G15=$AA$12,$AV15,0),0) -> 0 | BH15: =IF(UPPER($K15) =$AB$12,IF($G15<>$AA$12,$AT15,0),0) -> 0 | BI15: =IF(UPPER($K15) =$AB$12,IF($G15=$AA$12,$AW15,0),0) -> 0 | BJ15: =IF(UPPER($K15) =$AB$12,IF($G15<>$AA$12,$AU15,0),0) -> 0 | BL15: =IF(($E15+$F15>0), IF($G15=$AA$10,1,0),0) -> 0 | BM15: =IF(($E15+$F15<=0), IF($G15<>$AA$10,1,0),0) -> 0 | BN15: =IF(($E15+$F15>0), IF($C15=$AA$10,1,0),0) -> 0
A16: 6 | Z16: Cambio Valuta -> € | AE16: =IF($C16=$Z$11,$E16,0) -> 0 | AF16: =IF($C16=$Z$11,$F16,0) -> 0 | AG16: =IF($C16=$Z$12,$E16,0) -> 0 | AH16: =IF($C16=$Z$12,$F16,0) -> 0 | AI16: =IF($C16=$Z$13,$E16,0) -> 0 | AJ16: =IF($C16=$Z$13,$F16,0) -> 0 | AK16: =IF($C16=$Z$14,$E16,0) -> 0 | AL16: =IF($C16=$Z$14,$F16,0) -> 0 | AM16: =IF($C16=$Z$15,$E16,0) -> 0 | AN16: =IF($C16=$Z$15,$F16,0) -> 0 | AO16: =IF($C16=$Z$16,$E16,0) -> 0 | AP16: =IF($C16=$Z$16,$F16,0) -> 0 | AQ16: =IF($C16=$Z$17,$E16,0) -> 0 | AR16: =IF($C16=$Z$17,$F16,0) -> 0 | AT16: =IF(OR($G16=$AA$11,$G16=$AA$13,($G16=$AA$14),$G16=$AA$15),$AE16+$AG16+$AI16+$AK16+$AQ16,0) -> 0 | AU16: =IF(OR($G16=$AA$11,$G16=$AA$13,($G16=$AA$14),$G16=$AA$15),$AF16+$AH16+$AJ16+AL16+AR16,0) -> 0 | AV16: =IF($G16=$AA$12,$AE16+$AG16+$AI16+AK16+AQ16,0) -> 0 | AW16: =IF($G16=$AA$12,$AF16+$AH16+$AJ16+AL16+AR16,0) -> 0 | AY16: =IF(UPPER($I16) =$AB$12,IF($G16=$AA$12,$AV16,0),0) -> 0 | AZ16: =IF(UPPER($I16) =$AB$12,IF($G16<>$AA$12,$AT16,0),0) -> 0 | BA16: =IF(UPPER($I16) =$AB$12,IF($G16=$AA$12,$AW16,0),0) -> 0 | BB16: =IF(UPPER($I16) =$AB$12,IF($G16<>$AA$12,$AU16,0),0) -> 0 | BC16: =IF(UPPER($J16) =$AB$12,IF($G16=$AA$12,$AV16,0),0) -> 0 | BD16: =IF(UPPER($J16) =$AB$12,IF($G16<>$AA$12,$AT16,0),0) -> 0 | BE16: =IF(UPPER($J16) =$AB$12,IF($G16=$AA$12,$AW16,0),0) -> 0 | BF16: =IF(UPPER($J16) =$AB$12,IF($G16<>$AA$12,$AU16,0),0) -> 0 | BG16: =IF(UPPER($K16) =$AB$12,IF($G16=$AA$12,$AV16,0),0) -> 0 | BH16: =IF(UPPER($K16) =$AB$12,IF($G16<>$AA$12,$AT16,0),0) -> 0 | BI16: =IF(UPPER($K16) =$AB$12,IF($G16=$AA$12,$AW16,0),0) -> 0 | BJ16: =IF(UPPER($K16) =$AB$12,IF($G16<>$AA$12,$AU16,0),0) -> 0 | BL16: =IF(($E16+$F16>0), IF($G16=$AA$10,1,0),0) -> 0 | BM16: =IF(($E16+$F16<=0), IF($G16<>$AA$10,1,0),0) -> 0 | BN16: =IF(($E16+$F16>0), IF($C16=$AA$10,1,0),0) -> 0
A17: 7 | Z17: Prelievo Contante | AE17: =IF($C17=$Z$11,$E17,0) -> 0 | AF17: =IF($C17=$Z$11,$F17,0) -> 0 | AG17: =IF($C17=$Z$12,$E17,0) -> 0 | AH17: =IF($C17=$Z$12,$F17,0) -> 0 | AI17: =IF($C17=$Z$13,$E17,0) -> 0 | AJ17: =IF($C17=$Z$13,$F17,0) -> 0 | AK17: =IF($C17=$Z$14,$E17,0) -> 0 | AL17: =IF($C17=$Z$14,$F17,0) -> 0 | AM17: =IF($C17=$Z$15,$E17,0) -> 0 | AN17: =IF($C17=$Z$15,$F17,0) -> 0 | AO17: =IF($C17=$Z$16,$E17,0) -> 0 | AP17: =IF($C17=$Z$16,$F17,0) -> 0 | AQ17: =IF($C17=$Z$17,$E17,0) -> 0 | AR17: =IF($C17=$Z$17,$F17,0) -> 0 | AT17: =IF(OR($G17=$AA$11,$G17=$AA$13,($G17=$AA$14),$G17=$AA$15),$AE17+$AG17+$AI17+$AK17+$AQ17,0) -> 0 | AU17: =IF(OR($G17=$AA$11,$G17=$AA$13,($G17=$AA$14),$G17=$AA$15),$AF17+$AH17+$AJ17+AL17+AR17,0) -> 0 | AV17: =IF($G17=$AA$12,$AE17+$AG17+$AI17+AK17+AQ17,0) -> 0 | AW17: =IF($G17=$AA$12,$AF17+$AH17+$AJ17+AL17+AR17,0) -> 0 | AY17: =IF(UPPER($I17) =$AB$12,IF($G17=$AA$12,$AV17,0),0) -> 0 | AZ17: =IF(UPPER($I17) =$AB$12,IF($G17<>$AA$12,$AT17,0),0) -> 0 | BA17: =IF(UPPER($I17) =$AB$12,IF($G17=$AA$12,$AW17,0),0) -> 0 | BB17: =IF(UPPER($I17) =$AB$12,IF($G17<>$AA$12,$AU17,0),0) -> 0 | BC17: =IF(UPPER($J17) =$AB$12,IF($G17=$AA$12,$AV17,0),0) -> 0 | BD17: =IF(UPPER($J17) =$AB$12,IF($G17<>$AA$12,$AT17,0),0) -> 0 | BE17: =IF(UPPER($J17) =$AB$12,IF($G17=$AA$12,$AW17,0),0) -> 0 | BF17: =IF(UPPER($J17) =$AB$12,IF($G17<>$AA$12,$AU17,0),0) -> 0 | BG17: =IF(UPPER($K17) =$AB$12,IF($G17=$AA$12,$AV17,0),0) -> 0 | BH17: =IF(UPPER($K17) =$AB$12,IF($G17<>$AA$12,$AT17,0),0) -> 0 | BI17: =IF(UPPER($K17) =$AB$12,IF($G17=$AA$12,$AW17,0),0) -> 0 | BJ17: =IF(UPPER($K17) =$AB$12,IF($G17<>$AA$12,$AU17,0),0) -> 0 | BL17: =IF(($E17+$F17>0), IF($G17=$AA$10,1,0),0) -> 0 | BM17: =IF(($E17+$F17<=0), IF($G17<>$AA$10,1,0),0) -> 0 | BN17: =IF(($E17+$F17>0), IF($C17=$AA$10,1,0),0) -> 0
A18: 8 | AE18: =IF($C18=$Z$11,$E18,0) -> 0 | AF18: =IF($C18=$Z$11,$F18,0) -> 0 | AG18: =IF($C18=$Z$12,$E18,0) -> 0 | AH18: =IF($C18=$Z$12,$F18,0) -> 0 | AI18: =IF($C18=$Z$13,$E18,0) -> 0 | AJ18: =IF($C18=$Z$13,$F18,0) -> 0 | AK18: =IF($C18=$Z$14,$E18,0) -> 0 | AL18: =IF($C18=$Z$14,$F18,0) -> 0 | AM18: =IF($C18=$Z$15,$E18,0) -> 0 | AN18: =IF($C18=$Z$15,$F18,0) -> 0 | AO18: =IF($C18=$Z$16,$E18,0) -> 0 | AP18: =IF($C18=$Z$16,$F18,0) -> 0 | AQ18: =IF($C18=$Z$17,$E18,0) -> 0 | AR18: =IF($C18=$Z$17,$F18,0) -> 0 | AT18: =IF(OR($G18=$AA$11,$G18=$AA$13,($G18=$AA$14),$G18=$AA$15),$AE18+$AG18+$AI18+$AK18+$AQ18,0) -> 0 | AU18: =IF(OR($G18=$AA$11,$G18=$AA$13,($G18=$AA$14),$G18=$AA$15),$AF18+$AH18+$AJ18+AL18+AR18,0) -> 0 | AV18: =IF($G18=$AA$12,$AE18+$AG18+$AI18+AK18+AQ18,0) -> 0 | AW18: =IF($G18=$AA$12,$AF18+$AH18+$AJ18+AL18+AR18,0) -> 0 | AY18: =IF(UPPER($I18) =$AB$12,IF($G18=$AA$12,$AV18,0),0) -> 0 | AZ18: =IF(UPPER($I18) =$AB$12,IF($G18<>$AA$12,$AT18,0),0) -> 0 | BA18: =IF(UPPER($I18) =$AB$12,IF($G18=$AA$12,$AW18,0),0) -> 0 | BB18: =IF(UPPER($I18) =$AB$12,IF($G18<>$AA$12,$AU18,0),0) -> 0 | BC18: =IF(UPPER($J18) =$AB$12,IF($G18=$AA$12,$AV18,0),0) -> 0 | BD18: =IF(UPPER($J18) =$AB$12,IF($G18<>$AA$12,$AT18,0),0) -> 0 | BE18: =IF(UPPER($J18) =$AB$12,IF($G18=$AA$12,$AW18,0),0) -> 0 | BF18: =IF(UPPER($J18) =$AB$12,IF($G18<>$AA$12,$AU18,0),0) -> 0 | BG18: =IF(UPPER($K18) =$AB$12,IF($G18=$AA$12,$AV18,0),0) -> 0 | BH18: =IF(UPPER($K18) =$AB$12,IF($G18<>$AA$12,$AT18,0),0) -> 0 | BI18: =IF(UPPER($K18) =$AB$12,IF($G18=$AA$12,$AW18,0),0) -> 0 | BJ18: =IF(UPPER($K18) =$AB$12,IF($G18<>$AA$12,$AU18,0),0) -> 0 | BL18: =IF(($E18+$F18>0), IF($G18=$AA$10,1,0),0) -> 0 | BM18: =IF(($E18+$F18<=0), IF($G18<>$AA$10,1,0),0) -> 0 | BN18: =IF(($E18+$F18>0), IF($C18=$AA$10,1,0),0) -> 0
A19: 9 | AE19: =IF($C19=$Z$11,$E19,0) -> 0 | AF19: =IF($C19=$Z$11,$F19,0) -> 0 | AG19: =IF($C19=$Z$12,$E19,0) -> 0 | AH19: =IF($C19=$Z$12,$F19,0) -> 0 | AI19: =IF($C19=$Z$13,$E19,0) -> 0 | AJ19: =IF($C19=$Z$13,$F19,0) -> 0 | AK19: =IF($C19=$Z$14,$E19,0) -> 0 | AL19: =IF($C19=$Z$14,$F19,0) -> 0 | AM19: =IF($C19=$Z$15,$E19,0) -> 0 | AN19: =IF($C19=$Z$15,$F19,0) -> 0 | AO19: =IF($C19=$Z$16,$E19,0) -> 0 | AP19: =IF($C19=$Z$16,$F19,0) -> 0 | AQ19: =IF($C19=$Z$17,$E19,0) -> 0 | AR19: =IF($C19=$Z$17,$F19,0) -> 0 | AT19: =IF(OR($G19=$AA$11,$G19=$AA$13,($G19=$AA$14),$G19=$AA$15),$AE19+$AG19+$AI19+$AK19+$AQ19,0) -> 0 | AU19: =IF(OR($G19=$AA$11,$G19=$AA$13,($G19=$AA$14),$G19=$AA$15),$AF19+$AH19+$AJ19+AL19+AR19,0) -> 0 | AV19: =IF($G19=$AA$12,$AE19+$AG19+$AI19+AK19+AQ19,0) -> 0 | AW19: =IF($G19=$AA$12,$AF19+$AH19+$AJ19+AL19+AR19,0) -> 0 | AY19: =IF(UPPER($I19) =$AB$12,IF($G19=$AA$12,$AV19,0),0) -> 0 | AZ19: =IF(UPPER($I19) =$AB$12,IF($G19<>$AA$12,$AT19,0),0) -> 0 | BA19: =IF(UPPER($I19) =$AB$12,IF($G19=$AA$12,$AW19,0),0) -> 0 | BB19: =IF(UPPER($I19) =$AB$12,IF($G19<>$AA$12,$AU19,0),0) -> 0 | BC19: =IF(UPPER($J19) =$AB$12,IF($G19=$AA$12,$AV19,0),0) -> 0 | BD19: =IF(UPPER($J19) =$AB$12,IF($G19<>$AA$12,$AT19,0),0) -> 0 | BE19: =IF(UPPER($J19) =$AB$12,IF($G19=$AA$12,$AW19,0),0) -> 0 | BF19: =IF(UPPER($J19) =$AB$12,IF($G19<>$AA$12,$AU19,0),0) -> 0 | BG19: =IF(UPPER($K19) =$AB$12,IF($G19=$AA$12,$AV19,0),0) -> 0 | BH19: =IF(UPPER($K19) =$AB$12,IF($G19<>$AA$12,$AT19,0),0) -> 0 | BI19: =IF(UPPER($K19) =$AB$12,IF($G19=$AA$12,$AW19,0),0) -> 0 | BJ19: =IF(UPPER($K19) =$AB$12,IF($G19<>$AA$12,$AU19,0),0) -> 0 | BL19: =IF(($E19+$F19>0), IF($G19=$AA$10,1,0),0) -> 0 | BM19: =IF(($E19+$F19<=0), IF($G19<>$AA$10,1,0),0) -> 0 | BN19: =IF(($E19+$F19>0), IF($C19=$AA$10,1,0),0) -> 0
A20: 10 | AE20: =IF($C20=$Z$11,$E20,0) -> 0 | AF20: =IF($C20=$Z$11,$F20,0) -> 0 | AG20: =IF($C20=$Z$12,$E20,0) -> 0 | AH20: =IF($C20=$Z$12,$F20,0) -> 0 | AI20: =IF($C20=$Z$13,$E20,0) -> 0 | AJ20: =IF($C20=$Z$13,$F20,0) -> 0 | AK20: =IF($C20=$Z$14,$E20,0) -> 0 | AL20: =IF($C20=$Z$14,$F20,0) -> 0 | AM20: =IF($C20=$Z$15,$E20,0) -> 0 | AN20: =IF($C20=$Z$15,$F20,0) -> 0 | AO20: =IF($C20=$Z$16,$E20,0) -> 0 | AP20: =IF($C20=$Z$16,$F20,0) -> 0 | AQ20: =IF($C20=$Z$17,$E20,0) -> 0 | AR20: =IF($C20=$Z$17,$F20,0) -> 0 | AT20: =IF(OR($G20=$AA$11,$G20=$AA$13,($G20=$AA$14),$G20=$AA$15),$AE20+$AG20+$AI20+$AK20+$AQ20,0) -> 0 | AU20: =IF(OR($G20=$AA$11,$G20=$AA$13,($G20=$AA$14),$G20=$AA$15),$AF20+$AH20+$AJ20+AL20+AR20,0) -> 0 | AV20: =IF($G20=$AA$12,$AE20+$AG20+$AI20+AK20+AQ20,0) -> 0 | AW20: =IF($G20=$AA$12,$AF20+$AH20+$AJ20+AL20+AR20,0) -> 0 | AY20: =IF(UPPER($I20) =$AB$12,IF($G20=$AA$12,$AV20,0),0) -> 0 | AZ20: =IF(UPPER($I20) =$AB$12,IF($G20<>$AA$12,$AT20,0),0) -> 0 | BA20: =IF(UPPER($I20) =$AB$12,IF($G20=$AA$12,$AW20,0),0) -> 0 | BB20: =IF(UPPER($I20) =$AB$12,IF($G20<>$AA$12,$AU20,0),0) -> 0 | BC20: =IF(UPPER($J20) =$AB$12,IF($G20=$AA$12,$AV20,0),0) -> 0 | BD20: =IF(UPPER($J20) =$AB$12,IF($G20<>$AA$12,$AT20,0),0) -> 0 | BE20: =IF(UPPER($J20) =$AB$12,IF($G20=$AA$12,$AW20,0),0) -> 0 | BF20: =IF(UPPER($J20) =$AB$12,IF($G20<>$AA$12,$AU20,0),0) -> 0 | BG20: =IF(UPPER($K20) =$AB$12,IF($G20=$AA$12,$AV20,0),0) -> 0 | BH20: =IF(UPPER($K20) =$AB$12,IF($G20<>$AA$12,$AT20,0),0) -> 0 | BI20: =IF(UPPER($K20) =$AB$12,IF($G20=$AA$12,$AW20,0),0) -> 0 | BJ20: =IF(UPPER($K20) =$AB$12,IF($G20<>$AA$12,$AU20,0),0) -> 0 | BL20: =IF(($E20+$F20>0), IF($G20=$AA$10,1,0),0) -> 0 | BM20: =IF(($E20+$F20<=0), IF($G20<>$AA$10,1,0),0) -> 0 | BN20: =IF(($E20+$F20>0), IF($C20=$AA$10,1,0),0) -> 0
A21: 11 | AE21: =IF($C21=$Z$11,$E21,0) -> 0 | AF21: =IF($C21=$Z$11,$F21,0) -> 0 | AG21: =IF($C21=$Z$12,$E21,0) -> 0 | AH21: =IF($C21=$Z$12,$F21,0) -> 0 | AI21: =IF($C21=$Z$13,$E21,0) -> 0 | AJ21: =IF($C21=$Z$13,$F21,0) -> 0 | AK21: =IF($C21=$Z$14,$E21,0) -> 0 | AL21: =IF($C21=$Z$14,$F21,0) -> 0 | AM21: =IF($C21=$Z$15,$E21,0) -> 0 | AN21: =IF($C21=$Z$15,$F21,0) -> 0 | AO21: =IF($C21=$Z$16,$E21,0) -> 0 | AP21: =IF($C21=$Z$16,$F21,0) -> 0 | AQ21: =IF($C21=$Z$17,$E21,0) -> 0 | AR21: =IF($C21=$Z$17,$F21,0) -> 0 | AT21: =IF(OR($G21=$AA$11,$G21=$AA$13,($G21=$AA$14),$G21=$AA$15),$AE21+$AG21+$AI21+$AK21+$AQ21,0) -> 0 | AU21: =IF(OR($G21=$AA$11,$G21=$AA$13,($G21=$AA$14),$G21=$AA$15),$AF21+$AH21+$AJ21+AL21+AR21,0) -> 0 | AV21: =IF($G21=$AA$12,$AE21+$AG21+$AI21+AK21+AQ21,0) -> 0 | AW21: =IF($G21=$AA$12,$AF21+$AH21+$AJ21+AL21+AR21,0) -> 0 | AY21: =IF(UPPER($I21) =$AB$12,IF($G21=$AA$12,$AV21,0),0) -> 0 | AZ21: =IF(UPPER($I21) =$AB$12,IF($G21<>$AA$12,$AT21,0),0) -> 0 | BA21: =IF(UPPER($I21) =$AB$12,IF($G21=$AA$12,$AW21,0),0) -> 0 | BB21: =IF(UPPER($I21) =$AB$12,IF($G21<>$AA$12,$AU21,0),0) -> 0 | BC21: =IF(UPPER($J21) =$AB$12,IF($G21=$AA$12,$AV21,0),0) -> 0 | BD21: =IF(UPPER($J21) =$AB$12,IF($G21<>$AA$12,$AT21,0),0) -> 0 | BE21: =IF(UPPER($J21) =$AB$12,IF($G21=$AA$12,$AW21,0),0) -> 0 | BF21: =IF(UPPER($J21) =$AB$12,IF($G21<>$AA$12,$AU21,0),0) -> 0 | BG21: =IF(UPPER($K21) =$AB$12,IF($G21=$AA$12,$AV21,0),0) -> 0 | BH21: =IF(UPPER($K21) =$AB$12,IF($G21<>$AA$12,$AT21,0),0) -> 0 | BI21: =IF(UPPER($K21) =$AB$12,IF($G21=$AA$12,$AW21,0),0) -> 0 | BJ21: =IF(UPPER($K21) =$AB$12,IF($G21<>$AA$12,$AU21,0),0) -> 0 | BL21: =IF(($E21+$F21>0), IF($G21=$AA$10,1,0),0) -> 0 | BM21: =IF(($E21+$F21<=0), IF($G21<>$AA$10,1,0),0) -> 0 | BN21: =IF(($E21+$F21>0), IF($C21=$AA$10,1,0),0) -> 0
A22: 12 | AE22: =IF($C22=$Z$11,$E22,0) -> 0 | AF22: =IF($C22=$Z$11,$F22,0) -> 0 | AG22: =IF($C22=$Z$12,$E22,0) -> 0 | AH22: =IF($C22=$Z$12,$F22,0) -> 0 | AI22: =IF($C22=$Z$13,$E22,0) -> 0 | AJ22: =IF($C22=$Z$13,$F22,0) -> 0 | AK22: =IF($C22=$Z$14,$E22,0) -> 0 | AL22: =IF($C22=$Z$14,$F22,0) -> 0 | AM22: =IF($C22=$Z$15,$E22,0) -> 0 | AN22: =IF($C22=$Z$15,$F22,0) -> 0 | AO22: =IF($C22=$Z$16,$E22,0) -> 0 | AP22: =IF($C22=$Z$16,$F22,0) -> 0 | AQ22: =IF($C22=$Z$17,$E22,0) -> 0 | AR22: =IF($C22=$Z$17,$F22,0) -> 0 | AT22: =IF(OR($G22=$AA$11,$G22=$AA$13,($G22=$AA$14),$G22=$AA$15),$AE22+$AG22+$AI22+$AK22+$AQ22,0) -> 0 | AU22: =IF(OR($G22=$AA$11,$G22=$AA$13,($G22=$AA$14),$G22=$AA$15),$AF22+$AH22+$AJ22+AL22+AR22,0) -> 0 | AV22: =IF($G22=$AA$12,$AE22+$AG22+$AI22+AK22+AQ22,0) -> 0 | AW22: =IF($G22=$AA$12,$AF22+$AH22+$AJ22+AL22+AR22,0) -> 0 | AY22: =IF(UPPER($I22) =$AB$12,IF($G22=$AA$12,$AV22,0),0) -> 0 | AZ22: =IF(UPPER($I22) =$AB$12,IF($G22<>$AA$12,$AT22,0),0) -> 0 | BA22: =IF(UPPER($I22) =$AB$12,IF($G22=$AA$12,$AW22,0),0) -> 0 | BB22: =IF(UPPER($I22) =$AB$12,IF($G22<>$AA$12,$AU22,0),0) -> 0 | BC22: =IF(UPPER($J22) =$AB$12,IF($G22=$AA$12,$AV22,0),0) -> 0 | BD22: =IF(UPPER($J22) =$AB$12,IF($G22<>$AA$12,$AT22,0),0) -> 0 | BE22: =IF(UPPER($J22) =$AB$12,IF($G22=$AA$12,$AW22,0),0) -> 0 | BF22: =IF(UPPER($J22) =$AB$12,IF($G22<>$AA$12,$AU22,0),0) -> 0 | BG22: =IF(UPPER($K22) =$AB$12,IF($G22=$AA$12,$AV22,0),0) -> 0 | BH22: =IF(UPPER($K22) =$AB$12,IF($G22<>$AA$12,$AT22,0),0) -> 0 | BI22: =IF(UPPER($K22) =$AB$12,IF($G22=$AA$12,$AW22,0),0) -> 0 | BJ22: =IF(UPPER($K22) =$AB$12,IF($G22<>$AA$12,$AU22,0),0) -> 0 | BL22: =IF(($E22+$F22>0), IF($G22=$AA$10,1,0),0) -> 0 | BM22: =IF(($E22+$F22<=0), IF($G22<>$AA$10,1,0),0) -> 0 | BN22: =IF(($E22+$F22>0), IF($C22=$AA$10,1,0),0) -> 0
A23: 13 | AE23: =IF($C23=$Z$11,$E23,0) -> 0 | AF23: =IF($C23=$Z$11,$F23,0) -> 0 | AG23: =IF($C23=$Z$12,$E23,0) -> 0 | AH23: =IF($C23=$Z$12,$F23,0) -> 0 | AI23: =IF($C23=$Z$13,$E23,0) -> 0 | AJ23: =IF($C23=$Z$13,$F23,0) -> 0 | AK23: =IF($C23=$Z$14,$E23,0) -> 0 | AL23: =IF($C23=$Z$14,$F23,0) -> 0 | AM23: =IF($C23=$Z$15,$E23,0) -> 0 | AN23: =IF($C23=$Z$15,$F23,0) -> 0 | AO23: =IF($C23=$Z$16,$E23,0) -> 0 | AP23: =IF($C23=$Z$16,$F23,0) -> 0 | AQ23: =IF($C23=$Z$17,$E23,0) -> 0 | AR23: =IF($C23=$Z$17,$F23,0) -> 0 | AT23: =IF(OR($G23=$AA$11,$G23=$AA$13,($G23=$AA$14),$G23=$AA$15),$AE23+$AG23+$AI23+$AK23+$AQ23,0) -> 0 | AU23: =IF(OR($G23=$AA$11,$G23=$AA$13,($G23=$AA$14),$G23=$AA$15),$AF23+$AH23+$AJ23+AL23+AR23,0) -> 0 | AV23: =IF($G23=$AA$12,$AE23+$AG23+$AI23+AK23+AQ23,0) -> 0 | AW23: =IF($G23=$AA$12,$AF23+$AH23+$AJ23+AL23+AR23,0) -> 0 | AY23: =IF(UPPER($I23) =$AB$12,IF($G23=$AA$12,$AV23,0),0) -> 0 | AZ23: =IF(UPPER($I23) =$AB$12,IF($G23<>$AA$12,$AT23,0),0) -> 0 | BA23: =IF(UPPER($I23) =$AB$12,IF($G23=$AA$12,$AW23,0),0) -> 0 | BB23: =IF(UPPER($I23) =$AB$12,IF($G23<>$AA$12,$AU23,0),0) -> 0 | BC23: =IF(UPPER($J23) =$AB$12,IF($G23=$AA$12,$AV23,0),0) -> 0 | BD23: =IF(UPPER($J23) =$AB$12,IF($G23<>$AA$12,$AT23,0),0) -> 0 | BE23: =IF(UPPER($J23) =$AB$12,IF($G23=$AA$12,$AW23,0),0) -> 0 | BF23: =IF(UPPER($J23) =$AB$12,IF($G23<>$AA$12,$AU23,0),0) -> 0 | BG23: =IF(UPPER($K23) =$AB$12,IF($G23=$AA$12,$AV23,0),0) -> 0 | BH23: =IF(UPPER($K23) =$AB$12,IF($G23<>$AA$12,$AT23,0),0) -> 0 | BI23: =IF(UPPER($K23) =$AB$12,IF($G23=$AA$12,$AW23,0),0) -> 0 | BJ23: =IF(UPPER($K23) =$AB$12,IF($G23<>$AA$12,$AU23,0),0) -> 0 | BL23: =IF(($E23+$F23>0), IF($G23=$AA$10,1,0),0) -> 0 | BM23: =IF(($E23+$F23<=0), IF($G23<>$AA$10,1,0),0) -> 0 | BN23: =IF(($E23+$F23>0), IF($C23=$AA$10,1,0),0) -> 0
A24: 14 | AE24: =IF($C24=$Z$11,$E24,0) -> 0 | AF24: =IF($C24=$Z$11,$F24,0) -> 0 | AG24: =IF($C24=$Z$12,$E24,0) -> 0 | AH24: =IF($C24=$Z$12,$F24,0) -> 0 | AI24: =IF($C24=$Z$13,$E24,0) -> 0 | AJ24: =IF($C24=$Z$13,$F24,0) -> 0 | AK24: =IF($C24=$Z$14,$E24,0) -> 0 | AL24: =IF($C24=$Z$14,$F24,0) -> 0 | AM24: =IF($C24=$Z$15,$E24,0) -> 0 | AN24: =IF($C24=$Z$15,$F24,0) -> 0 | AO24: =IF($C24=$Z$16,$E24,0) -> 0 | AP24: =IF($C24=$Z$16,$F24,0) -> 0 | AQ24: =IF($C24=$Z$17,$E24,0) -> 0 | AR24: =IF($C24=$Z$17,$F24,0) -> 0 | AT24: =IF(OR($G24=$AA$11,$G24=$AA$13,($G24=$AA$14),$G24=$AA$15),$AE24+$AG24+$AI24+$AK24+$AQ24,0) -> 0 | AU24: =IF(OR($G24=$AA$11,$G24=$AA$13,($G24=$AA$14),$G24=$AA$15),$AF24+$AH24+$AJ24+AL24+AR24,0) -> 0 | AV24: =IF($G24=$AA$12,$AE24+$AG24+$AI24+AK24+AQ24,0) -> 0 | AW24: =IF($G24=$AA$12,$AF24+$AH24+$AJ24+AL24+AR24,0) -> 0 | AY24: =IF(UPPER($I24) =$AB$12,IF($G24=$AA$12,$AV24,0),0) -> 0 | AZ24: =IF(UPPER($I24) =$AB$12,IF($G24<>$AA$12,$AT24,0),0) -> 0 | BA24: =IF(UPPER($I24) =$AB$12,IF($G24=$AA$12,$AW24,0),0) -> 0 | BB24: =IF(UPPER($I24) =$AB$12,IF($G24<>$AA$12,$AU24,0),0) -> 0 | BC24: =IF(UPPER($J24) =$AB$12,IF($G24=$AA$12,$AV24,0),0) -> 0 | BD24: =IF(UPPER($J24) =$AB$12,IF($G24<>$AA$12,$AT24,0),0) -> 0 | BE24: =IF(UPPER($J24) =$AB$12,IF($G24=$AA$12,$AW24,0),0) -> 0 | BF24: =IF(UPPER($J24) =$AB$12,IF($G24<>$AA$12,$AU24,0),0) -> 0 | BG24: =IF(UPPER($K24) =$AB$12,IF($G24=$AA$12,$AV24,0),0) -> 0 | BH24: =IF(UPPER($K24) =$AB$12,IF($G24<>$AA$12,$AT24,0),0) -> 0 | BI24: =IF(UPPER($K24) =$AB$12,IF($G24=$AA$12,$AW24,0),0) -> 0 | BJ24: =IF(UPPER($K24) =$AB$12,IF($G24<>$AA$12,$AU24,0),0) -> 0 | BL24: =IF(($E24+$F24>0), IF($G24=$AA$10,1,0),0) -> 0 | BM24: =IF(($E24+$F24<=0), IF($G24<>$AA$10,1,0),0) -> 0 | BN24: =IF(($E24+$F24>0), IF($C24=$AA$10,1,0),0) -> 0
A25: 15 | AE25: =IF($C25=$Z$11,$E25,0) -> 0 | AF25: =IF($C25=$Z$11,$F25,0) -> 0 | AG25: =IF($C25=$Z$12,$E25,0) -> 0 | AH25: =IF($C25=$Z$12,$F25,0) -> 0 | AI25: =IF($C25=$Z$13,$E25,0) -> 0 | AJ25: =IF($C25=$Z$13,$F25,0) -> 0 | AK25: =IF($C25=$Z$14,$E25,0) -> 0 | AL25: =IF($C25=$Z$14,$F25,0) -> 0 | AM25: =IF($C25=$Z$15,$E25,0) -> 0 | AN25: =IF($C25=$Z$15,$F25,0) -> 0 | AO25: =IF($C25=$Z$16,$E25,0) -> 0 | AP25: =IF($C25=$Z$16,$F25,0) -> 0 | AQ25: =IF($C25=$Z$17,$E25,0) -> 0 | AR25: =IF($C25=$Z$17,$F25,0) -> 0 | AT25: =IF(OR($G25=$AA$11,$G25=$AA$13,($G25=$AA$14),$G25=$AA$15),$AE25+$AG25+$AI25+$AK25+$AQ25,0) -> 0 | AU25: =IF(OR($G25=$AA$11,$G25=$AA$13,($G25=$AA$14),$G25=$AA$15),$AF25+$AH25+$AJ25+AL25+AR25,0) -> 0 | AV25: =IF($G25=$AA$12,$AE25+$AG25+$AI25+AK25+AQ25,0) -> 0 | AW25: =IF($G25=$AA$12,$AF25+$AH25+$AJ25+AL25+AR25,0) -> 0 | AY25: =IF(UPPER($I25) =$AB$12,IF($G25=$AA$12,$AV25,0),0) -> 0 | AZ25: =IF(UPPER($I25) =$AB$12,IF($G25<>$AA$12,$AT25,0),0) -> 0 | BA25: =IF(UPPER($I25) =$AB$12,IF($G25=$AA$12,$AW25,0),0) -> 0 | BB25: =IF(UPPER($I25) =$AB$12,IF($G25<>$AA$12,$AU25,0),0) -> 0 | BC25: =IF(UPPER($J25) =$AB$12,IF($G25=$AA$12,$AV25,0),0) -> 0 | BD25: =IF(UPPER($J25) =$AB$12,IF($G25<>$AA$12,$AT25,0),0) -> 0 | BE25: =IF(UPPER($J25) =$AB$12,IF($G25=$AA$12,$AW25,0),0) -> 0 | BF25: =IF(UPPER($J25) =$AB$12,IF($G25<>$AA$12,$AU25,0),0) -> 0 | BG25: =IF(UPPER($K25) =$AB$12,IF($G25=$AA$12,$AV25,0),0) -> 0 | BH25: =IF(UPPER($K25) =$AB$12,IF($G25<>$AA$12,$AT25,0),0) -> 0 | BI25: =IF(UPPER($K25) =$AB$12,IF($G25=$AA$12,$AW25,0),0) -> 0 | BJ25: =IF(UPPER($K25) =$AB$12,IF($G25<>$AA$12,$AU25,0),0) -> 0 | BL25: =IF(($E25+$F25>0), IF($G25=$AA$10,1,0),0) -> 0 | BM25: =IF(($E25+$F25<=0), IF($G25<>$AA$10,1,0),0) -> 0 | BN25: =IF(($E25+$F25>0), IF($C25=$AA$10,1,0),0) -> 0
A26: 16 | AE26: =IF($C26=$Z$11,$E26,0) -> 0 | AF26: =IF($C26=$Z$11,$F26,0) -> 0 | AG26: =IF($C26=$Z$12,$E26,0) -> 0 | AH26: =IF($C26=$Z$12,$F26,0) -> 0 | AI26: =IF($C26=$Z$13,$E26,0) -> 0 | AJ26: =IF($C26=$Z$13,$F26,0) -> 0 | AK26: =IF($C26=$Z$14,$E26,0) -> 0 | AL26: =IF($C26=$Z$14,$F26,0) -> 0 | AM26: =IF($C26=$Z$15,$E26,0) -> 0 | AN26: =IF($C26=$Z$15,$F26,0) -> 0 | AO26: =IF($C26=$Z$16,$E26,0) -> 0 | AP26: =IF($C26=$Z$16,$F26,0) -> 0 | AQ26: =IF($C26=$Z$17,$E26,0) -> 0 | AR26: =IF($C26=$Z$17,$F26,0) -> 0 | AT26: =IF(OR($G26=$AA$11,$G26=$AA$13,($G26=$AA$14),$G26=$AA$15),$AE26+$AG26+$AI26+$AK26+$AQ26,0) -> 0 | AU26: =IF(OR($G26=$AA$11,$G26=$AA$13,($G26=$AA$14),$G26=$AA$15),$AF26+$AH26+$AJ26+AL26+AR26,0) -> 0 | AV26: =IF($G26=$AA$12,$AE26+$AG26+$AI26+AK26+AQ26,0) -> 0 | AW26: =IF($G26=$AA$12,$AF26+$AH26+$AJ26+AL26+AR26,0) -> 0 | AY26: =IF(UPPER($I26) =$AB$12,IF($G26=$AA$12,$AV26,0),0) -> 0 | AZ26: =IF(UPPER($I26) =$AB$12,IF($G26<>$AA$12,$AT26,0),0) -> 0 | BA26: =IF(UPPER($I26) =$AB$12,IF($G26=$AA$12,$AW26,0),0) -> 0 | BB26: =IF(UPPER($I26) =$AB$12,IF($G26<>$AA$12,$AU26,0),0) -> 0 | BC26: =IF(UPPER($J26) =$AB$12,IF($G26=$AA$12,$AV26,0),0) -> 0 | BD26: =IF(UPPER($J26) =$AB$12,IF($G26<>$AA$12,$AT26,0),0) -> 0 | BE26: =IF(UPPER($J26) =$AB$12,IF($G26=$AA$12,$AW26,0),0) -> 0 | BF26: =IF(UPPER($J26) =$AB$12,IF($G26<>$AA$12,$AU26,0),0) -> 0 | BG26: =IF(UPPER($K26) =$AB$12,IF($G26=$AA$12,$AV26,0),0) -> 0 | BH26: =IF(UPPER($K26) =$AB$12,IF($G26<>$AA$12,$AT26,0),0) -> 0 | BI26: =IF(UPPER($K26) =$AB$12,IF($G26=$AA$12,$AW26,0),0) -> 0 | BJ26: =IF(UPPER($K26) =$AB$12,IF($G26<>$AA$12,$AU26,0),0) -> 0 | BL26: =IF(($E26+$F26>0), IF($G26=$AA$10,1,0),0) -> 0 | BM26: =IF(($E26+$F26<=0), IF($G26<>$AA$10,1,0),0) -> 0 | BN26: =IF(($E26+$F26>0), IF($C26=$AA$10,1,0),0) -> 0
A27: 17 | AE27: =IF($C27=$Z$11,$E27,0) -> 0 | AF27: =IF($C27=$Z$11,$F27,0) -> 0 | AG27: =IF($C27=$Z$12,$E27,0) -> 0 | AH27: =IF($C27=$Z$12,$F27,0) -> 0 | AI27: =IF($C27=$Z$13,$E27,0) -> 0 | AJ27: =IF($C27=$Z$13,$F27,0) -> 0 | AK27: =IF($C27=$Z$14,$E27,0) -> 0 | AL27: =IF($C27=$Z$14,$F27,0) -> 0 | AM27: =IF($C27=$Z$15,$E27,0) -> 0 | AN27: =IF($C27=$Z$15,$F27,0) -> 0 | AO27: =IF($C27=$Z$16,$E27,0) -> 0 | AP27: =IF($C27=$Z$16,$F27,0) -> 0 | AQ27: =IF($C27=$Z$17,$E27,0) -> 0 | AR27: =IF($C27=$Z$17,$F27,0) -> 0 | AT27: =IF(OR($G27=$AA$11,$G27=$AA$13,($G27=$AA$14),$G27=$AA$15),$AE27+$AG27+$AI27+$AK27+$AQ27,0) -> 0 | AU27: =IF(OR($G27=$AA$11,$G27=$AA$13,($G27=$AA$14),$G27=$AA$15),$AF27+$AH27+$AJ27+AL27+AR27,0) -> 0 | AV27: =IF($G27=$AA$12,$AE27+$AG27+$AI27+AK27+AQ27,0) -> 0 | AW27: =IF($G27=$AA$12,$AF27+$AH27+$AJ27+AL27+AR27,0) -> 0 | AY27: =IF(UPPER($I27) =$AB$12,IF($G27=$AA$12,$AV27,0),0) -> 0 | AZ27: =IF(UPPER($I27) =$AB$12,IF($G27<>$AA$12,$AT27,0),0) -> 0 | BA27: =IF(UPPER($I27) =$AB$12,IF($G27=$AA$12,$AW27,0),0) -> 0 | BB27: =IF(UPPER($I27) =$AB$12,IF($G27<>$AA$12,$AU27,0),0) -> 0 | BC27: =IF(UPPER($J27) =$AB$12,IF($G27=$AA$12,$AV27,0),0) -> 0 | BD27: =IF(UPPER($J27) =$AB$12,IF($G27<>$AA$12,$AT27,0),0) -> 0 | BE27: =IF(UPPER($J27) =$AB$12,IF($G27=$AA$12,$AW27,0),0) -> 0 | BF27: =IF(UPPER($J27) =$AB$12,IF($G27<>$AA$12,$AU27,0),0) -> 0 | BG27: =IF(UPPER($K27) =$AB$12,IF($G27=$AA$12,$AV27,0),0) -> 0 | BH27: =IF(UPPER($K27) =$AB$12,IF($G27<>$AA$12,$AT27,0),0) -> 0 | BI27: =IF(UPPER($K27) =$AB$12,IF($G27=$AA$12,$AW27,0),0) -> 0 | BJ27: =IF(UPPER($K27) =$AB$12,IF($G27<>$AA$12,$AU27,0),0) -> 0 | BL27: =IF(($E27+$F27>0), IF($G27=$AA$10,1,0),0) -> 0 | BM27: =IF(($E27+$F27<=0), IF($G27<>$AA$10,1,0),0) -> 0 | BN27: =IF(($E27+$F27>0), IF($C27=$AA$10,1,0),0) -> 0
A28: 18 | AE28: =IF($C28=$Z$11,$E28,0) -> 0 | AF28: =IF($C28=$Z$11,$F28,0) -> 0 | AG28: =IF($C28=$Z$12,$E28,0) -> 0 | AH28: =IF($C28=$Z$12,$F28,0) -> 0 | AI28: =IF($C28=$Z$13,$E28,0) -> 0 | AJ28: =IF($C28=$Z$13,$F28,0) -> 0 | AK28: =IF($C28=$Z$14,$E28,0) -> 0 | AL28: =IF($C28=$Z$14,$F28,0) -> 0 | AM28: =IF($C28=$Z$15,$E28,0) -> 0 | AN28: =IF($C28=$Z$15,$F28,0) -> 0 | AO28: =IF($C28=$Z$16,$E28,0) -> 0 | AP28: =IF($C28=$Z$16,$F28,0) -> 0 | AQ28: =IF($C28=$Z$17,$E28,0) -> 0 | AR28: =IF($C28=$Z$17,$F28,0) -> 0 | AT28: =IF(OR($G28=$AA$11,$G28=$AA$13,($G28=$AA$14),$G28=$AA$15),$AE28+$AG28+$AI28+$AK28+$AQ28,0) -> 0 | AU28: =IF(OR($G28=$AA$11,$G28=$AA$13,($G28=$AA$14),$G28=$AA$15),$AF28+$AH28+$AJ28+AL28+AR28,0) -> 0 | AV28: =IF($G28=$AA$12,$AE28+$AG28+$AI28+AK28+AQ28,0) -> 0 | AW28: =IF($G28=$AA$12,$AF28+$AH28+$AJ28+AL28+AR28,0) -> 0 | AY28: =IF(UPPER($I28) =$AB$12,IF($G28=$AA$12,$AV28,0),0) -> 0 | AZ28: =IF(UPPER($I28) =$AB$12,IF($G28<>$AA$12,$AT28,0),0) -> 0 | BA28: =IF(UPPER($I28) =$AB$12,IF($G28=$AA$12,$AW28,0),0) -> 0 | BB28: =IF(UPPER($I28) =$AB$12,IF($G28<>$AA$12,$AU28,0),0) -> 0 | BC28: =IF(UPPER($J28) =$AB$12,IF($G28=$AA$12,$AV28,0),0) -> 0 | BD28: =IF(UPPER($J28) =$AB$12,IF($G28<>$AA$12,$AT28,0),0) -> 0 | BE28: =IF(UPPER($J28) =$AB$12,IF($G28=$AA$12,$AW28,0),0) -> 0 | BF28: =IF(UPPER($J28) =$AB$12,IF($G28<>$AA$12,$AU28,0),0) -> 0 | BG28: =IF(UPPER($K28) =$AB$12,IF($G28=$AA$12,$AV28,0),0) -> 0 | BH28: =IF(UPPER($K28) =$AB$12,IF($G28<>$AA$12,$AT28,0),0) -> 0 | BI28: =IF(UPPER($K28) =$AB$12,IF($G28=$AA$12,$AW28,0),0) -> 0 | BJ28: =IF(UPPER($K28) =$AB$12,IF($G28<>$AA$12,$AU28,0),0) -> 0 | BL28: =IF(($E28+$F28>0), IF($G28=$AA$10,1,0),0) -> 0 | BM28: =IF(($E28+$F28<=0), IF($G28<>$AA$10,1,0),0) -> 0 | BN28: =IF(($E28+$F28>0), IF($C28=$AA$10,1,0),0) -> 0
A29: 19 | AE29: =IF($C29=$Z$11,$E29,0) -> 0 | AF29: =IF($C29=$Z$11,$F29,0) -> 0 | AG29: =IF($C29=$Z$12,$E29,0) -> 0 | AH29: =IF($C29=$Z$12,$F29,0) -> 0 | AI29: =IF($C29=$Z$13,$E29,0) -> 0 | AJ29: =IF($C29=$Z$13,$F29,0) -> 0 | AK29: =IF($C29=$Z$14,$E29,0) -> 0 | AL29: =IF($C29=$Z$14,$F29,0) -> 0 | AM29: =IF($C29=$Z$15,$E29,0) -> 0 | AN29: =IF($C29=$Z$15,$F29,0) -> 0 | AO29: =IF($C29=$Z$16,$E29,0) -> 0 | AP29: =IF($C29=$Z$16,$F29,0) -> 0 | AQ29: =IF($C29=$Z$17,$E29,0) -> 0 | AR29: =IF($C29=$Z$17,$F29,0) -> 0 | AT29: =IF(OR($G29=$AA$11,$G29=$AA$13,($G29=$AA$14),$G29=$AA$15),$AE29+$AG29+$AI29+$AK29+$AQ29,0) -> 0 | AU29: =IF(OR($G29=$AA$11,$G29=$AA$13,($G29=$AA$14),$G29=$AA$15),$AF29+$AH29+$AJ29+AL29+AR29,0) -> 0 | AV29: =IF($G29=$AA$12,$AE29+$AG29+$AI29+AK29+AQ29,0) -> 0 | AW29: =IF($G29=$AA$12,$AF29+$AH29+$AJ29+AL29+AR29,0) -> 0 | AY29: =IF(UPPER($I29) =$AB$12,IF($G29=$AA$12,$AV29,0),0) -> 0 | AZ29: =IF(UPPER($I29) =$AB$12,IF($G29<>$AA$12,$AT29,0),0) -> 0 | BA29: =IF(UPPER($I29) =$AB$12,IF($G29=$AA$12,$AW29,0),0) -> 0 | BB29: =IF(UPPER($I29) =$AB$12,IF($G29<>$AA$12,$AU29,0),0) -> 0 | BC29: =IF(UPPER($J29) =$AB$12,IF($G29=$AA$12,$AV29,0),0) -> 0 | BD29: =IF(UPPER($J29) =$AB$12,IF($G29<>$AA$12,$AT29,0),0) -> 0 | BE29: =IF(UPPER($J29) =$AB$12,IF($G29=$AA$12,$AW29,0),0) -> 0 | BF29: =IF(UPPER($J29) =$AB$12,IF($G29<>$AA$12,$AU29,0),0) -> 0 | BG29: =IF(UPPER($K29) =$AB$12,IF($G29=$AA$12,$AV29,0),0) -> 0 | BH29: =IF(UPPER($K29) =$AB$12,IF($G29<>$AA$12,$AT29,0),0) -> 0 | BI29: =IF(UPPER($K29) =$AB$12,IF($G29=$AA$12,$AW29,0),0) -> 0 | BJ29: =IF(UPPER($K29) =$AB$12,IF($G29<>$AA$12,$AU29,0),0) -> 0 | BL29: =IF(($E29+$F29>0), IF($G29=$AA$10,1,0),0) -> 0 | BM29: =IF(($E29+$F29<=0), IF($G29<>$AA$10,1,0),0) -> 0 | BN29: =IF(($E29+$F29>0), IF($C29=$AA$10,1,0),0) -> 0
... A34: 24 | AE34: =IF($C34=$Z$11,$E34,0) -> 0 | AF34: =IF($C34=$Z$11,$F34,0) -> 0 | AG34: =IF($C34=$Z$12,$E34,0) -> 0 | AH34: =IF($C34=$Z$12,$F34,0) -> 0 | AI34: =IF($C34=$Z$13,$E34,0) -> 0 | AJ34: =IF($C34=$Z$13,$F34,0) -> 0 | AK34: =IF($C34=$Z$14,$E34,0) -> 0 | AL34: =IF($C34=$Z$14,$F34,0) -> 0 | AM34: =IF($C34=$Z$15,$E34,0) -> 0 | AN34: =IF($C34=$Z$15,$F34,0) -> 0 | AO34: =IF($C34=$Z$16,$E34,0) -> 0 | AP34: =IF($C34=$Z$16,$F34,0) -> 0 | AQ34: =IF($C34=$Z$17,$E34,0) -> 0 | AR34: =IF($C34=$Z$17,$F34,0) -> 0 | AT34: =IF(OR($G34=$AA$11,$G34=$AA$13,($G34=$AA$14),$G34=$AA$15),$AE34+$AG34+$AI34+$AK34+$AQ34,0) -> 0 | AU34: =IF(OR($G34=$AA$11,$G34=$AA$13,($G34=$AA$14),$G34=$AA$15),$AF34+$AH34+$AJ34+AL34+AR34,0) -> 0 | AV34: =IF($G34=$AA$12,$AE34+$AG34+$AI34+AK34+AQ34,0) -> 0 | AW34: =IF($G34=$AA$12,$AF34+$AH34+$AJ34+AL34+AR34,0) -> 0 | AY34: =IF(UPPER($I34) =$AB$12,IF($G34=$AA$12,$AV34,0),0) -> 0 | AZ34: =IF(UPPER($I34) =$AB$12,IF($G34<>$AA$12,$AT34,0),0) -> 0 | BA34: =IF(UPPER($I34) =$AB$12,IF($G34=$AA$12,$AW34,0),0) -> 0 | BB34: =IF(UPPER($I34) =$AB$12,IF($G34<>$AA$12,$AU34,0),0) -> 0 | BC34: =IF(UPPER($J34) =$AB$12,IF($G34=$AA$12,$AV34,0),0) -> 0 | BD34: =IF(UPPER($J34) =$AB$12,IF($G34<>$AA$12,$AT34,0),0) -> 0 | BE34: =IF(UPPER($J34) =$AB$12,IF($G34=$AA$12,$AW34,0),0) -> 0 | BF34: =IF(UPPER($J34) =$AB$12,IF($G34<>$AA$12,$AU34,0),0) -> 0 | BG34: =IF(UPPER($K34) =$AB$12,IF($G34=$AA$12,$AV34,0),0) -> 0 | BH34: =IF(UPPER($K34) =$AB$12,IF($G34<>$AA$12,$AT34,0),0) -> 0 | BI34: =IF(UPPER($K34) =$AB$12,IF($G34=$AA$12,$AW34,0),0) -> 0 | BJ34: =IF(UPPER($K34) =$AB$12,IF($G34<>$AA$12,$AU34,0),0) -> 0 | BL34: =IF(($E34+$F34>0), IF($G34=$AA$10,1,0),0) -> 0 | BM34: =IF(($E34+$F34<=0), IF($G34<>$AA$10,1,0),0) -> 0 | BN34: =IF(($E34+$F34>0), IF($C34=$AA$10,1,0),0) -> 0
AE35: =IF($C35=$Z$11,$E35,0) -> 0 | AF35: =IF($C35=$Z$11,$F35,0) -> 0 | AG35: =IF($C35=$Z$12,$E35,0) -> 0 | AH35: =IF($C35=$Z$12,$F35,0) -> 0 | AI35: =IF($C35=$Z$13,$E35,0) -> 0 | AJ35: =IF($C35=$Z$13,$F35,0) -> 0 | AK35: =IF($C35=$Z$14,$E35,0) -> 0 | AL35: =IF($C35=$Z$14,$F35,0) -> 0 | AM35: =IF($C35=$Z$15,$E35,0) -> 0 | AN35: =IF($C35=$Z$15,$F35,0) -> 0 | AO35: =IF($C35=$Z$16,$E35,0) -> 0 | AP35: =IF($C35=$Z$16,$F35,0) -> 0 | AQ35: =IF($C35=$Z$17,$E35,0) -> 0 | AR35: =IF($C35=$Z$17,$F35,0) -> 0 | AT35: =IF(OR($G35=$AA$11,$G35=$AA$13,($G35=$AA$14),$G35=$AA$15),$AE35+$AG35+$AI35+$AK35+$AQ35,0) -> 0 | AU35: =IF(OR($G35=$AA$11,$G35=$AA$13,($G35=$AA$14),$G35=$AA$15),$AF35+$AH35+$AJ35+AL35+AR35,0) -> 0 | AV35: =IF($G35=$AA$12,$AE35+$AG35+$AI35+AK35+AQ35,0) -> 0 | AW35: =IF($G35=$AA$12,$AF35+$AH35+$AJ35+AL35+AR35,0) -> 0 | AY35: =IF(UPPER($I35) =$AB$12,IF($G35=$AA$12,$AV35,0),0) -> 0 | AZ35: =IF(UPPER($I35) =$AB$12,IF($G35<>$AA$12,$AT35,0),0) -> 0 | BA35: =IF(UPPER($I35) =$AB$12,IF($G35=$AA$12,$AW35,0),0) -> 0 | BB35: =IF(UPPER($I35) =$AB$12,IF($G35<>$AA$12,$AU35,0),0) -> 0 | BC35: =IF(UPPER($J35) =$AB$12,IF($G35=$AA$12,$AV35,0),0) -> 0 | BD35: =IF(UPPER($J35) =$AB$12,IF($G35<>$AA$12,$AT35,0),0) -> 0 | BE35: =IF(UPPER($J35) =$AB$12,IF($G35=$AA$12,$AW35,0),0) -> 0 | BF35: =IF(UPPER($J35) =$AB$12,IF($G35<>$AA$12,$AU35,0),0) -> 0 | BG35: =IF(UPPER($K35) =$AB$12,IF($G35=$AA$12,$AV35,0),0) -> 0 | BH35: =IF(UPPER($K35) =$AB$12,IF($G35<>$AA$12,$AT35,0),0) -> 0 | BI35: =IF(UPPER($K35) =$AB$12,IF($G35=$AA$12,$AW35,0),0) -> 0 | BJ35: =IF(UPPER($K35) =$AB$12,IF($G35<>$AA$12,$AU35,0),0) -> 0 | BL35: =IF(($E35+$F35>0), IF($G35=$AA$10,1,0),0) -> 0 | BM35: =IF(($E35+$F35<=0), IF($G35<>$AA$10,1,0),0) -> 0 | BN35: =IF(($E35+$F35>0), IF($C35=$AA$10,1,0),0) -> 0
A36: 25 | L36: PAGINA 2
A37: 26 | AE37: =IF($C37=$Z$11,$E37,0) -> 0 | AF37: =IF($C37=$Z$11,$F37,0) -> 0 | AG37: =IF($C37=$Z$12,$E37,0) -> 0 | AH37: =IF($C37=$Z$12,$F37,0) -> 0 | AI37: =IF($C37=$Z$13,$E37,0) -> 0 | AJ37: =IF($C37=$Z$13,$F37,0) -> 0 | AK37: =IF($C37=$Z$14,$E37,0) -> 0 | AL37: =IF($C37=$Z$14,$F37,0) -> 0 | AM37: =IF($C37=$Z$15,$E37,0) -> 0 | AN37: =IF($C37=$Z$15,$F37,0) -> 0 | AO37: =IF($C37=$Z$16,$E37,0) -> 0 | AP37: =IF($C37=$Z$16,$F37,0) -> 0 | AQ37: =IF($C37=$Z$17,$E37,0) -> 0 | AR37: =IF($C37=$Z$17,$F37,0) -> 0 | AT37: =IF(OR($G37=$AA$11,$G37=$AA$13,($G37=$AA$14),$G37=$AA$15),$AE37+$AG37+$AI37+$AK37+$AQ37,0) -> 0 | AU37: =IF(OR($G37=$AA$11,$G37=$AA$13,($G37=$AA$14),$G37=$AA$15),$AF37+$AH37+$AJ37+AL37+AR37,0) -> 0 | AV37: =IF($G37=$AA$12,$AE37+$AG37+$AI37+AK37+AQ37,0) -> 0 | AW37: =IF($G37=$AA$12,$AF37+$AH37+$AJ37+AL37+AR37,0) -> 0 | AY37: =IF(UPPER($I37) =$AB$12,IF($G37=$AA$12,$AV37,0),0) -> 0 | AZ37: =IF(UPPER($I37) =$AB$12,IF($G37<>$AA$12,$AT37,0),0) -> 0 | BA37: =IF(UPPER($I37) =$AB$12,IF($G37=$AA$12,$AW37,0),0) -> 0 | BB37: =IF(UPPER($I37) =$AB$12,IF($G37<>$AA$12,$AU37,0),0) -> 0 | BC37: =IF(UPPER($J37) =$AB$12,IF($G37=$AA$12,$AV37,0),0) -> 0 | BD37: =IF(UPPER($J37) =$AB$12,IF($G37<>$AA$12,$AT37,0),0) -> 0 | BE37: =IF(UPPER($J37) =$AB$12,IF($G37=$AA$12,$AW37,0),0) -> 0 | BF37: =IF(UPPER($J37) =$AB$12,IF($G37<>$AA$12,$AU37,0),0) -> 0 | BG37: =IF(UPPER($K37) =$AB$12,IF($G37=$AA$12,$AV37,0),0) -> 0 | BH37: =IF(UPPER($K37) =$AB$12,IF($G37<>$AA$12,$AT37,0),0) -> 0 | BI37: =IF(UPPER($K37) =$AB$12,IF($G37=$AA$12,$AW37,0),0) -> 0 | BJ37: =IF(UPPER($K37) =$AB$12,IF($G37<>$AA$12,$AU37,0),0) -> 0 | BL37: =IF(($E37+$F37>0), IF($G37=$AA$10,1,0),0) -> 0 | BM37: =IF(($E37+$F37<=0), IF($G37<>$AA$10,1,0),0) -> 0 | BN37: =IF(($E37+$F37>0), IF($C37=$AA$10,1,0),0) -> 0
A38: 27 | AE38: =IF($C38=$Z$11,$E38,0) -> 0 | AF38: =IF($C38=$Z$11,$F38,0) -> 0 | AG38: =IF($C38=$Z$12,$E38,0) -> 0 | AH38: =IF($C38=$Z$12,$F38,0) -> 0 | AI38: =IF($C38=$Z$13,$E38,0) -> 0 | AJ38: =IF($C38=$Z$13,$F38,0) -> 0 | AK38: =IF($C38=$Z$14,$E38,0) -> 0 | AL38: =IF($C38=$Z$14,$F38,0) -> 0 | AM38: =IF($C38=$Z$15,$E38,0) -> 0 | AN38: =IF($C38=$Z$15,$F38,0) -> 0 | AO38: =IF($C38=$Z$16,$E38,0) -> 0 | AP38: =IF($C38=$Z$16,$F38,0) -> 0 | AQ38: =IF($C38=$Z$17,$E38,0) -> 0 | AR38: =IF($C38=$Z$17,$F38,0) -> 0 | AT38: =IF(OR($G38=$AA$11,$G38=$AA$13,($G38=$AA$14),$G38=$AA$15),$AE38+$AG38+$AI38+$AK38+$AQ38,0) -> 0 | AU38: =IF(OR($G38=$AA$11,$G38=$AA$13,($G38=$AA$14),$G38=$AA$15),$AF38+$AH38+$AJ38+AL38+AR38,0) -> 0 | AV38: =IF($G38=$AA$12,$AE38+$AG38+$AI38+AK38+AQ38,0) -> 0 | AW38: =IF($G38=$AA$12,$AF38+$AH38+$AJ38+AL38+AR38,0) -> 0 | AY38: =IF(UPPER($I38) =$AB$12,IF($G38=$AA$12,$AV38,0),0) -> 0 | AZ38: =IF(UPPER($I38) =$AB$12,IF($G38<>$AA$12,$AT38,0),0) -> 0 | BA38: =IF(UPPER($I38) =$AB$12,IF($G38=$AA$12,$AW38,0),0) -> 0 | BB38: =IF(UPPER($I38) =$AB$12,IF($G38<>$AA$12,$AU38,0),0) -> 0 | BC38: =IF(UPPER($J38) =$AB$12,IF($G38=$AA$12,$AV38,0),0) -> 0 | BD38: =IF(UPPER($J38) =$AB$12,IF($G38<>$AA$12,$AT38,0),0) -> 0 | BE38: =IF(UPPER($J38) =$AB$12,IF($G38=$AA$12,$AW38,0),0) -> 0 | BF38: =IF(UPPER($J38) =$AB$12,IF($G38<>$AA$12,$AU38,0),0) -> 0 | BG38: =IF(UPPER($K38) =$AB$12,IF($G38=$AA$12,$AV38,0),0) -> 0 | BH38: =IF(UPPER($K38) =$AB$12,IF($G38<>$AA$12,$AT38,0),0) -> 0 | BI38: =IF(UPPER($K38) =$AB$12,IF($G38=$AA$12,$AW38,0),0) -> 0 | BJ38: =IF(UPPER($K38) =$AB$12,IF($G38<>$AA$12,$AU38,0),0) -> 0 | BL38: =IF(($E38+$F38>0), IF($G38=$AA$10,1,0),0) -> 0 | BM38: =IF(($E38+$F38<=0), IF($G38<>$AA$10,1,0),0) -> 0 | BN38: =IF(($E38+$F38>0), IF($C38=$AA$10,1,0),0) -> 0
A39: 28 | AE39: =IF($C39=$Z$11,$E39,0) -> 0 | AF39: =IF($C39=$Z$11,$F39,0) -> 0 | AG39: =IF($C39=$Z$12,$E39,0) -> 0 | AH39: =IF($C39=$Z$12,$F39,0) -> 0 | AI39: =IF($C39=$Z$13,$E39,0) -> 0 | AJ39: =IF($C39=$Z$13,$F39,0) -> 0 | AK39: =IF($C39=$Z$14,$E39,0) -> 0 | AL39: =IF($C39=$Z$14,$F39,0) -> 0 | AM39: =IF($C39=$Z$15,$E39,0) -> 0 | AN39: =IF($C39=$Z$15,$F39,0) -> 0 | AO39: =IF($C39=$Z$16,$E39,0) -> 0 | AP39: =IF($C39=$Z$16,$F39,0) -> 0 | AQ39: =IF($C39=$Z$17,$E39,0) -> 0 | AR39: =IF($C39=$Z$17,$F39,0) -> 0 | AT39: =IF(OR($G39=$AA$11,$G39=$AA$13,($G39=$AA$14),$G39=$AA$15),$AE39+$AG39+$AI39+$AK39+$AQ39,0) -> 0 | AU39: =IF(OR($G39=$AA$11,$G39=$AA$13,($G39=$AA$14),$G39=$AA$15),$AF39+$AH39+$AJ39+AL39+AR39,0) -> 0 | AV39: =IF($G39=$AA$12,$AE39+$AG39+$AI39+AK39+AQ39,0) -> 0 | AW39: =IF($G39=$AA$12,$AF39+$AH39+$AJ39+AL39+AR39,0) -> 0 | AY39: =IF(UPPER($I39) =$AB$12,IF($G39=$AA$12,$AV39,0),0) -> 0 | AZ39: =IF(UPPER($I39) =$AB$12,IF($G39<>$AA$12,$AT39,0),0) -> 0 | BA39: =IF(UPPER($I39) =$AB$12,IF($G39=$AA$12,$AW39,0),0) -> 0 | BB39: =IF(UPPER($I39) =$AB$12,IF($G39<>$AA$12,$AU39,0),0) -> 0 | BC39: =IF(UPPER($J39) =$AB$12,IF($G39=$AA$12,$AV39,0),0) -> 0 | BD39: =IF(UPPER($J39) =$AB$12,IF($G39<>$AA$12,$AT39,0),0) -> 0 | BE39: =IF(UPPER($J39) =$AB$12,IF($G39=$AA$12,$AW39,0),0) -> 0 | BF39: =IF(UPPER($J39) =$AB$12,IF($G39<>$AA$12,$AU39,0),0) -> 0 | BG39: =IF(UPPER($K39) =$AB$12,IF($G39=$AA$12,$AV39,0),0) -> 0 | BH39: =IF(UPPER($K39) =$AB$12,IF($G39<>$AA$12,$AT39,0),0) -> 0 | BI39: =IF(UPPER($K39) =$AB$12,IF($G39=$AA$12,$AW39,0),0) -> 0 | BJ39: =IF(UPPER($K39) =$AB$12,IF($G39<>$AA$12,$AU39,0),0) -> 0 | BL39: =IF(($E39+$F39>0), IF($G39=$AA$10,1,0),0) -> 0 | BM39: =IF(($E39+$F39<=0), IF($G39<>$AA$10,1,0),0) -> 0 | BN39: =IF(($E39+$F39>0), IF($C39=$AA$10,1,0),0) -> 0
A40: 29 | AE40: =IF($C40=$Z$11,$E40,0) -> 0 | AF40: =IF($C40=$Z$11,$F40,0) -> 0 | AG40: =IF($C40=$Z$12,$E40,0) -> 0 | AH40: =IF($C40=$Z$12,$F40,0) -> 0 | AI40: =IF($C40=$Z$13,$E40,0) -> 0 | AJ40: =IF($C40=$Z$13,$F40,0) -> 0 | AK40: =IF($C40=$Z$14,$E40,0) -> 0 | AL40: =IF($C40=$Z$14,$F40,0) -> 0 | AM40: =IF($C40=$Z$15,$E40,0) -> 0 | AN40: =IF($C40=$Z$15,$F40,0) -> 0 | AO40: =IF($C40=$Z$16,$E40,0) -> 0 | AP40: =IF($C40=$Z$16,$F40,0) -> 0 | AQ40: =IF($C40=$Z$17,$E40,0) -> 0 | AR40: =IF($C40=$Z$17,$F40,0) -> 0 | AT40: =IF(OR($G40=$AA$11,$G40=$AA$13,($G40=$AA$14),$G40=$AA$15),$AE40+$AG40+$AI40+$AK40+$AQ40,0) -> 0 | AU40: =IF(OR($G40=$AA$11,$G40=$AA$13,($G40=$AA$14),$G40=$AA$15),$AF40+$AH40+$AJ40+AL40+AR40,0) -> 0 | AV40: =IF($G40=$AA$12,$AE40+$AG40+$AI40+AK40+AQ40,0) -> 0 | AW40: =IF($G40=$AA$12,$AF40+$AH40+$AJ40+AL40+AR40,0) -> 0 | AY40: =IF(UPPER($I40) =$AB$12,IF($G40=$AA$12,$AV40,0),0) -> 0 | AZ40: =IF(UPPER($I40) =$AB$12,IF($G40<>$AA$12,$AT40,0),0) -> 0 | BA40: =IF(UPPER($I40) =$AB$12,IF($G40=$AA$12,$AW40,0),0) -> 0 | BB40: =IF(UPPER($I40) =$AB$12,IF($G40<>$AA$12,$AU40,0),0) -> 0 | BC40: =IF(UPPER($J40) =$AB$12,IF($G40=$AA$12,$AV40,0),0) -> 0 | BD40: =IF(UPPER($J40) =$AB$12,IF($G40<>$AA$12,$AT40,0),0) -> 0 | BE40: =IF(UPPER($J40) =$AB$12,IF($G40=$AA$12,$AW40,0),0) -> 0 | BF40: =IF(UPPER($J40) =$AB$12,IF($G40<>$AA$12,$AU40,0),0) -> 0 | BG40: =IF(UPPER($K40) =$AB$12,IF($G40=$AA$12,$AV40,0),0) -> 0 | BH40: =IF(UPPER($K40) =$AB$12,IF($G40<>$AA$12,$AT40,0),0) -> 0 | BI40: =IF(UPPER($K40) =$AB$12,IF($G40=$AA$12,$AW40,0),0) -> 0 | BJ40: =IF(UPPER($K40) =$AB$12,IF($G40<>$AA$12,$AU40,0),0) -> 0 | BL40: =IF(($E40+$F40>0), IF($G40=$AA$10,1,0),0) -> 0 | BM40: =IF(($E40+$F40<=0), IF($G40<>$AA$10,1,0),0) -> 0 | BN40: =IF(($E40+$F40>0), IF($C40=$AA$10,1,0),0) -> 0
A41: 30 | AE41: =IF($C41=$Z$11,$E41,0) -> 0 | AF41: =IF($C41=$Z$11,$F41,0) -> 0 | AG41: =IF($C41=$Z$12,$E41,0) -> 0 | AH41: =IF($C41=$Z$12,$F41,0) -> 0 | AI41: =IF($C41=$Z$13,$E41,0) -> 0 | AJ41: =IF($C41=$Z$13,$F41,0) -> 0 | AK41: =IF($C41=$Z$14,$E41,0) -> 0 | AL41: =IF($C41=$Z$14,$F41,0) -> 0 | AM41: =IF($C41=$Z$15,$E41,0) -> 0 | AN41: =IF($C41=$Z$15,$F41,0) -> 0 | AO41: =IF($C41=$Z$16,$E41,0) -> 0 | AP41: =IF($C41=$Z$16,$F41,0) -> 0 | AQ41: =IF($C41=$Z$17,$E41,0) -> 0 | AR41: =IF($C41=$Z$17,$F41,0) -> 0 | AT41: =IF(OR($G41=$AA$11,$G41=$AA$13,($G41=$AA$14),$G41=$AA$15),$AE41+$AG41+$AI41+$AK41+$AQ41,0) -> 0 | AU41: =IF(OR($G41=$AA$11,$G41=$AA$13,($G41=$AA$14),$G41=$AA$15),$AF41+$AH41+$AJ41+AL41+AR41,0) -> 0 | AV41: =IF($G41=$AA$12,$AE41+$AG41+$AI41+AK41+AQ41,0) -> 0 | AW41: =IF($G41=$AA$12,$AF41+$AH41+$AJ41+AL41+AR41,0) -> 0 | AY41: =IF(UPPER($I41) =$AB$12,IF($G41=$AA$12,$AV41,0),0) -> 0 | AZ41: =IF(UPPER($I41) =$AB$12,IF($G41<>$AA$12,$AT41,0),0) -> 0 | BA41: =IF(UPPER($I41) =$AB$12,IF($G41=$AA$12,$AW41,0),0) -> 0 | BB41: =IF(UPPER($I41) =$AB$12,IF($G41<>$AA$12,$AU41,0),0) -> 0 | BC41: =IF(UPPER($J41) =$AB$12,IF($G41=$AA$12,$AV41,0),0) -> 0 | BD41: =IF(UPPER($J41) =$AB$12,IF($G41<>$AA$12,$AT41,0),0) -> 0 | BE41: =IF(UPPER($J41) =$AB$12,IF($G41=$AA$12,$AW41,0),0) -> 0 | BF41: =IF(UPPER($J41) =$AB$12,IF($G41<>$AA$12,$AU41,0),0) -> 0 | BG41: =IF(UPPER($K41) =$AB$12,IF($G41=$AA$12,$AV41,0),0) -> 0 | BH41: =IF(UPPER($K41) =$AB$12,IF($G41<>$AA$12,$AT41,0),0) -> 0 | BI41: =IF(UPPER($K41) =$AB$12,IF($G41=$AA$12,$AW41,0),0) -> 0 | BJ41: =IF(UPPER($K41) =$AB$12,IF($G41<>$AA$12,$AU41,0),0) -> 0 | BL41: =IF(($E41+$F41>0), IF($G41=$AA$10,1,0),0) -> 0 | BM41: =IF(($E41+$F41<=0), IF($G41<>$AA$10,1,0),0) -> 0 | BN41: =IF(($E41+$F41>0), IF($C41=$AA$10,1,0),0) -> 0
A42: 31 | AE42: =IF($C42=$Z$11,$E42,0) -> 0 | AF42: =IF($C42=$Z$11,$F42,0) -> 0 | AG42: =IF($C42=$Z$12,$E42,0) -> 0 | AH42: =IF($C42=$Z$12,$F42,0) -> 0 | AI42: =IF($C42=$Z$13,$E42,0) -> 0 | AJ42: =IF($C42=$Z$13,$F42,0) -> 0 | AK42: =IF($C42=$Z$14,$E42,0) -> 0 | AL42: =IF($C42=$Z$14,$F42,0) -> 0 | AM42: =IF($C42=$Z$15,$E42,0) -> 0 | AN42: =IF($C42=$Z$15,$F42,0) -> 0 | AO42: =IF($C42=$Z$16,$E42,0) -> 0 | AP42: =IF($C42=$Z$16,$F42,0) -> 0 | AQ42: =IF($C42=$Z$17,$E42,0) -> 0 | AR42: =IF($C42=$Z$17,$F42,0) -> 0 | AT42: =IF(OR($G42=$AA$11,$G42=$AA$13,($G42=$AA$14),$G42=$AA$15),$AE42+$AG42+$AI42+$AK42+$AQ42,0) -> 0 | AU42: =IF(OR($G42=$AA$11,$G42=$AA$13,($G42=$AA$14),$G42=$AA$15),$AF42+$AH42+$AJ42+AL42+AR42,0) -> 0 | AV42: =IF($G42=$AA$12,$AE42+$AG42+$AI42+AK42+AQ42,0) -> 0 | AW42: =IF($G42=$AA$12,$AF42+$AH42+$AJ42+AL42+AR42,0) -> 0 | AY42: =IF(UPPER($I42) =$AB$12,IF($G42=$AA$12,$AV42,0),0) -> 0 | AZ42: =IF(UPPER($I42) =$AB$12,IF($G42<>$AA$12,$AT42,0),0) -> 0 | BA42: =IF(UPPER($I42) =$AB$12,IF($G42=$AA$12,$AW42,0),0) -> 0 | BB42: =IF(UPPER($I42) =$AB$12,IF($G42<>$AA$12,$AU42,0),0) -> 0 | BC42: =IF(UPPER($J42) =$AB$12,IF($G42=$AA$12,$AV42,0),0) -> 0 | BD42: =IF(UPPER($J42) =$AB$12,IF($G42<>$AA$12,$AT42,0),0) -> 0 | BE42: =IF(UPPER($J42) =$AB$12,IF($G42=$AA$12,$AW42,0),0) -> 0 | BF42: =IF(UPPER($J42) =$AB$12,IF($G42<>$AA$12,$AU42,0),0) -> 0 | BG42: =IF(UPPER($K42) =$AB$12,IF($G42=$AA$12,$AV42,0),0) -> 0 | BH42: =IF(UPPER($K42) =$AB$12,IF($G42<>$AA$12,$AT42,0),0) -> 0 | BI42: =IF(UPPER($K42) =$AB$12,IF($G42=$AA$12,$AW42,0),0) -> 0 | BJ42: =IF(UPPER($K42) =$AB$12,IF($G42<>$AA$12,$AU42,0),0) -> 0 | BL42: =IF(($E42+$F42>0), IF($G42=$AA$10,1,0),0) -> 0 | BM42: =IF(($E42+$F42<=0), IF($G42<>$AA$10,1,0),0) -> 0 | BN42: =IF(($E42+$F42>0), IF($C42=$AA$10,1,0),0) -> 0
A43: 32 | AE43: =IF($C43=$Z$11,$E43,0) -> 0 | AF43: =IF($C43=$Z$11,$F43,0) -> 0 | AG43: =IF($C43=$Z$12,$E43,0) -> 0 | AH43: =IF($C43=$Z$12,$F43,0) -> 0 | AI43: =IF($C43=$Z$13,$E43,0) -> 0 | AJ43: =IF($C43=$Z$13,$F43,0) -> 0 | AK43: =IF($C43=$Z$14,$E43,0) -> 0 | AL43: =IF($C43=$Z$14,$F43,0) -> 0 | AM43: =IF($C43=$Z$15,$E43,0) -> 0 | AN43: =IF($C43=$Z$15,$F43,0) -> 0 | AO43: =IF($C43=$Z$16,$E43,0) -> 0 | AP43: =IF($C43=$Z$16,$F43,0) -> 0 | AQ43: =IF($C43=$Z$17,$E43,0) -> 0 | AR43: =IF($C43=$Z$17,$F43,0) -> 0 | AT43: =IF(OR($G43=$AA$11,$G43=$AA$13,($G43=$AA$14),$G43=$AA$15),$AE43+$AG43+$AI43+$AK43+$AQ43,0) -> 0 | AU43: =IF(OR($G43=$AA$11,$G43=$AA$13,($G43=$AA$14),$G43=$AA$15),$AF43+$AH43+$AJ43+AL43+AR43,0) -> 0 | AV43: =IF($G43=$AA$12,$AE43+$AG43+$AI43+AK43+AQ43,0) -> 0 | AW43: =IF($G43=$AA$12,$AF43+$AH43+$AJ43+AL43+AR43,0) -> 0 | AY43: =IF(UPPER($I43) =$AB$12,IF($G43=$AA$12,$AV43,0),0) -> 0 | AZ43: =IF(UPPER($I43) =$AB$12,IF($G43<>$AA$12,$AT43,0),0) -> 0 | BA43: =IF(UPPER($I43) =$AB$12,IF($G43=$AA$12,$AW43,0),0) -> 0 | BB43: =IF(UPPER($I43) =$AB$12,IF($G43<>$AA$12,$AU43,0),0) -> 0 | BC43: =IF(UPPER($J43) =$AB$12,IF($G43=$AA$12,$AV43,0),0) -> 0 | BD43: =IF(UPPER($J43) =$AB$12,IF($G43<>$AA$12,$AT43,0),0) -> 0 | BE43: =IF(UPPER($J43) =$AB$12,IF($G43=$AA$12,$AW43,0),0) -> 0 | BF43: =IF(UPPER($J43) =$AB$12,IF($G43<>$AA$12,$AU43,0),0) -> 0 | BG43: =IF(UPPER($K43) =$AB$12,IF($G43=$AA$12,$AV43,0),0) -> 0 | BH43: =IF(UPPER($K43) =$AB$12,IF($G43<>$AA$12,$AT43,0),0) -> 0 | BI43: =IF(UPPER($K43) =$AB$12,IF($G43=$AA$12,$AW43,0),0) -> 0 | BJ43: =IF(UPPER($K43) =$AB$12,IF($G43<>$AA$12,$AU43,0),0) -> 0 | BL43: =IF(($E43+$F43>0), IF($G43=$AA$10,1,0),0) -> 0 | BM43: =IF(($E43+$F43<=0), IF($G43<>$AA$10,1,0),0) -> 0 | BN43: =IF(($E43+$F43>0), IF($C43=$AA$10,1,0),0) -> 0
A44: 33 | AE44: =IF($C44=$Z$11,$E44,0) -> 0 | AF44: =IF($C44=$Z$11,$F44,0) -> 0 | AG44: =IF($C44=$Z$12,$E44,0) -> 0 | AH44: =IF($C44=$Z$12,$F44,0) -> 0 | AI44: =IF($C44=$Z$13,$E44,0) -> 0 | AJ44: =IF($C44=$Z$13,$F44,0) -> 0 | AK44: =IF($C44=$Z$14,$E44,0) -> 0 | AL44: =IF($C44=$Z$14,$F44,0) -> 0 | AM44: =IF($C44=$Z$15,$E44,0) -> 0 | AN44: =IF($C44=$Z$15,$F44,0) -> 0 | AO44: =IF($C44=$Z$16,$E44,0) -> 0 | AP44: =IF($C44=$Z$16,$F44,0) -> 0 | AQ44: =IF($C44=$Z$17,$E44,0) -> 0 | AR44: =IF($C44=$Z$17,$F44,0) -> 0 | AT44: =IF(OR($G44=$AA$11,$G44=$AA$13,($G44=$AA$14),$G44=$AA$15),$AE44+$AG44+$AI44+$AK44+$AQ44,0) -> 0 | AU44: =IF(OR($G44=$AA$11,$G44=$AA$13,($G44=$AA$14),$G44=$AA$15),$AF44+$AH44+$AJ44+AL44+AR44,0) -> 0 | AV44: =IF($G44=$AA$12,$AE44+$AG44+$AI44+AK44+AQ44,0) -> 0 | AW44: =IF($G44=$AA$12,$AF44+$AH44+$AJ44+AL44+AR44,0) -> 0 | AY44: =IF(UPPER($I44) =$AB$12,IF($G44=$AA$12,$AV44,0),0) -> 0 | AZ44: =IF(UPPER($I44) =$AB$12,IF($G44<>$AA$12,$AT44,0),0) -> 0 | BA44: =IF(UPPER($I44) =$AB$12,IF($G44=$AA$12,$AW44,0),0) -> 0 | BB44: =IF(UPPER($I44) =$AB$12,IF($G44<>$AA$12,$AU44,0),0) -> 0 | BC44: =IF(UPPER($J44) =$AB$12,IF($G44=$AA$12,$AV44,0),0) -> 0 | BD44: =IF(UPPER($J44) =$AB$12,IF($G44<>$AA$12,$AT44,0),0) -> 0 | BE44: =IF(UPPER($J44) =$AB$12,IF($G44=$AA$12,$AW44,0),0) -> 0 | BF44: =IF(UPPER($J44) =$AB$12,IF($G44<>$AA$12,$AU44,0),0) -> 0 | BG44: =IF(UPPER($K44) =$AB$12,IF($G44=$AA$12,$AV44,0),0) -> 0 | BH44: =IF(UPPER($K44) =$AB$12,IF($G44<>$AA$12,$AT44,0),0) -> 0 | BI44: =IF(UPPER($K44) =$AB$12,IF($G44=$AA$12,$AW44,0),0) -> 0 | BJ44: =IF(UPPER($K44) =$AB$12,IF($G44<>$AA$12,$AU44,0),0) -> 0 | BL44: =IF(($E44+$F44>0), IF($G44=$AA$10,1,0),0) -> 0 | BM44: =IF(($E44+$F44<=0), IF($G44<>$AA$10,1,0),0) -> 0 | BN44: =IF(($E44+$F44>0), IF($C44=$AA$10,1,0),0) -> 0
A45: 34 | AE45: =IF($C45=$Z$11,$E45,0) -> 0 | AF45: =IF($C45=$Z$11,$F45,0) -> 0 | AG45: =IF($C45=$Z$12,$E45,0) -> 0 | AH45: =IF($C45=$Z$12,$F45,0) -> 0 | AI45: =IF($C45=$Z$13,$E45,0) -> 0 | AJ45: =IF($C45=$Z$13,$F45,0) -> 0 | AK45: =IF($C45=$Z$14,$E45,0) -> 0 | AL45: =IF($C45=$Z$14,$F45,0) -> 0 | AM45: =IF($C45=$Z$15,$E45,0) -> 0 | AN45: =IF($C45=$Z$15,$F45,0) -> 0 | AO45: =IF($C45=$Z$16,$E45,0) -> 0 | AP45: =IF($C45=$Z$16,$F45,0) -> 0 | AQ45: =IF($C45=$Z$17,$E45,0) -> 0 | AR45: =IF($C45=$Z$17,$F45,0) -> 0 | AT45: =IF(OR($G45=$AA$11,$G45=$AA$13,($G45=$AA$14),$G45=$AA$15),$AE45+$AG45+$AI45+$AK45+$AQ45,0) -> 0 | AU45: =IF(OR($G45=$AA$11,$G45=$AA$13,($G45=$AA$14),$G45=$AA$15),$AF45+$AH45+$AJ45+AL45+AR45,0) -> 0 | AV45: =IF($G45=$AA$12,$AE45+$AG45+$AI45+AK45+AQ45,0) -> 0 | AW45: =IF($G45=$AA$12,$AF45+$AH45+$AJ45+AL45+AR45,0) -> 0 | AY45: =IF(UPPER($I45) =$AB$12,IF($G45=$AA$12,$AV45,0),0) -> 0 | AZ45: =IF(UPPER($I45) =$AB$12,IF($G45<>$AA$12,$AT45,0),0) -> 0 | BA45: =IF(UPPER($I45) =$AB$12,IF($G45=$AA$12,$AW45,0),0) -> 0 | BB45: =IF(UPPER($I45) =$AB$12,IF($G45<>$AA$12,$AU45,0),0) -> 0 | BC45: =IF(UPPER($J45) =$AB$12,IF($G45=$AA$12,$AV45,0),0) -> 0 | BD45: =IF(UPPER($J45) =$AB$12,IF($G45<>$AA$12,$AT45,0),0) -> 0 | BE45: =IF(UPPER($J45) =$AB$12,IF($G45=$AA$12,$AW45,0),0) -> 0 | BF45: =IF(UPPER($J45) =$AB$12,IF($G45<>$AA$12,$AU45,0),0) -> 0 | BG45: =IF(UPPER($K45) =$AB$12,IF($G45=$AA$12,$AV45,0),0) -> 0 | BH45: =IF(UPPER($K45) =$AB$12,IF($G45<>$AA$12,$AT45,0),0) -> 0 | BI45: =IF(UPPER($K45) =$AB$12,IF($G45=$AA$12,$AW45,0),0) -> 0 | BJ45: =IF(UPPER($K45) =$AB$12,IF($G45<>$AA$12,$AU45,0),0) -> 0 | BL45: =IF(($E45+$F45>0), IF($G45=$AA$10,1,0),0) -> 0 | BM45: =IF(($E45+$F45<=0), IF($G45<>$AA$10,1,0),0) -> 0 | BN45: =IF(($E45+$F45>0), IF($C45=$AA$10,1,0),0) -> 0
A46: 35 | AE46: =IF($C46=$Z$11,$E46,0) -> 0 | AF46: =IF($C46=$Z$11,$F46,0) -> 0 | AG46: =IF($C46=$Z$12,$E46,0) -> 0 | AH46: =IF($C46=$Z$12,$F46,0) -> 0 | AI46: =IF($C46=$Z$13,$E46,0) -> 0 | AJ46: =IF($C46=$Z$13,$F46,0) -> 0 | AK46: =IF($C46=$Z$14,$E46,0) -> 0 | AL46: =IF($C46=$Z$14,$F46,0) -> 0 | AM46: =IF($C46=$Z$15,$E46,0) -> 0 | AN46: =IF($C46=$Z$15,$F46,0) -> 0 | AO46: =IF($C46=$Z$16,$E46,0) -> 0 | AP46: =IF($C46=$Z$16,$F46,0) -> 0 | AQ46: =IF($C46=$Z$17,$E46,0) -> 0 | AR46: =IF($C46=$Z$17,$F46,0) -> 0 | AT46: =IF(OR($G46=$AA$11,$G46=$AA$13,($G46=$AA$14),$G46=$AA$15),$AE46+$AG46+$AI46+$AK46+$AQ46,0) -> 0 | AU46: =IF(OR($G46=$AA$11,$G46=$AA$13,($G46=$AA$14),$G46=$AA$15),$AF46+$AH46+$AJ46+AL46+AR46,0) -> 0 | AV46: =IF($G46=$AA$12,$AE46+$AG46+$AI46+AK46+AQ46,0) -> 0 | AW46: =IF($G46=$AA$12,$AF46+$AH46+$AJ46+AL46+AR46,0) -> 0 | AY46: =IF(UPPER($I46) =$AB$12,IF($G46=$AA$12,$AV46,0),0) -> 0 | AZ46: =IF(UPPER($I46) =$AB$12,IF($G46<>$AA$12,$AT46,0),0) -> 0 | BA46: =IF(UPPER($I46) =$AB$12,IF($G46=$AA$12,$AW46,0),0) -> 0 | BB46: =IF(UPPER($I46) =$AB$12,IF($G46<>$AA$12,$AU46,0),0) -> 0 | BC46: =IF(UPPER($J46) =$AB$12,IF($G46=$AA$12,$AV46,0),0) -> 0 | BD46: =IF(UPPER($J46) =$AB$12,IF($G46<>$AA$12,$AT46,0),0) -> 0 | BE46: =IF(UPPER($J46) =$AB$12,IF($G46=$AA$12,$AW46,0),0) -> 0 | BF46: =IF(UPPER($J46) =$AB$12,IF($G46<>$AA$12,$AU46,0),0) -> 0 | BG46: =IF(UPPER($K46) =$AB$12,IF($G46=$AA$12,$AV46,0),0) -> 0 | BH46: =IF(UPPER($K46) =$AB$12,IF($G46<>$AA$12,$AT46,0),0) -> 0 | BI46: =IF(UPPER($K46) =$AB$12,IF($G46=$AA$12,$AW46,0),0) -> 0 | BJ46: =IF(UPPER($K46) =$AB$12,IF($G46<>$AA$12,$AU46,0),0) -> 0 | BL46: =IF(($E46+$F46>0), IF($G46=$AA$10,1,0),0) -> 0 | BM46: =IF(($E46+$F46<=0), IF($G46<>$AA$10,1,0),0) -> 0 | BN46: =IF(($E46+$F46>0), IF($C46=$AA$10,1,0),0) -> 0
A47: 36 | AE47: =IF($C47=$Z$11,$E47,0) -> 0 | AF47: =IF($C47=$Z$11,$F47,0) -> 0 | AG47: =IF($C47=$Z$12,$E47,0) -> 0 | AH47: =IF($C47=$Z$12,$F47,0) -> 0 | AI47: =IF($C47=$Z$13,$E47,0) -> 0 | AJ47: =IF($C47=$Z$13,$F47,0) -> 0 | AK47: =IF($C47=$Z$14,$E47,0) -> 0 | AL47: =IF($C47=$Z$14,$F47,0) -> 0 | AM47: =IF($C47=$Z$15,$E47,0) -> 0 | AN47: =IF($C47=$Z$15,$F47,0) -> 0 | AO47: =IF($C47=$Z$16,$E47,0) -> 0 | AP47: =IF($C47=$Z$16,$F47,0) -> 0 | AQ47: =IF($C47=$Z$17,$E47,0) -> 0 | AR47: =IF($C47=$Z$17,$F47,0) -> 0 | AT47: =IF(OR($G47=$AA$11,$G47=$AA$13,($G47=$AA$14),$G47=$AA$15),$AE47+$AG47+$AI47+$AK47+$AQ47,0) -> 0 | AU47: =IF(OR($G47=$AA$11,$G47=$AA$13,($G47=$AA$14),$G47=$AA$15),$AF47+$AH47+$AJ47+AL47+AR47,0) -> 0 | AV47: =IF($G47=$AA$12,$AE47+$AG47+$AI47+AK47+AQ47,0) -> 0 | AW47: =IF($G47=$AA$12,$AF47+$AH47+$AJ47+AL47+AR47,0) -> 0 | AY47: =IF(UPPER($I47) =$AB$12,IF($G47=$AA$12,$AV47,0),0) -> 0 | AZ47: =IF(UPPER($I47) =$AB$12,IF($G47<>$AA$12,$AT47,0),0) -> 0 | BA47: =IF(UPPER($I47) =$AB$12,IF($G47=$AA$12,$AW47,0),0) -> 0 | BB47: =IF(UPPER($I47) =$AB$12,IF($G47<>$AA$12,$AU47,0),0) -> 0 | BC47: =IF(UPPER($J47) =$AB$12,IF($G47=$AA$12,$AV47,0),0) -> 0 | BD47: =IF(UPPER($J47) =$AB$12,IF($G47<>$AA$12,$AT47,0),0) -> 0 | BE47: =IF(UPPER($J47) =$AB$12,IF($G47=$AA$12,$AW47,0),0) -> 0 | BF47: =IF(UPPER($J47) =$AB$12,IF($G47<>$AA$12,$AU47,0),0) -> 0 | BG47: =IF(UPPER($K47) =$AB$12,IF($G47=$AA$12,$AV47,0),0) -> 0 | BH47: =IF(UPPER($K47) =$AB$12,IF($G47<>$AA$12,$AT47,0),0) -> 0 | BI47: =IF(UPPER($K47) =$AB$12,IF($G47=$AA$12,$AW47,0),0) -> 0 | BJ47: =IF(UPPER($K47) =$AB$12,IF($G47<>$AA$12,$AU47,0),0) -> 0 | BL47: =IF(($E47+$F47>0), IF($G47=$AA$10,1,0),0) -> 0 | BM47: =IF(($E47+$F47<=0), IF($G47<>$AA$10,1,0),0) -> 0 | BN47: =IF(($E47+$F47>0), IF($C47=$AA$10,1,0),0) -> 0
A48: 37 | AE48: =IF($C48=$Z$11,$E48,0) -> 0 | AF48: =IF($C48=$Z$11,$F48,0) -> 0 | AG48: =IF($C48=$Z$12,$E48,0) -> 0 | AH48: =IF($C48=$Z$12,$F48,0) -> 0 | AI48: =IF($C48=$Z$13,$E48,0) -> 0 | AJ48: =IF($C48=$Z$13,$F48,0) -> 0 | AK48: =IF($C48=$Z$14,$E48,0) -> 0 | AL48: =IF($C48=$Z$14,$F48,0) -> 0 | AM48: =IF($C48=$Z$15,$E48,0) -> 0 | AN48: =IF($C48=$Z$15,$F48,0) -> 0 | AO48: =IF($C48=$Z$16,$E48,0) -> 0 | AP48: =IF($C48=$Z$16,$F48,0) -> 0 | AQ48: =IF($C48=$Z$17,$E48,0) -> 0 | AR48: =IF($C48=$Z$17,$F48,0) -> 0 | AT48: =IF(OR($G48=$AA$11,$G48=$AA$13,($G48=$AA$14),$G48=$AA$15),$AE48+$AG48+$AI48+$AK48+$AQ48,0) -> 0 | AU48: =IF(OR($G48=$AA$11,$G48=$AA$13,($G48=$AA$14),$G48=$AA$15),$AF48+$AH48+$AJ48+AL48+AR48,0) -> 0 | AV48: =IF($G48=$AA$12,$AE48+$AG48+$AI48+AK48+AQ48,0) -> 0 | AW48: =IF($G48=$AA$12,$AF48+$AH48+$AJ48+AL48+AR48,0) -> 0 | AY48: =IF(UPPER($I48) =$AB$12,IF($G48=$AA$12,$AV48,0),0) -> 0 | AZ48: =IF(UPPER($I48) =$AB$12,IF($G48<>$AA$12,$AT48,0),0) -> 0 | BA48: =IF(UPPER($I48) =$AB$12,IF($G48=$AA$12,$AW48,0),0) -> 0 | BB48: =IF(UPPER($I48) =$AB$12,IF($G48<>$AA$12,$AU48,0),0) -> 0 | BC48: =IF(UPPER($J48) =$AB$12,IF($G48=$AA$12,$AV48,0),0) -> 0 | BD48: =IF(UPPER($J48) =$AB$12,IF($G48<>$AA$12,$AT48,0),0) -> 0 | BE48: =IF(UPPER($J48) =$AB$12,IF($G48=$AA$12,$AW48,0),0) -> 0 | BF48: =IF(UPPER($J48) =$AB$12,IF($G48<>$AA$12,$AU48,0),0) -> 0 | BG48: =IF(UPPER($K48) =$AB$12,IF($G48=$AA$12,$AV48,0),0) -> 0 | BH48: =IF(UPPER($K48) =$AB$12,IF($G48<>$AA$12,$AT48,0),0) -> 0 | BI48: =IF(UPPER($K48) =$AB$12,IF($G48=$AA$12,$AW48,0),0) -> 0 | BJ48: =IF(UPPER($K48) =$AB$12,IF($G48<>$AA$12,$AU48,0),0) -> 0 | BL48: =IF(($E48+$F48>0), IF($G48=$AA$10,1,0),0) -> 0 | BM48: =IF(($E48+$F48<=0), IF($G48<>$AA$10,1,0),0) -> 0 | BN48: =IF(($E48+$F48>0), IF($C48=$AA$10,1,0),0) -> 0
... A61: 50 | AE61: =IF($C61=$Z$11,$E61,0) -> 0 | AF61: =IF($C61=$Z$11,$F61,0) -> 0 | AG61: =IF($C61=$Z$12,$E61,0) -> 0 | AH61: =IF($C61=$Z$12,$F61,0) -> 0 | AI61: =IF($C61=$Z$13,$E61,0) -> 0 | AJ61: =IF($C61=$Z$13,$F61,0) -> 0 | AK61: =IF($C61=$Z$14,$E61,0) -> 0 | AL61: =IF($C61=$Z$14,$F61,0) -> 0 | AM61: =IF($C61=$Z$15,$E61,0) -> 0 | AN61: =IF($C61=$Z$15,$F61,0) -> 0 | AO61: =IF($C61=$Z$16,$E61,0) -> 0 | AP61: =IF($C61=$Z$16,$F61,0) -> 0 | AQ61: =IF($C61=$Z$17,$E61,0) -> 0 | AR61: =IF($C61=$Z$17,$F61,0) -> 0 | AT61: =IF(OR($G61=$AA$11,$G61=$AA$13,($G61=$AA$14),$G61=$AA$15),$AE61+$AG61+$AI61+$AK61+$AQ61,0) -> 0 | AU61: =IF(OR($G61=$AA$11,$G61=$AA$13,($G61=$AA$14),$G61=$AA$15),$AF61+$AH61+$AJ61+AL61+AR61,0) -> 0 | AV61: =IF($G61=$AA$12,$AE61+$AG61+$AI61+AK61+AQ61,0) -> 0 | AW61: =IF($G61=$AA$12,$AF61+$AH61+$AJ61+AL61+AR61,0) -> 0 | AY61: =IF(UPPER($I61) =$AB$12,IF($G61=$AA$12,$AV61,0),0) -> 0 | AZ61: =IF(UPPER($I61) =$AB$12,IF($G61<>$AA$12,$AT61,0),0) -> 0 | BA61: =IF(UPPER($I61) =$AB$12,IF($G61=$AA$12,$AW61,0),0) -> 0 | BB61: =IF(UPPER($I61) =$AB$12,IF($G61<>$AA$12,$AU61,0),0) -> 0 | BC61: =IF(UPPER($J61) =$AB$12,IF($G61=$AA$12,$AV61,0),0) -> 0 | BD61: =IF(UPPER($J61) =$AB$12,IF($G61<>$AA$12,$AT61,0),0) -> 0 | BE61: =IF(UPPER($J61) =$AB$12,IF($G61=$AA$12,$AW61,0),0) -> 0 | BF61: =IF(UPPER($J61) =$AB$12,IF($G61<>$AA$12,$AU61,0),0) -> 0 | BG61: =IF(UPPER($K61) =$AB$12,IF($G61=$AA$12,$AV61,0),0) -> 0 | BH61: =IF(UPPER($K61) =$AB$12,IF($G61<>$AA$12,$AT61,0),0) -> 0 | BI61: =IF(UPPER($K61) =$AB$12,IF($G61=$AA$12,$AW61,0),0) -> 0 | BJ61: =IF(UPPER($K61) =$AB$12,IF($G61<>$AA$12,$AU61,0),0) -> 0 | BL61: =IF(($E61+$F61>0), IF($G61=$AA$10,1,0),0) -> 0 | BM61: =IF(($E61+$F61<=0), IF($G61<>$AA$10,1,0),0) -> 0 | BN61: =IF(($E61+$F61>0), IF($C61=$AA$10,1,0),0) -> 0
AE62: =IF($C62=$Z$11,$E62,0) -> 0 | AF62: =IF($C62=$Z$11,$F62,0) -> 0 | AG62: =IF($C62=$Z$12,$E62,0) -> 0 | AH62: =IF($C62=$Z$12,$F62,0) -> 0 | AI62: =IF($C62=$Z$13,$E62,0) -> 0 | AJ62: =IF($C62=$Z$13,$F62,0) -> 0 | AK62: =IF($C62=$Z$14,$E62,0) -> 0 | AL62: =IF($C62=$Z$14,$F62,0) -> 0 | AM62: =IF($C62=$Z$15,$E62,0) -> 0 | AN62: =IF($C62=$Z$15,$F62,0) -> 0 | AO62: =IF($C62=$Z$16,$E62,0) -> 0 | AP62: =IF($C62=$Z$16,$F62,0) -> 0 | AQ62: =IF($C62=$Z$17,$E62,0) -> 0 | AR62: =IF($C62=$Z$17,$F62,0) -> 0 | AT62: =IF(OR($G62=$AA$11,$G62=$AA$13,($G62=$AA$14),$G62=$AA$15),$AE62+$AG62+$AI62+$AK62+$AQ62,0) -> 0 | AU62: =IF(OR($G62=$AA$11,$G62=$AA$13,($G62=$AA$14),$G62=$AA$15),$AF62+$AH62+$AJ62+AL62+AR62,0) -> 0 | AV62: =IF($G62=$AA$12,$AE62+$AG62+$AI62+AK62+AQ62,0) -> 0 | AW62: =IF($G62=$AA$12,$AF62+$AH62+$AJ62+AL62+AR62,0) -> 0 | AY62: =IF(UPPER($I62) =$AB$12,IF($G62=$AA$12,$AV62,0),0) -> 0 | AZ62: =IF(UPPER($I62) =$AB$12,IF($G62<>$AA$12,$AT62,0),0) -> 0 | BA62: =IF(UPPER($I62) =$AB$12,IF($G62=$AA$12,$AW62,0),0) -> 0 | BB62: =IF(UPPER($I62) =$AB$12,IF($G62<>$AA$12,$AU62,0),0) -> 0 | BC62: =IF(UPPER($J62) =$AB$12,IF($G62=$AA$12,$AV62,0),0) -> 0 | BD62: =IF(UPPER($J62) =$AB$12,IF($G62<>$AA$12,$AT62,0),0) -> 0 | BE62: =IF(UPPER($J62) =$AB$12,IF($G62=$AA$12,$AW62,0),0) -> 0 | BF62: =IF(UPPER($J62) =$AB$12,IF($G62<>$AA$12,$AU62,0),0) -> 0 | BG62: =IF(UPPER($K62) =$AB$12,IF($G62=$AA$12,$AV62,0),0) -> 0 | BH62: =IF(UPPER($K62) =$AB$12,IF($G62<>$AA$12,$AT62,0),0) -> 0 | BI62: =IF(UPPER($K62) =$AB$12,IF($G62=$AA$12,$AW62,0),0) -> 0 | BJ62: =IF(UPPER($K62) =$AB$12,IF($G62<>$AA$12,$AU62,0),0) -> 0 | BL62: =IF(($E62+$F62>0), IF($G62=$AA$10,1,0),0) -> 0 | BM62: =IF(($E62+$F62<=0), IF($G62<>$AA$10,1,0),0) -> 0 | BN62: =IF(($E62+$F62>0), IF($C62=$AA$10,1,0),0) -> 0
A63: 51 | L63: PAGINA 3
A64: 52 | AE64: =IF($C64=$Z$11,$E64,0) -> 0 | AF64: =IF($C64=$Z$11,$F64,0) -> 0 | AG64: =IF($C64=$Z$12,$E64,0) -> 0 | AH64: =IF($C64=$Z$12,$F64,0) -> 0 | AI64: =IF($C64=$Z$13,$E64,0) -> 0 | AJ64: =IF($C64=$Z$13,$F64,0) -> 0 | AK64: =IF($C64=$Z$14,$E64,0) -> 0 | AL64: =IF($C64=$Z$14,$F64,0) -> 0 | AM64: =IF($C64=$Z$15,$E64,0) -> 0 | AN64: =IF($C64=$Z$15,$F64,0) -> 0 | AO64: =IF($C64=$Z$16,$E64,0) -> 0 | AP64: =IF($C64=$Z$16,$F64,0) -> 0 | AQ64: =IF($C64=$Z$17,$E64,0) -> 0 | AR64: =IF($C64=$Z$17,$F64,0) -> 0 | AT64: =IF(OR($G64=$AA$11,$G64=$AA$13,($G64=$AA$14),$G64=$AA$15),$AE64+$AG64+$AI64+$AK64+$AQ64,0) -> 0 | AU64: =IF(OR($G64=$AA$11,$G64=$AA$13,($G64=$AA$14),$G64=$AA$15),$AF64+$AH64+$AJ64+AL64+AR64,0) -> 0 | AV64: =IF($G64=$AA$12,$AE64+$AG64+$AI64+AK64+AQ64,0) -> 0 | AW64: =IF($G64=$AA$12,$AF64+$AH64+$AJ64+AL64+AR64,0) -> 0 | AY64: =IF(UPPER($I64) =$AB$12,IF($G64=$AA$12,$AV64,0),0) -> 0 | AZ64: =IF(UPPER($I64) =$AB$12,IF($G64<>$AA$12,$AT64,0),0) -> 0 | BA64: =IF(UPPER($I64) =$AB$12,IF($G64=$AA$12,$AW64,0),0) -> 0 | BB64: =IF(UPPER($I64) =$AB$12,IF($G64<>$AA$12,$AU64,0),0) -> 0 | BC64: =IF(UPPER($J64) =$AB$12,IF($G64=$AA$12,$AV64,0),0) -> 0 | BD64: =IF(UPPER($J64) =$AB$12,IF($G64<>$AA$12,$AT64,0),0) -> 0 | BE64: =IF(UPPER($J64) =$AB$12,IF($G64=$AA$12,$AW64,0),0) -> 0 | BF64: =IF(UPPER($J64) =$AB$12,IF($G64<>$AA$12,$AU64,0),0) -> 0 | BG64: =IF(UPPER($K64) =$AB$12,IF($G64=$AA$12,$AV64,0),0) -> 0 | BH64: =IF(UPPER($K64) =$AB$12,IF($G64<>$AA$12,$AT64,0),0) -> 0 | BI64: =IF(UPPER($K64) =$AB$12,IF($G64=$AA$12,$AW64,0),0) -> 0 | BJ64: =IF(UPPER($K64) =$AB$12,IF($G64<>$AA$12,$AU64,0),0) -> 0 | BL64: =IF(($E64+$F64>0), IF($G64=$AA$10,1,0),0) -> 0 | BM64: =IF(($E64+$F64<=0), IF($G64<>$AA$10,1,0),0) -> 0 | BN64: =IF(($E64+$F64>0), IF($C64=$AA$10,1,0),0) -> 0
A65: 53 | AE65: =IF($C65=$Z$11,$E65,0) -> 0 | AF65: =IF($C65=$Z$11,$F65,0) -> 0 | AG65: =IF($C65=$Z$12,$E65,0) -> 0 | AH65: =IF($C65=$Z$12,$F65,0) -> 0 | AI65: =IF($C65=$Z$13,$E65,0) -> 0 | AJ65: =IF($C65=$Z$13,$F65,0) -> 0 | AK65: =IF($C65=$Z$14,$E65,0) -> 0 | AL65: =IF($C65=$Z$14,$F65,0) -> 0 | AM65: =IF($C65=$Z$15,$E65,0) -> 0 | AN65: =IF($C65=$Z$15,$F65,0) -> 0 | AO65: =IF($C65=$Z$16,$E65,0) -> 0 | AP65: =IF($C65=$Z$16,$F65,0) -> 0 | AQ65: =IF($C65=$Z$17,$E65,0) -> 0 | AR65: =IF($C65=$Z$17,$F65,0) -> 0 | AT65: =IF(OR($G65=$AA$11,$G65=$AA$13,($G65=$AA$14),$G65=$AA$15),$AE65+$AG65+$AI65+$AK65+$AQ65,0) -> 0 | AU65: =IF(OR($G65=$AA$11,$G65=$AA$13,($G65=$AA$14),$G65=$AA$15),$AF65+$AH65+$AJ65+AL65+AR65,0) -> 0 | AV65: =IF($G65=$AA$12,$AE65+$AG65+$AI65+AK65+AQ65,0) -> 0 | AW65: =IF($G65=$AA$12,$AF65+$AH65+$AJ65+AL65+AR65,0) -> 0 | AY65: =IF(UPPER($I65) =$AB$12,IF($G65=$AA$12,$AV65,0),0) -> 0 | AZ65: =IF(UPPER($I65) =$AB$12,IF($G65<>$AA$12,$AT65,0),0) -> 0 | BA65: =IF(UPPER($I65) =$AB$12,IF($G65=$AA$12,$AW65,0),0) -> 0 | BB65: =IF(UPPER($I65) =$AB$12,IF($G65<>$AA$12,$AU65,0),0) -> 0 | BC65: =IF(UPPER($J65) =$AB$12,IF($G65=$AA$12,$AV65,0),0) -> 0 | BD65: =IF(UPPER($J65) =$AB$12,IF($G65<>$AA$12,$AT65,0),0) -> 0 | BE65: =IF(UPPER($J65) =$AB$12,IF($G65=$AA$12,$AW65,0),0) -> 0 | BF65: =IF(UPPER($J65) =$AB$12,IF($G65<>$AA$12,$AU65,0),0) -> 0 | BG65: =IF(UPPER($K65) =$AB$12,IF($G65=$AA$12,$AV65,0),0) -> 0 | BH65: =IF(UPPER($K65) =$AB$12,IF($G65<>$AA$12,$AT65,0),0) -> 0 | BI65: =IF(UPPER($K65) =$AB$12,IF($G65=$AA$12,$AW65,0),0) -> 0 | BJ65: =IF(UPPER($K65) =$AB$12,IF($G65<>$AA$12,$AU65,0),0) -> 0 | BL65: =IF(($E65+$F65>0), IF($G65=$AA$10,1,0),0) -> 0 | BM65: =IF(($E65+$F65<=0), IF($G65<>$AA$10,1,0),0) -> 0 | BN65: =IF(($E65+$F65>0), IF($C65=$AA$10,1,0),0) -> 0
A66: 54 | AE66: =IF($C66=$Z$11,$E66,0) -> 0 | AF66: =IF($C66=$Z$11,$F66,0) -> 0 | AG66: =IF($C66=$Z$12,$E66,0) -> 0 | AH66: =IF($C66=$Z$12,$F66,0) -> 0 | AI66: =IF($C66=$Z$13,$E66,0) -> 0 | AJ66: =IF($C66=$Z$13,$F66,0) -> 0 | AK66: =IF($C66=$Z$14,$E66,0) -> 0 | AL66: =IF($C66=$Z$14,$F66,0) -> 0 | AM66: =IF($C66=$Z$15,$E66,0) -> 0 | AN66: =IF($C66=$Z$15,$F66,0) -> 0 | AO66: =IF($C66=$Z$16,$E66,0) -> 0 | AP66: =IF($C66=$Z$16,$F66,0) -> 0 | AQ66: =IF($C66=$Z$17,$E66,0) -> 0 | AR66: =IF($C66=$Z$17,$F66,0) -> 0 | AT66: =IF(OR($G66=$AA$11,$G66=$AA$13,($G66=$AA$14),$G66=$AA$15),$AE66+$AG66+$AI66+$AK66+$AQ66,0) -> 0 | AU66: =IF(OR($G66=$AA$11,$G66=$AA$13,($G66=$AA$14),$G66=$AA$15),$AF66+$AH66+$AJ66+AL66+AR66,0) -> 0 | AV66: =IF($G66=$AA$12,$AE66+$AG66+$AI66+AK66+AQ66,0) -> 0 | AW66: =IF($G66=$AA$12,$AF66+$AH66+$AJ66+AL66+AR66,0) -> 0 | AY66: =IF(UPPER($I66) =$AB$12,IF($G66=$AA$12,$AV66,0),0) -> 0 | AZ66: =IF(UPPER($I66) =$AB$12,IF($G66<>$AA$12,$AT66,0),0) -> 0 | BA66: =IF(UPPER($I66) =$AB$12,IF($G66=$AA$12,$AW66,0),0) -> 0 | BB66: =IF(UPPER($I66) =$AB$12,IF($G66<>$AA$12,$AU66,0),0) -> 0 | BC66: =IF(UPPER($J66) =$AB$12,IF($G66=$AA$12,$AV66,0),0) -> 0 | BD66: =IF(UPPER($J66) =$AB$12,IF($G66<>$AA$12,$AT66,0),0) -> 0 | BE66: =IF(UPPER($J66) =$AB$12,IF($G66=$AA$12,$AW66,0),0) -> 0 | BF66: =IF(UPPER($J66) =$AB$12,IF($G66<>$AA$12,$AU66,0),0) -> 0 | BG66: =IF(UPPER($K66) =$AB$12,IF($G66=$AA$12,$AV66,0),0) -> 0 | BH66: =IF(UPPER($K66) =$AB$12,IF($G66<>$AA$12,$AT66,0),0) -> 0 | BI66: =IF(UPPER($K66) =$AB$12,IF($G66=$AA$12,$AW66,0),0) -> 0 | BJ66: =IF(UPPER($K66) =$AB$12,IF($G66<>$AA$12,$AU66,0),0) -> 0 | BL66: =IF(($E66+$F66>0), IF($G66=$AA$10,1,0),0) -> 0 | BM66: =IF(($E66+$F66<=0), IF($G66<>$AA$10,1,0),0) -> 0 | BN66: =IF(($E66+$F66>0), IF($C66=$AA$10,1,0),0) -> 0
A67: 55 | AE67: =IF($C67=$Z$11,$E67,0) -> 0 | AF67: =IF($C67=$Z$11,$F67,0) -> 0 | AG67: =IF($C67=$Z$12,$E67,0) -> 0 | AH67: =IF($C67=$Z$12,$F67,0) -> 0 | AI67: =IF($C67=$Z$13,$E67,0) -> 0 | AJ67: =IF($C67=$Z$13,$F67,0) -> 0 | AK67: =IF($C67=$Z$14,$E67,0) -> 0 | AL67: =IF($C67=$Z$14,$F67,0) -> 0 | AM67: =IF($C67=$Z$15,$E67,0) -> 0 | AN67: =IF($C67=$Z$15,$F67,0) -> 0 | AO67: =IF($C67=$Z$16,$E67,0) -> 0 | AP67: =IF($C67=$Z$16,$F67,0) -> 0 | AQ67: =IF($C67=$Z$17,$E67,0) -> 0 | AR67: =IF($C67=$Z$17,$F67,0) -> 0 | AT67: =IF(OR($G67=$AA$11,$G67=$AA$13,($G67=$AA$14),$G67=$AA$15),$AE67+$AG67+$AI67+$AK67+$AQ67,0) -> 0 | AU67: =IF(OR($G67=$AA$11,$G67=$AA$13,($G67=$AA$14),$G67=$AA$15),$AF67+$AH67+$AJ67+AL67+AR67,0) -> 0 | AV67: =IF($G67=$AA$12,$AE67+$AG67+$AI67+AK67+AQ67,0) -> 0 | AW67: =IF($G67=$AA$12,$AF67+$AH67+$AJ67+AL67+AR67,0) -> 0 | AY67: =IF(UPPER($I67) =$AB$12,IF($G67=$AA$12,$AV67,0),0) -> 0 | AZ67: =IF(UPPER($I67) =$AB$12,IF($G67<>$AA$12,$AT67,0),0) -> 0 | BA67: =IF(UPPER($I67) =$AB$12,IF($G67=$AA$12,$AW67,0),0) -> 0 | BB67: =IF(UPPER($I67) =$AB$12,IF($G67<>$AA$12,$AU67,0),0) -> 0 | BC67: =IF(UPPER($J67) =$AB$12,IF($G67=$AA$12,$AV67,0),0) -> 0 | BD67: =IF(UPPER($J67) =$AB$12,IF($G67<>$AA$12,$AT67,0),0) -> 0 | BE67: =IF(UPPER($J67) =$AB$12,IF($G67=$AA$12,$AW67,0),0) -> 0 | BF67: =IF(UPPER($J67) =$AB$12,IF($G67<>$AA$12,$AU67,0),0) -> 0 | BG67: =IF(UPPER($K67) =$AB$12,IF($G67=$AA$12,$AV67,0),0) -> 0 | BH67: =IF(UPPER($K67) =$AB$12,IF($G67<>$AA$12,$AT67,0),0) -> 0 | BI67: =IF(UPPER($K67) =$AB$12,IF($G67=$AA$12,$AW67,0),0) -> 0 | BJ67: =IF(UPPER($K67) =$AB$12,IF($G67<>$AA$12,$AU67,0),0) -> 0 | BL67: =IF(($E67+$F67>0), IF($G67=$AA$10,1,0),0) -> 0 | BM67: =IF(($E67+$F67<=0), IF($G67<>$AA$10,1,0),0) -> 0 | BN67: =IF(($E67+$F67>0), IF($C67=$AA$10,1,0),0) -> 0
A68: 56 | AE68: =IF($C68=$Z$11,$E68,0) -> 0 | AF68: =IF($C68=$Z$11,$F68,0) -> 0 | AG68: =IF($C68=$Z$12,$E68,0) -> 0 | AH68: =IF($C68=$Z$12,$F68,0) -> 0 | AI68: =IF($C68=$Z$13,$E68,0) -> 0 | AJ68: =IF($C68=$Z$13,$F68,0) -> 0 | AK68: =IF($C68=$Z$14,$E68,0) -> 0 | AL68: =IF($C68=$Z$14,$F68,0) -> 0 | AM68: =IF($C68=$Z$15,$E68,0) -> 0 | AN68: =IF($C68=$Z$15,$F68,0) -> 0 | AO68: =IF($C68=$Z$16,$E68,0) -> 0 | AP68: =IF($C68=$Z$16,$F68,0) -> 0 | AQ68: =IF($C68=$Z$17,$E68,0) -> 0 | AR68: =IF($C68=$Z$17,$F68,0) -> 0 | AT68: =IF(OR($G68=$AA$11,$G68=$AA$13,($G68=$AA$14),$G68=$AA$15),$AE68+$AG68+$AI68+$AK68+$AQ68,0) -> 0 | AU68: =IF(OR($G68=$AA$11,$G68=$AA$13,($G68=$AA$14),$G68=$AA$15),$AF68+$AH68+$AJ68+AL68+AR68,0) -> 0 | AV68: =IF($G68=$AA$12,$AE68+$AG68+$AI68+AK68+AQ68,0) -> 0 | AW68: =IF($G68=$AA$12,$AF68+$AH68+$AJ68+AL68+AR68,0) -> 0 | AY68: =IF(UPPER($I68) =$AB$12,IF($G68=$AA$12,$AV68,0),0) -> 0 | AZ68: =IF(UPPER($I68) =$AB$12,IF($G68<>$AA$12,$AT68,0),0) -> 0 | BA68: =IF(UPPER($I68) =$AB$12,IF($G68=$AA$12,$AW68,0),0) -> 0 | BB68: =IF(UPPER($I68) =$AB$12,IF($G68<>$AA$12,$AU68,0),0) -> 0 | BC68: =IF(UPPER($J68) =$AB$12,IF($G68=$AA$12,$AV68,0),0) -> 0 | BD68: =IF(UPPER($J68) =$AB$12,IF($G68<>$AA$12,$AT68,0),0) -> 0 | BE68: =IF(UPPER($J68) =$AB$12,IF($G68=$AA$12,$AW68,0),0) -> 0 | BF68: =IF(UPPER($J68) =$AB$12,IF($G68<>$AA$12,$AU68,0),0) -> 0 | BG68: =IF(UPPER($K68) =$AB$12,IF($G68=$AA$12,$AV68,0),0) -> 0 | BH68: =IF(UPPER($K68) =$AB$12,IF($G68<>$AA$12,$AT68,0),0) -> 0 | BI68: =IF(UPPER($K68) =$AB$12,IF($G68=$AA$12,$AW68,0),0) -> 0 | BJ68: =IF(UPPER($K68) =$AB$12,IF($G68<>$AA$12,$AU68,0),0) -> 0 | BL68: =IF(($E68+$F68>0), IF($G68=$AA$10,1,0),0) -> 0 | BM68: =IF(($E68+$F68<=0), IF($G68<>$AA$10,1,0),0) -> 0 | BN68: =IF(($E68+$F68>0), IF($C68=$AA$10,1,0),0) -> 0
A69: 57 | AE69: =IF($C69=$Z$11,$E69,0) -> 0 | AF69: =IF($C69=$Z$11,$F69,0) -> 0 | AG69: =IF($C69=$Z$12,$E69,0) -> 0 | AH69: =IF($C69=$Z$12,$F69,0) -> 0 | AI69: =IF($C69=$Z$13,$E69,0) -> 0 | AJ69: =IF($C69=$Z$13,$F69,0) -> 0 | AK69: =IF($C69=$Z$14,$E69,0) -> 0 | AL69: =IF($C69=$Z$14,$F69,0) -> 0 | AM69: =IF($C69=$Z$15,$E69,0) -> 0 | AN69: =IF($C69=$Z$15,$F69,0) -> 0 | AO69: =IF($C69=$Z$16,$E69,0) -> 0 | AP69: =IF($C69=$Z$16,$F69,0) -> 0 | AQ69: =IF($C69=$Z$17,$E69,0) -> 0 | AR69: =IF($C69=$Z$17,$F69,0) -> 0 | AT69: =IF(OR($G69=$AA$11,$G69=$AA$13,($G69=$AA$14),$G69=$AA$15),$AE69+$AG69+$AI69+$AK69+$AQ69,0) -> 0 | AU69: =IF(OR($G69=$AA$11,$G69=$AA$13,($G69=$AA$14),$G69=$AA$15),$AF69+$AH69+$AJ69+AL69+AR69,0) -> 0 | AV69: =IF($G69=$AA$12,$AE69+$AG69+$AI69+AK69+AQ69,0) -> 0 | AW69: =IF($G69=$AA$12,$AF69+$AH69+$AJ69+AL69+AR69,0) -> 0 | AY69: =IF(UPPER($I69) =$AB$12,IF($G69=$AA$12,$AV69,0),0) -> 0 | AZ69: =IF(UPPER($I69) =$AB$12,IF($G69<>$AA$12,$AT69,0),0) -> 0 | BA69: =IF(UPPER($I69) =$AB$12,IF($G69=$AA$12,$AW69,0),0) -> 0 | BB69: =IF(UPPER($I69) =$AB$12,IF($G69<>$AA$12,$AU69,0),0) -> 0 | BC69: =IF(UPPER($J69) =$AB$12,IF($G69=$AA$12,$AV69,0),0) -> 0 | BD69: =IF(UPPER($J69) =$AB$12,IF($G69<>$AA$12,$AT69,0),0) -> 0 | BE69: =IF(UPPER($J69) =$AB$12,IF($G69=$AA$12,$AW69,0),0) -> 0 | BF69: =IF(UPPER($J69) =$AB$12,IF($G69<>$AA$12,$AU69,0),0) -> 0 | BG69: =IF(UPPER($K69) =$AB$12,IF($G69=$AA$12,$AV69,0),0) -> 0 | BH69: =IF(UPPER($K69) =$AB$12,IF($G69<>$AA$12,$AT69,0),0) -> 0 | BI69: =IF(UPPER($K69) =$AB$12,IF($G69=$AA$12,$AW69,0),0) -> 0 | BJ69: =IF(UPPER($K69) =$AB$12,IF($G69<>$AA$12,$AU69,0),0) -> 0 | BL69: =IF(($E69+$F69>0), IF($G69=$AA$10,1,0),0) -> 0 | BM69: =IF(($E69+$F69<=0), IF($G69<>$AA$10,1,0),0) -> 0 | BN69: =IF(($E69+$F69>0), IF($C69=$AA$10,1,0),0) -> 0
A70: 58 | AE70: =IF($C70=$Z$11,$E70,0) -> 0 | AF70: =IF($C70=$Z$11,$F70,0) -> 0 | AG70: =IF($C70=$Z$12,$E70,0) -> 0 | AH70: =IF($C70=$Z$12,$F70,0) -> 0 | AI70: =IF($C70=$Z$13,$E70,0) -> 0 | AJ70: =IF($C70=$Z$13,$F70,0) -> 0 | AK70: =IF($C70=$Z$14,$E70,0) -> 0 | AL70: =IF($C70=$Z$14,$F70,0) -> 0 | AM70: =IF($C70=$Z$15,$E70,0) -> 0 | AN70: =IF($C70=$Z$15,$F70,0) -> 0 | AO70: =IF($C70=$Z$16,$E70,0) -> 0 | AP70: =IF($C70=$Z$16,$F70,0) -> 0 | AQ70: =IF($C70=$Z$17,$E70,0) -> 0 | AR70: =IF($C70=$Z$17,$F70,0) -> 0 | AT70: =IF(OR($G70=$AA$11,$G70=$AA$13,($G70=$AA$14),$G70=$AA$15),$AE70+$AG70+$AI70+$AK70+$AQ70,0) -> 0 | AU70: =IF(OR($G70=$AA$11,$G70=$AA$13,($G70=$AA$14),$G70=$AA$15),$AF70+$AH70+$AJ70+AL70+AR70,0) -> 0 | AV70: =IF($G70=$AA$12,$AE70+$AG70+$AI70+AK70+AQ70,0) -> 0 | AW70: =IF($G70=$AA$12,$AF70+$AH70+$AJ70+AL70+AR70,0) -> 0 | AY70: =IF(UPPER($I70) =$AB$12,IF($G70=$AA$12,$AV70,0),0) -> 0 | AZ70: =IF(UPPER($I70) =$AB$12,IF($G70<>$AA$12,$AT70,0),0) -> 0 | BA70: =IF(UPPER($I70) =$AB$12,IF($G70=$AA$12,$AW70,0),0) -> 0 | BB70: =IF(UPPER($I70) =$AB$12,IF($G70<>$AA$12,$AU70,0),0) -> 0 | BC70: =IF(UPPER($J70) =$AB$12,IF($G70=$AA$12,$AV70,0),0) -> 0 | BD70: =IF(UPPER($J70) =$AB$12,IF($G70<>$AA$12,$AT70,0),0) -> 0 | BE70: =IF(UPPER($J70) =$AB$12,IF($G70=$AA$12,$AW70,0),0) -> 0 | BF70: =IF(UPPER($J70) =$AB$12,IF($G70<>$AA$12,$AU70,0),0) -> 0 | BG70: =IF(UPPER($K70) =$AB$12,IF($G70=$AA$12,$AV70,0),0) -> 0 | BH70: =IF(UPPER($K70) =$AB$12,IF($G70<>$AA$12,$AT70,0),0) -> 0 | BI70: =IF(UPPER($K70) =$AB$12,IF($G70=$AA$12,$AW70,0),0) -> 0 | BJ70: =IF(UPPER($K70) =$AB$12,IF($G70<>$AA$12,$AU70,0),0) -> 0 | BL70: =IF(($E70+$F70>0), IF($G70=$AA$10,1,0),0) -> 0 | BM70: =IF(($E70+$F70<=0), IF($G70<>$AA$10,1,0),0) -> 0 | BN70: =IF(($E70+$F70>0), IF($C70=$AA$10,1,0),0) -> 0
A71: 59 | AE71: =IF($C71=$Z$11,$E71,0) -> 0 | AF71: =IF($C71=$Z$11,$F71,0) -> 0 | AG71: =IF($C71=$Z$12,$E71,0) -> 0 | AH71: =IF($C71=$Z$12,$F71,0) -> 0 | AI71: =IF($C71=$Z$13,$E71,0) -> 0 | AJ71: =IF($C71=$Z$13,$F71,0) -> 0 | AK71: =IF($C71=$Z$14,$E71,0) -> 0 | AL71: =IF($C71=$Z$14,$F71,0) -> 0 | AM71: =IF($C71=$Z$15,$E71,0) -> 0 | AN71: =IF($C71=$Z$15,$F71,0) -> 0 | AO71: =IF($C71=$Z$16,$E71,0) -> 0 | AP71: =IF($C71=$Z$16,$F71,0) -> 0 | AQ71: =IF($C71=$Z$17,$E71,0) -> 0 | AR71: =IF($C71=$Z$17,$F71,0) -> 0 | AT71: =IF(OR($G71=$AA$11,$G71=$AA$13,($G71=$AA$14),$G71=$AA$15),$AE71+$AG71+$AI71+$AK71+$AQ71,0) -> 0 | AU71: =IF(OR($G71=$AA$11,$G71=$AA$13,($G71=$AA$14),$G71=$AA$15),$AF71+$AH71+$AJ71+AL71+AR71,0) -> 0 | AV71: =IF($G71=$AA$12,$AE71+$AG71+$AI71+AK71+AQ71,0) -> 0 | AW71: =IF($G71=$AA$12,$AF71+$AH71+$AJ71+AL71+AR71,0) -> 0 | AY71: =IF(UPPER($I71) =$AB$12,IF($G71=$AA$12,$AV71,0),0) -> 0 | AZ71: =IF(UPPER($I71) =$AB$12,IF($G71<>$AA$12,$AT71,0),0) -> 0 | BA71: =IF(UPPER($I71) =$AB$12,IF($G71=$AA$12,$AW71,0),0) -> 0 | BB71: =IF(UPPER($I71) =$AB$12,IF($G71<>$AA$12,$AU71,0),0) -> 0 | BC71: =IF(UPPER($J71) =$AB$12,IF($G71=$AA$12,$AV71,0),0) -> 0 | BD71: =IF(UPPER($J71) =$AB$12,IF($G71<>$AA$12,$AT71,0),0) -> 0 | BE71: =IF(UPPER($J71) =$AB$12,IF($G71=$AA$12,$AW71,0),0) -> 0 | BF71: =IF(UPPER($J71) =$AB$12,IF($G71<>$AA$12,$AU71,0),0) -> 0 | BG71: =IF(UPPER($K71) =$AB$12,IF($G71=$AA$12,$AV71,0),0) -> 0 | BH71: =IF(UPPER($K71) =$AB$12,IF($G71<>$AA$12,$AT71,0),0) -> 0 | BI71: =IF(UPPER($K71) =$AB$12,IF($G71=$AA$12,$AW71,0),0) -> 0 | BJ71: =IF(UPPER($K71) =$AB$12,IF($G71<>$AA$12,$AU71,0),0) -> 0 | BL71: =IF(($E71+$F71>0), IF($G71=$AA$10,1,0),0) -> 0 | BM71: =IF(($E71+$F71<=0), IF($G71<>$AA$10,1,0),0) -> 0 | BN71: =IF(($E71+$F71>0), IF($C71=$AA$10,1,0),0) -> 0
A72: 60 | AE72: =IF($C72=$Z$11,$E72,0) -> 0 | AF72: =IF($C72=$Z$11,$F72,0) -> 0 | AG72: =IF($C72=$Z$12,$E72,0) -> 0 | AH72: =IF($C72=$Z$12,$F72,0) -> 0 | AI72: =IF($C72=$Z$13,$E72,0) -> 0 | AJ72: =IF($C72=$Z$13,$F72,0) -> 0 | AK72: =IF($C72=$Z$14,$E72,0) -> 0 | AL72: =IF($C72=$Z$14,$F72,0) -> 0 | AM72: =IF($C72=$Z$15,$E72,0) -> 0 | AN72: =IF($C72=$Z$15,$F72,0) -> 0 | AO72: =IF($C72=$Z$16,$E72,0) -> 0 | AP72: =IF($C72=$Z$16,$F72,0) -> 0 | AQ72: =IF($C72=$Z$17,$E72,0) -> 0 | AR72: =IF($C72=$Z$17,$F72,0) -> 0 | AT72: =IF(OR($G72=$AA$11,$G72=$AA$13,($G72=$AA$14),$G72=$AA$15),$AE72+$AG72+$AI72+$AK72+$AQ72,0) -> 0 | AU72: =IF(OR($G72=$AA$11,$G72=$AA$13,($G72=$AA$14),$G72=$AA$15),$AF72+$AH72+$AJ72+AL72+AR72,0) -> 0 | AV72: =IF($G72=$AA$12,$AE72+$AG72+$AI72+AK72+AQ72,0) -> 0 | AW72: =IF($G72=$AA$12,$AF72+$AH72+$AJ72+AL72+AR72,0) -> 0 | AY72: =IF(UPPER($I72) =$AB$12,IF($G72=$AA$12,$AV72,0),0) -> 0 | AZ72: =IF(UPPER($I72) =$AB$12,IF($G72<>$AA$12,$AT72,0),0) -> 0 | BA72: =IF(UPPER($I72) =$AB$12,IF($G72=$AA$12,$AW72,0),0) -> 0 | BB72: =IF(UPPER($I72) =$AB$12,IF($G72<>$AA$12,$AU72,0),0) -> 0 | BC72: =IF(UPPER($J72) =$AB$12,IF($G72=$AA$12,$AV72,0),0) -> 0 | BD72: =IF(UPPER($J72) =$AB$12,IF($G72<>$AA$12,$AT72,0),0) -> 0 | BE72: =IF(UPPER($J72) =$AB$12,IF($G72=$AA$12,$AW72,0),0) -> 0 | BF72: =IF(UPPER($J72) =$AB$12,IF($G72<>$AA$12,$AU72,0),0) -> 0 | BG72: =IF(UPPER($K72) =$AB$12,IF($G72=$AA$12,$AV72,0),0) -> 0 | BH72: =IF(UPPER($K72) =$AB$12,IF($G72<>$AA$12,$AT72,0),0) -> 0 | BI72: =IF(UPPER($K72) =$AB$12,IF($G72=$AA$12,$AW72,0),0) -> 0 | BJ72: =IF(UPPER($K72) =$AB$12,IF($G72<>$AA$12,$AU72,0),0) -> 0 | BL72: =IF(($E72+$F72>0), IF($G72=$AA$10,1,0),0) -> 0 | BM72: =IF(($E72+$F72<=0), IF($G72<>$AA$10,1,0),0) -> 0 | BN72: =IF(($E72+$F72>0), IF($C72=$AA$10,1,0),0) -> 0
A73: 61 | AE73: =IF($C73=$Z$11,$E73,0) -> 0 | AF73: =IF($C73=$Z$11,$F73,0) -> 0 | AG73: =IF($C73=$Z$12,$E73,0) -> 0 | AH73: =IF($C73=$Z$12,$F73,0) -> 0 | AI73: =IF($C73=$Z$13,$E73,0) -> 0 | AJ73: =IF($C73=$Z$13,$F73,0) -> 0 | AK73: =IF($C73=$Z$14,$E73,0) -> 0 | AL73: =IF($C73=$Z$14,$F73,0) -> 0 | AM73: =IF($C73=$Z$15,$E73,0) -> 0 | AN73: =IF($C73=$Z$15,$F73,0) -> 0 | AO73: =IF($C73=$Z$16,$E73,0) -> 0 | AP73: =IF($C73=$Z$16,$F73,0) -> 0 | AQ73: =IF($C73=$Z$17,$E73,0) -> 0 | AR73: =IF($C73=$Z$17,$F73,0) -> 0 | AT73: =IF(OR($G73=$AA$11,$G73=$AA$13,($G73=$AA$14),$G73=$AA$15),$AE73+$AG73+$AI73+$AK73+$AQ73,0) -> 0 | AU73: =IF(OR($G73=$AA$11,$G73=$AA$13,($G73=$AA$14),$G73=$AA$15),$AF73+$AH73+$AJ73+AL73+AR73,0) -> 0 | AV73: =IF($G73=$AA$12,$AE73+$AG73+$AI73+AK73+AQ73,0) -> 0 | AW73: =IF($G73=$AA$12,$AF73+$AH73+$AJ73+AL73+AR73,0) -> 0 | AY73: =IF(UPPER($I73) =$AB$12,IF($G73=$AA$12,$AV73,0),0) -> 0 | AZ73: =IF(UPPER($I73) =$AB$12,IF($G73<>$AA$12,$AT73,0),0) -> 0 | BA73: =IF(UPPER($I73) =$AB$12,IF($G73=$AA$12,$AW73,0),0) -> 0 | BB73: =IF(UPPER($I73) =$AB$12,IF($G73<>$AA$12,$AU73,0),0) -> 0 | BC73: =IF(UPPER($J73) =$AB$12,IF($G73=$AA$12,$AV73,0),0) -> 0 | BD73: =IF(UPPER($J73) =$AB$12,IF($G73<>$AA$12,$AT73,0),0) -> 0 | BE73: =IF(UPPER($J73) =$AB$12,IF($G73=$AA$12,$AW73,0),0) -> 0 | BF73: =IF(UPPER($J73) =$AB$12,IF($G73<>$AA$12,$AU73,0),0) -> 0 | BG73: =IF(UPPER($K73) =$AB$12,IF($G73=$AA$12,$AV73,0),0) -> 0 | BH73: =IF(UPPER($K73) =$AB$12,IF($G73<>$AA$12,$AT73,0),0) -> 0 | BI73: =IF(UPPER($K73) =$AB$12,IF($G73=$AA$12,$AW73,0),0) -> 0 | BJ73: =IF(UPPER($K73) =$AB$12,IF($G73<>$AA$12,$AU73,0),0) -> 0 | BL73: =IF(($E73+$F73>0), IF($G73=$AA$10,1,0),0) -> 0 | BM73: =IF(($E73+$F73<=0), IF($G73<>$AA$10,1,0),0) -> 0 | BN73: =IF(($E73+$F73>0), IF($C73=$AA$10,1,0),0) -> 0
A74: 62 | AE74: =IF($C74=$Z$11,$E74,0) -> 0 | AF74: =IF($C74=$Z$11,$F74,0) -> 0 | AG74: =IF($C74=$Z$12,$E74,0) -> 0 | AH74: =IF($C74=$Z$12,$F74,0) -> 0 | AI74: =IF($C74=$Z$13,$E74,0) -> 0 | AJ74: =IF($C74=$Z$13,$F74,0) -> 0 | AK74: =IF($C74=$Z$14,$E74,0) -> 0 | AL74: =IF($C74=$Z$14,$F74,0) -> 0 | AM74: =IF($C74=$Z$15,$E74,0) -> 0 | AN74: =IF($C74=$Z$15,$F74,0) -> 0 | AO74: =IF($C74=$Z$16,$E74,0) -> 0 | AP74: =IF($C74=$Z$16,$F74,0) -> 0 | AQ74: =IF($C74=$Z$17,$E74,0) -> 0 | AR74: =IF($C74=$Z$17,$F74,0) -> 0 | AT74: =IF(OR($G74=$AA$11,$G74=$AA$13,($G74=$AA$14),$G74=$AA$15),$AE74+$AG74+$AI74+$AK74+$AQ74,0) -> 0 | AU74: =IF(OR($G74=$AA$11,$G74=$AA$13,($G74=$AA$14),$G74=$AA$15),$AF74+$AH74+$AJ74+AL74+AR74,0) -> 0 | AV74: =IF($G74=$AA$12,$AE74+$AG74+$AI74+AK74+AQ74,0) -> 0 | AW74: =IF($G74=$AA$12,$AF74+$AH74+$AJ74+AL74+AR74,0) -> 0 | AY74: =IF(UPPER($I74) =$AB$12,IF($G74=$AA$12,$AV74,0),0) -> 0 | AZ74: =IF(UPPER($I74) =$AB$12,IF($G74<>$AA$12,$AT74,0),0) -> 0 | BA74: =IF(UPPER($I74) =$AB$12,IF($G74=$AA$12,$AW74,0),0) -> 0 | BB74: =IF(UPPER($I74) =$AB$12,IF($G74<>$AA$12,$AU74,0),0) -> 0 | BC74: =IF(UPPER($J74) =$AB$12,IF($G74=$AA$12,$AV74,0),0) -> 0 | BD74: =IF(UPPER($J74) =$AB$12,IF($G74<>$AA$12,$AT74,0),0) -> 0 | BE74: =IF(UPPER($J74) =$AB$12,IF($G74=$AA$12,$AW74,0),0) -> 0 | BF74: =IF(UPPER($J74) =$AB$12,IF($G74<>$AA$12,$AU74,0),0) -> 0 | BG74: =IF(UPPER($K74) =$AB$12,IF($G74=$AA$12,$AV74,0),0) -> 0 | BH74: =IF(UPPER($K74) =$AB$12,IF($G74<>$AA$12,$AT74,0),0) -> 0 | BI74: =IF(UPPER($K74) =$AB$12,IF($G74=$AA$12,$AW74,0),0) -> 0 | BJ74: =IF(UPPER($K74) =$AB$12,IF($G74<>$AA$12,$AU74,0),0) -> 0 | BL74: =IF(($E74+$F74>0), IF($G74=$AA$10,1,0),0) -> 0 | BM74: =IF(($E74+$F74<=0), IF($G74<>$AA$10,1,0),0) -> 0 | BN74: =IF(($E74+$F74>0), IF($C74=$AA$10,1,0),0) -> 0
A75: 63 | AE75: =IF($C75=$Z$11,$E75,0) -> 0 | AF75: =IF($C75=$Z$11,$F75,0) -> 0 | AG75: =IF($C75=$Z$12,$E75,0) -> 0 | AH75: =IF($C75=$Z$12,$F75,0) -> 0 | AI75: =IF($C75=$Z$13,$E75,0) -> 0 | AJ75: =IF($C75=$Z$13,$F75,0) -> 0 | AK75: =IF($C75=$Z$14,$E75,0) -> 0 | AL75: =IF($C75=$Z$14,$F75,0) -> 0 | AM75: =IF($C75=$Z$15,$E75,0) -> 0 | AN75: =IF($C75=$Z$15,$F75,0) -> 0 | AO75: =IF($C75=$Z$16,$E75,0) -> 0 | AP75: =IF($C75=$Z$16,$F75,0) -> 0 | AQ75: =IF($C75=$Z$17,$E75,0) -> 0 | AR75: =IF($C75=$Z$17,$F75,0) -> 0 | AT75: =IF(OR($G75=$AA$11,$G75=$AA$13,($G75=$AA$14),$G75=$AA$15),$AE75+$AG75+$AI75+$AK75+$AQ75,0) -> 0 | AU75: =IF(OR($G75=$AA$11,$G75=$AA$13,($G75=$AA$14),$G75=$AA$15),$AF75+$AH75+$AJ75+AL75+AR75,0) -> 0 | AV75: =IF($G75=$AA$12,$AE75+$AG75+$AI75+AK75+AQ75,0) -> 0 | AW75: =IF($G75=$AA$12,$AF75+$AH75+$AJ75+AL75+AR75,0) -> 0 | AY75: =IF(UPPER($I75) =$AB$12,IF($G75=$AA$12,$AV75,0),0) -> 0 | AZ75: =IF(UPPER($I75) =$AB$12,IF($G75<>$AA$12,$AT75,0),0) -> 0 | BA75: =IF(UPPER($I75) =$AB$12,IF($G75=$AA$12,$AW75,0),0) -> 0 | BB75: =IF(UPPER($I75) =$AB$12,IF($G75<>$AA$12,$AU75,0),0) -> 0 | BC75: =IF(UPPER($J75) =$AB$12,IF($G75=$AA$12,$AV75,0),0) -> 0 | BD75: =IF(UPPER($J75) =$AB$12,IF($G75<>$AA$12,$AT75,0),0) -> 0 | BE75: =IF(UPPER($J75) =$AB$12,IF($G75=$AA$12,$AW75,0),0) -> 0 | BF75: =IF(UPPER($J75) =$AB$12,IF($G75<>$AA$12,$AU75,0),0) -> 0 | BG75: =IF(UPPER($K75) =$AB$12,IF($G75=$AA$12,$AV75,0),0) -> 0 | BH75: =IF(UPPER($K75) =$AB$12,IF($G75<>$AA$12,$AT75,0),0) -> 0 | BI75: =IF(UPPER($K75) =$AB$12,IF($G75=$AA$12,$AW75,0),0) -> 0 | BJ75: =IF(UPPER($K75) =$AB$12,IF($G75<>$AA$12,$AU75,0),0) -> 0 | BL75: =IF(($E75+$F75>0), IF($G75=$AA$10,1,0),0) -> 0 | BM75: =IF(($E75+$F75<=0), IF($G75<>$AA$10,1,0),0) -> 0 | BN75: =IF(($E75+$F75>0), IF($C75=$AA$10,1,0),0) -> 0
... A87: 75 | AE87: =IF($C87=$Z$11,$E87,0) -> 0 | AF87: =IF($C87=$Z$11,$F87,0) -> 0 | AG87: =IF($C87=$Z$12,$E87,0) -> 0 | AH87: =IF($C87=$Z$12,$F87,0) -> 0 | AI87: =IF($C87=$Z$13,$E87,0) -> 0 | AJ87: =IF($C87=$Z$13,$F87,0) -> 0 | AK87: =IF($C87=$Z$14,$E87,0) -> 0 | AL87: =IF($C87=$Z$14,$F87,0) -> 0 | AM87: =IF($C87=$Z$15,$E87,0) -> 0 | AN87: =IF($C87=$Z$15,$F87,0) -> 0 | AO87: =IF($C87=$Z$16,$E87,0) -> 0 | AP87: =IF($C87=$Z$16,$F87,0) -> 0 | AQ87: =IF($C87=$Z$17,$E87,0) -> 0 | AR87: =IF($C87=$Z$17,$F87,0) -> 0 | AT87: =IF(OR($G87=$AA$11,$G87=$AA$13,($G87=$AA$14),$G87=$AA$15),$AE87+$AG87+$AI87+$AK87+$AQ87,0) -> 0 | AU87: =IF(OR($G87=$AA$11,$G87=$AA$13,($G87=$AA$14),$G87=$AA$15),$AF87+$AH87+$AJ87+AL87+AR87,0) -> 0 | AV87: =IF($G87=$AA$12,$AE87+$AG87+$AI87+AK87+AQ87,0) -> 0 | AW87: =IF($G87=$AA$12,$AF87+$AH87+$AJ87+AL87+AR87,0) -> 0 | AY87: =IF(UPPER($I87) =$AB$12,IF($G87=$AA$12,$AV87,0),0) -> 0 | AZ87: =IF(UPPER($I87) =$AB$12,IF($G87<>$AA$12,$AT87,0),0) -> 0 | BA87: =IF(UPPER($I87) =$AB$12,IF($G87=$AA$12,$AW87,0),0) -> 0 | BB87: =IF(UPPER($I87) =$AB$12,IF($G87<>$AA$12,$AU87,0),0) -> 0 | BC87: =IF(UPPER($J87) =$AB$12,IF($G87=$AA$12,$AV87,0),0) -> 0 | BD87: =IF(UPPER($J87) =$AB$12,IF($G87<>$AA$12,$AT87,0),0) -> 0 | BE87: =IF(UPPER($J87) =$AB$12,IF($G87=$AA$12,$AW87,0),0) -> 0 | BF87: =IF(UPPER($J87) =$AB$12,IF($G87<>$AA$12,$AU87,0),0) -> 0 | BG87: =IF(UPPER($K87) =$AB$12,IF($G87=$AA$12,$AV87,0),0) -> 0 | BH87: =IF(UPPER($K87) =$AB$12,IF($G87<>$AA$12,$AT87,0),0) -> 0 | BI87: =IF(UPPER($K87) =$AB$12,IF($G87=$AA$12,$AW87,0),0) -> 0 | BJ87: =IF(UPPER($K87) =$AB$12,IF($G87<>$AA$12,$AU87,0),0) -> 0 | BL87: =IF(($E87+$F87>0), IF($G87=$AA$10,1,0),0) -> 0 | BM87: =IF(($E87+$F87<=0), IF($G87<>$AA$10,1,0),0) -> 0 | BN87: =IF(($E87+$F87>0), IF($C87=$AA$10,1,0),0) -> 0
AE88: =IF($C88=$Z$11,$E88,0) -> 0 | AF88: =IF($C88=$Z$11,$F88,0) -> 0 | AG88: =IF($C88=$Z$12,$E88,0) -> 0 | AH88: =IF($C88=$Z$12,$F88,0) -> 0 | AI88: =IF($C88=$Z$13,$E88,0) -> 0 | AJ88: =IF($C88=$Z$13,$F88,0) -> 0 | AK88: =IF($C88=$Z$14,$E88,0) -> 0 | AL88: =IF($C88=$Z$14,$F88,0) -> 0 | AM88: =IF($C88=$Z$15,$E88,0) -> 0 | AN88: =IF($C88=$Z$15,$F88,0) -> 0 | AO88: =IF($C88=$Z$16,$E88,0) -> 0 | AP88: =IF($C88=$Z$16,$F88,0) -> 0 | AQ88: =IF($C88=$Z$17,$E88,0) -> 0 | AR88: =IF($C88=$Z$17,$F88,0) -> 0 | AT88: =IF(OR($G88=$AA$11,$G88=$AA$13,($G88=$AA$14),$G88=$AA$15),$AE88+$AG88+$AI88+$AK88+$AQ88,0) -> 0 | AU88: =IF(OR($G88=$AA$11,$G88=$AA$13,($G88=$AA$14),$G88=$AA$15),$AF88+$AH88+$AJ88+AL88+AR88,0) -> 0 | AV88: =IF($G88=$AA$12,$AE88+$AG88+$AI88+AK88+AQ88,0) -> 0 | AW88: =IF($G88=$AA$12,$AF88+$AH88+$AJ88+AL88+AR88,0) -> 0 | AY88: =IF(UPPER($I88) =$AB$12,IF($G88=$AA$12,$AV88,0),0) -> 0 | AZ88: =IF(UPPER($I88) =$AB$12,IF($G88<>$AA$12,$AT88,0),0) -> 0 | BA88: =IF(UPPER($I88) =$AB$12,IF($G88=$AA$12,$AW88,0),0) -> 0 | BB88: =IF(UPPER($I88) =$AB$12,IF($G88<>$AA$12,$AU88,0),0) -> 0 | BC88: =IF(UPPER($J88) =$AB$12,IF($G88=$AA$12,$AV88,0),0) -> 0 | BD88: =IF(UPPER($J88) =$AB$12,IF($G88<>$AA$12,$AT88,0),0) -> 0 | BE88: =IF(UPPER($J88) =$AB$12,IF($G88=$AA$12,$AW88,0),0) -> 0 | BF88: =IF(UPPER($J88) =$AB$12,IF($G88<>$AA$12,$AU88,0),0) -> 0 | BG88: =IF(UPPER($K88) =$AB$12,IF($G88=$AA$12,$AV88,0),0) -> 0 | BH88: =IF(UPPER($K88) =$AB$12,IF($G88<>$AA$12,$AT88,0),0) -> 0 | BI88: =IF(UPPER($K88) =$AB$12,IF($G88=$AA$12,$AW88,0),0) -> 0 | BJ88: =IF(UPPER($K88) =$AB$12,IF($G88<>$AA$12,$AU88,0),0) -> 0 | BL88: =IF(($E88+$F88>0), IF($G88=$AA$10,1,0),0) -> 0 | BM88: =IF(($E88+$F88<=0), IF($G88<>$AA$10,1,0),0) -> 0 | BN88: =IF(($E88+$F88>0), IF($C88=$AA$10,1,0),0) -> 0
A89: 76 | L89: PAGINA 4
A90: 77 | AE90: =IF($C90=$Z$11,$E90,0) -> 0 | AF90: =IF($C90=$Z$11,$F90,0) -> 0 | AG90: =IF($C90=$Z$12,$E90,0) -> 0 | AH90: =IF($C90=$Z$12,$F90,0) -> 0 | AI90: =IF($C90=$Z$13,$E90,0) -> 0 | AJ90: =IF($C90=$Z$13,$F90,0) -> 0 | AK90: =IF($C90=$Z$14,$E90,0) -> 0 | AL90: =IF($C90=$Z$14,$F90,0) -> 0 | AM90: =IF($C90=$Z$15,$E90,0) -> 0 | AN90: =IF($C90=$Z$15,$F90,0) -> 0 | AO90: =IF($C90=$Z$16,$E90,0) -> 0 | AP90: =IF($C90=$Z$16,$F90,0) -> 0 | AQ90: =IF($C90=$Z$17,$E90,0) -> 0 | AR90: =IF($C90=$Z$17,$F90,0) -> 0 | AT90: =IF(OR($G90=$AA$11,$G90=$AA$13,($G90=$AA$14),$G90=$AA$15),$AE90+$AG90+$AI90+$AK90+$AQ90,0) -> 0 | AU90: =IF(OR($G90=$AA$11,$G90=$AA$13,($G90=$AA$14),$G90=$AA$15),$AF90+$AH90+$AJ90+AL90+AR90,0) -> 0 | AV90: =IF($G90=$AA$12,$AE90+$AG90+$AI90+AK90+AQ90,0) -> 0 | AW90: =IF($G90=$AA$12,$AF90+$AH90+$AJ90+AL90+AR90,0) -> 0 | AY90: =IF(UPPER($I90) =$AB$12,IF($G90=$AA$12,$AV90,0),0) -> 0 | AZ90: =IF(UPPER($I90) =$AB$12,IF($G90<>$AA$12,$AT90,0),0) -> 0 | BA90: =IF(UPPER($I90) =$AB$12,IF($G90=$AA$12,$AW90,0),0) -> 0 | BB90: =IF(UPPER($I90) =$AB$12,IF($G90<>$AA$12,$AU90,0),0) -> 0 | BC90: =IF(UPPER($J90) =$AB$12,IF($G90=$AA$12,$AV90,0),0) -> 0 | BD90: =IF(UPPER($J90) =$AB$12,IF($G90<>$AA$12,$AT90,0),0) -> 0 | BE90: =IF(UPPER($J90) =$AB$12,IF($G90=$AA$12,$AW90,0),0) -> 0 | BF90: =IF(UPPER($J90) =$AB$12,IF($G90<>$AA$12,$AU90,0),0) -> 0 | BG90: =IF(UPPER($K90) =$AB$12,IF($G90=$AA$12,$AV90,0),0) -> 0 | BH90: =IF(UPPER($K90) =$AB$12,IF($G90<>$AA$12,$AT90,0),0) -> 0 | BI90: =IF(UPPER($K90) =$AB$12,IF($G90=$AA$12,$AW90,0),0) -> 0 | BJ90: =IF(UPPER($K90) =$AB$12,IF($G90<>$AA$12,$AU90,0),0) -> 0 | BL90: =IF(($E90+$F90>0), IF($G90=$AA$10,1,0),0) -> 0 | BM90: =IF(($E90+$F90<=0), IF($G90<>$AA$10,1,0),0) -> 0 | BN90: =IF(($E90+$F90>0), IF($C90=$AA$10,1,0),0) -> 0
A91: 78 | AE91: =IF($C91=$Z$11,$E91,0) -> 0 | AF91: =IF($C91=$Z$11,$F91,0) -> 0 | AG91: =IF($C91=$Z$12,$E91,0) -> 0 | AH91: =IF($C91=$Z$12,$F91,0) -> 0 | AI91: =IF($C91=$Z$13,$E91,0) -> 0 | AJ91: =IF($C91=$Z$13,$F91,0) -> 0 | AK91: =IF($C91=$Z$14,$E91,0) -> 0 | AL91: =IF($C91=$Z$14,$F91,0) -> 0 | AM91: =IF($C91=$Z$15,$E91,0) -> 0 | AN91: =IF($C91=$Z$15,$F91,0) -> 0 | AO91: =IF($C91=$Z$16,$E91,0) -> 0 | AP91: =IF($C91=$Z$16,$F91,0) -> 0 | AQ91: =IF($C91=$Z$17,$E91,0) -> 0 | AR91: =IF($C91=$Z$17,$F91,0) -> 0 | AT91: =IF(OR($G91=$AA$11,$G91=$AA$13,($G91=$AA$14),$G91=$AA$15),$AE91+$AG91+$AI91+$AK91+$AQ91,0) -> 0 | AU91: =IF(OR($G91=$AA$11,$G91=$AA$13,($G91=$AA$14),$G91=$AA$15),$AF91+$AH91+$AJ91+AL91+AR91,0) -> 0 | AV91: =IF($G91=$AA$12,$AE91+$AG91+$AI91+AK91+AQ91,0) -> 0 | AW91: =IF($G91=$AA$12,$AF91+$AH91+$AJ91+AL91+AR91,0) -> 0 | AY91: =IF(UPPER($I91) =$AB$12,IF($G91=$AA$12,$AV91,0),0) -> 0 | AZ91: =IF(UPPER($I91) =$AB$12,IF($G91<>$AA$12,$AT91,0),0) -> 0 | BA91: =IF(UPPER($I91) =$AB$12,IF($G91=$AA$12,$AW91,0),0) -> 0 | BB91: =IF(UPPER($I91) =$AB$12,IF($G91<>$AA$12,$AU91,0),0) -> 0 | BC91: =IF(UPPER($J91) =$AB$12,IF($G91=$AA$12,$AV91,0),0) -> 0 | BD91: =IF(UPPER($J91) =$AB$12,IF($G91<>$AA$12,$AT91,0),0) -> 0 | BE91: =IF(UPPER($J91) =$AB$12,IF($G91=$AA$12,$AW91,0),0) -> 0 | BF91: =IF(UPPER($J91) =$AB$12,IF($G91<>$AA$12,$AU91,0),0) -> 0 | BG91: =IF(UPPER($K91) =$AB$12,IF($G91=$AA$12,$AV91,0),0) -> 0 | BH91: =IF(UPPER($K91) =$AB$12,IF($G91<>$AA$12,$AT91,0),0) -> 0 | BI91: =IF(UPPER($K91) =$AB$12,IF($G91=$AA$12,$AW91,0),0) -> 0 | BJ91: =IF(UPPER($K91) =$AB$12,IF($G91<>$AA$12,$AU91,0),0) -> 0 | BL91: =IF(($E91+$F91>0), IF($G91=$AA$10,1,0),0) -> 0 | BM91: =IF(($E91+$F91<=0), IF($G91<>$AA$10,1,0),0) -> 0 | BN91: =IF(($E91+$F91>0), IF($C91=$AA$10,1,0),0) -> 0
A92: 79 | AE92: =IF($C92=$Z$11,$E92,0) -> 0 | AF92: =IF($C92=$Z$11,$F92,0) -> 0 | AG92: =IF($C92=$Z$12,$E92,0) -> 0 | AH92: =IF($C92=$Z$12,$F92,0) -> 0 | AI92: =IF($C92=$Z$13,$E92,0) -> 0 | AJ92: =IF($C92=$Z$13,$F92,0) -> 0 | AK92: =IF($C92=$Z$14,$E92,0) -> 0 | AL92: =IF($C92=$Z$14,$F92,0) -> 0 | AM92: =IF($C92=$Z$15,$E92,0) -> 0 | AN92: =IF($C92=$Z$15,$F92,0) -> 0 | AO92: =IF($C92=$Z$16,$E92,0) -> 0 | AP92: =IF($C92=$Z$16,$F92,0) -> 0 | AQ92: =IF($C92=$Z$17,$E92,0) -> 0 | AR92: =IF($C92=$Z$17,$F92,0) -> 0 | AT92: =IF(OR($G92=$AA$11,$G92=$AA$13,($G92=$AA$14),$G92=$AA$15),$AE92+$AG92+$AI92+$AK92+$AQ92,0) -> 0 | AU92: =IF(OR($G92=$AA$11,$G92=$AA$13,($G92=$AA$14),$G92=$AA$15),$AF92+$AH92+$AJ92+AL92+AR92,0) -> 0 | AV92: =IF($G92=$AA$12,$AE92+$AG92+$AI92+AK92+AQ92,0) -> 0 | AW92: =IF($G92=$AA$12,$AF92+$AH92+$AJ92+AL92+AR92,0) -> 0 | AY92: =IF(UPPER($I92) =$AB$12,IF($G92=$AA$12,$AV92,0),0) -> 0 | AZ92: =IF(UPPER($I92) =$AB$12,IF($G92<>$AA$12,$AT92,0),0) -> 0 | BA92: =IF(UPPER($I92) =$AB$12,IF($G92=$AA$12,$AW92,0),0) -> 0 | BB92: =IF(UPPER($I92) =$AB$12,IF($G92<>$AA$12,$AU92,0),0) -> 0 | BC92: =IF(UPPER($J92) =$AB$12,IF($G92=$AA$12,$AV92,0),0) -> 0 | BD92: =IF(UPPER($J92) =$AB$12,IF($G92<>$AA$12,$AT92,0),0) -> 0 | BE92: =IF(UPPER($J92) =$AB$12,IF($G92=$AA$12,$AW92,0),0) -> 0 | BF92: =IF(UPPER($J92) =$AB$12,IF($G92<>$AA$12,$AU92,0),0) -> 0 | BG92: =IF(UPPER($K92) =$AB$12,IF($G92=$AA$12,$AV92,0),0) -> 0 | BH92: =IF(UPPER($K92) =$AB$12,IF($G92<>$AA$12,$AT92,0),0) -> 0 | BI92: =IF(UPPER($K92) =$AB$12,IF($G92=$AA$12,$AW92,0),0) -> 0 | BJ92: =IF(UPPER($K92) =$AB$12,IF($G92<>$AA$12,$AU92,0),0) -> 0 | BL92: =IF(($E92+$F92>0), IF($G92=$AA$10,1,0),0) -> 0 | BM92: =IF(($E92+$F92<=0), IF($G92<>$AA$10,1,0),0) -> 0 | BN92: =IF(($E92+$F92>0), IF($C92=$AA$10,1,0),0) -> 0
A93: 80 | AE93: =IF($C93=$Z$11,$E93,0) -> 0 | AF93: =IF($C93=$Z$11,$F93,0) -> 0 | AG93: =IF($C93=$Z$12,$E93,0) -> 0 | AH93: =IF($C93=$Z$12,$F93,0) -> 0 | AI93: =IF($C93=$Z$13,$E93,0) -> 0 | AJ93: =IF($C93=$Z$13,$F93,0) -> 0 | AK93: =IF($C93=$Z$14,$E93,0) -> 0 | AL93: =IF($C93=$Z$14,$F93,0) -> 0 | AM93: =IF($C93=$Z$15,$E93,0) -> 0 | AN93: =IF($C93=$Z$15,$F93,0) -> 0 | AO93: =IF($C93=$Z$16,$E93,0) -> 0 | AP93: =IF($C93=$Z$16,$F93,0) -> 0 | AQ93: =IF($C93=$Z$17,$E93,0) -> 0 | AR93: =IF($C93=$Z$17,$F93,0) -> 0 | AT93: =IF(OR($G93=$AA$11,$G93=$AA$13,($G93=$AA$14),$G93=$AA$15),$AE93+$AG93+$AI93+$AK93+$AQ93,0) -> 0 | AU93: =IF(OR($G93=$AA$11,$G93=$AA$13,($G93=$AA$14),$G93=$AA$15),$AF93+$AH93+$AJ93+AL93+AR93,0) -> 0 | AV93: =IF($G93=$AA$12,$AE93+$AG93+$AI93+AK93+AQ93,0) -> 0 | AW93: =IF($G93=$AA$12,$AF93+$AH93+$AJ93+AL93+AR93,0) -> 0 | AY93: =IF(UPPER($I93) =$AB$12,IF($G93=$AA$12,$AV93,0),0) -> 0 | AZ93: =IF(UPPER($I93) =$AB$12,IF($G93<>$AA$12,$AT93,0),0) -> 0 | BA93: =IF(UPPER($I93) =$AB$12,IF($G93=$AA$12,$AW93,0),0) -> 0 | BB93: =IF(UPPER($I93) =$AB$12,IF($G93<>$AA$12,$AU93,0),0) -> 0 | BC93: =IF(UPPER($J93) =$AB$12,IF($G93=$AA$12,$AV93,0),0) -> 0 | BD93: =IF(UPPER($J93) =$AB$12,IF($G93<>$AA$12,$AT93,0),0) -> 0 | BE93: =IF(UPPER($J93) =$AB$12,IF($G93=$AA$12,$AW93,0),0) -> 0 | BF93: =IF(UPPER($J93) =$AB$12,IF($G93<>$AA$12,$AU93,0),0) -> 0 | BG93: =IF(UPPER($K93) =$AB$12,IF($G93=$AA$12,$AV93,0),0) -> 0 | BH93: =IF(UPPER($K93) =$AB$12,IF($G93<>$AA$12,$AT93,0),0) -> 0 | BI93: =IF(UPPER($K93) =$AB$12,IF($G93=$AA$12,$AW93,0),0) -> 0 | BJ93: =IF(UPPER($K93) =$AB$12,IF($G93<>$AA$12,$AU93,0),0) -> 0 | BL93: =IF(($E93+$F93>0), IF($G93=$AA$10,1,0),0) -> 0 | BM93: =IF(($E93+$F93<=0), IF($G93<>$AA$10,1,0),0) -> 0 | BN93: =IF(($E93+$F93>0), IF($C93=$AA$10,1,0),0) -> 0
A94: 81 | AE94: =IF($C94=$Z$11,$E94,0) -> 0 | AF94: =IF($C94=$Z$11,$F94,0) -> 0 | AG94: =IF($C94=$Z$12,$E94,0) -> 0 | AH94: =IF($C94=$Z$12,$F94,0) -> 0 | AI94: =IF($C94=$Z$13,$E94,0) -> 0 | AJ94: =IF($C94=$Z$13,$F94,0) -> 0 | AK94: =IF($C94=$Z$14,$E94,0) -> 0 | AL94: =IF($C94=$Z$14,$F94,0) -> 0 | AM94: =IF($C94=$Z$15,$E94,0) -> 0 | AN94: =IF($C94=$Z$15,$F94,0) -> 0 | AO94: =IF($C94=$Z$16,$E94,0) -> 0 | AP94: =IF($C94=$Z$16,$F94,0) -> 0 | AQ94: =IF($C94=$Z$17,$E94,0) -> 0 | AR94: =IF($C94=$Z$17,$F94,0) -> 0 | AT94: =IF(OR($G94=$AA$11,$G94=$AA$13,($G94=$AA$14),$G94=$AA$15),$AE94+$AG94+$AI94+$AK94+$AQ94,0) -> 0 | AU94: =IF(OR($G94=$AA$11,$G94=$AA$13,($G94=$AA$14),$G94=$AA$15),$AF94+$AH94+$AJ94+AL94+AR94,0) -> 0 | AV94: =IF($G94=$AA$12,$AE94+$AG94+$AI94+AK94+AQ94,0) -> 0 | AW94: =IF($G94=$AA$12,$AF94+$AH94+$AJ94+AL94+AR94,0) -> 0 | AY94: =IF(UPPER($I94) =$AB$12,IF($G94=$AA$12,$AV94,0),0) -> 0 | AZ94: =IF(UPPER($I94) =$AB$12,IF($G94<>$AA$12,$AT94,0),0) -> 0 | BA94: =IF(UPPER($I94) =$AB$12,IF($G94=$AA$12,$AW94,0),0) -> 0 | BB94: =IF(UPPER($I94) =$AB$12,IF($G94<>$AA$12,$AU94,0),0) -> 0 | BC94: =IF(UPPER($J94) =$AB$12,IF($G94=$AA$12,$AV94,0),0) -> 0 | BD94: =IF(UPPER($J94) =$AB$12,IF($G94<>$AA$12,$AT94,0),0) -> 0 | BE94: =IF(UPPER($J94) =$AB$12,IF($G94=$AA$12,$AW94,0),0) -> 0 | BF94: =IF(UPPER($J94) =$AB$12,IF($G94<>$AA$12,$AU94,0),0) -> 0 | BG94: =IF(UPPER($K94) =$AB$12,IF($G94=$AA$12,$AV94,0),0) -> 0 | BH94: =IF(UPPER($K94) =$AB$12,IF($G94<>$AA$12,$AT94,0),0) -> 0 | BI94: =IF(UPPER($K94) =$AB$12,IF($G94=$AA$12,$AW94,0),0) -> 0 | BJ94: =IF(UPPER($K94) =$AB$12,IF($G94<>$AA$12,$AU94,0),0) -> 0 | BL94: =IF(($E94+$F94>0), IF($G94=$AA$10,1,0),0) -> 0 | BM94: =IF(($E94+$F94<=0), IF($G94<>$AA$10,1,0),0) -> 0 | BN94: =IF(($E94+$F94>0), IF($C94=$AA$10,1,0),0) -> 0
A95: 82 | AE95: =IF($C95=$Z$11,$E95,0) -> 0 | AF95: =IF($C95=$Z$11,$F95,0) -> 0 | AG95: =IF($C95=$Z$12,$E95,0) -> 0 | AH95: =IF($C95=$Z$12,$F95,0) -> 0 | AI95: =IF($C95=$Z$13,$E95,0) -> 0 | AJ95: =IF($C95=$Z$13,$F95,0) -> 0 | AK95: =IF($C95=$Z$14,$E95,0) -> 0 | AL95: =IF($C95=$Z$14,$F95,0) -> 0 | AM95: =IF($C95=$Z$15,$E95,0) -> 0 | AN95: =IF($C95=$Z$15,$F95,0) -> 0 | AO95: =IF($C95=$Z$16,$E95,0) -> 0 | AP95: =IF($C95=$Z$16,$F95,0) -> 0 | AQ95: =IF($C95=$Z$17,$E95,0) -> 0 | AR95: =IF($C95=$Z$17,$F95,0) -> 0 | AT95: =IF(OR($G95=$AA$11,$G95=$AA$13,($G95=$AA$14),$G95=$AA$15),$AE95+$AG95+$AI95+$AK95+$AQ95,0) -> 0 | AU95: =IF(OR($G95=$AA$11,$G95=$AA$13,($G95=$AA$14),$G95=$AA$15),$AF95+$AH95+$AJ95+AL95+AR95,0) -> 0 | AV95: =IF($G95=$AA$12,$AE95+$AG95+$AI95+AK95+AQ95,0) -> 0 | AW95: =IF($G95=$AA$12,$AF95+$AH95+$AJ95+AL95+AR95,0) -> 0 | AY95: =IF(UPPER($I95) =$AB$12,IF($G95=$AA$12,$AV95,0),0) -> 0 | AZ95: =IF(UPPER($I95) =$AB$12,IF($G95<>$AA$12,$AT95,0),0) -> 0 | BA95: =IF(UPPER($I95) =$AB$12,IF($G95=$AA$12,$AW95,0),0) -> 0 | BB95: =IF(UPPER($I95) =$AB$12,IF($G95<>$AA$12,$AU95,0),0) -> 0 | BC95: =IF(UPPER($J95) =$AB$12,IF($G95=$AA$12,$AV95,0),0) -> 0 | BD95: =IF(UPPER($J95) =$AB$12,IF($G95<>$AA$12,$AT95,0),0) -> 0 | BE95: =IF(UPPER($J95) =$AB$12,IF($G95=$AA$12,$AW95,0),0) -> 0 | BF95: =IF(UPPER($J95) =$AB$12,IF($G95<>$AA$12,$AU95,0),0) -> 0 | BG95: =IF(UPPER($K95) =$AB$12,IF($G95=$AA$12,$AV95,0),0) -> 0 | BH95: =IF(UPPER($K95) =$AB$12,IF($G95<>$AA$12,$AT95,0),0) -> 0 | BI95: =IF(UPPER($K95) =$AB$12,IF($G95=$AA$12,$AW95,0),0) -> 0 | BJ95: =IF(UPPER($K95) =$AB$12,IF($G95<>$AA$12,$AU95,0),0) -> 0 | BL95: =IF(($E95+$F95>0), IF($G95=$AA$10,1,0),0) -> 0 | BM95: =IF(($E95+$F95<=0), IF($G95<>$AA$10,1,0),0) -> 0 | BN95: =IF(($E95+$F95>0), IF($C95=$AA$10,1,0),0) -> 0
A96: 83 | AE96: =IF($C96=$Z$11,$E96,0) -> 0 | AF96: =IF($C96=$Z$11,$F96,0) -> 0 | AG96: =IF($C96=$Z$12,$E96,0) -> 0 | AH96: =IF($C96=$Z$12,$F96,0) -> 0 | AI96: =IF($C96=$Z$13,$E96,0) -> 0 | AJ96: =IF($C96=$Z$13,$F96,0) -> 0 | AK96: =IF($C96=$Z$14,$E96,0) -> 0 | AL96: =IF($C96=$Z$14,$F96,0) -> 0 | AM96: =IF($C96=$Z$15,$E96,0) -> 0 | AN96: =IF($C96=$Z$15,$F96,0) -> 0 | AO96: =IF($C96=$Z$16,$E96,0) -> 0 | AP96: =IF($C96=$Z$16,$F96,0) -> 0 | AQ96: =IF($C96=$Z$17,$E96,0) -> 0 | AR96: =IF($C96=$Z$17,$F96,0) -> 0 | AT96: =IF(OR($G96=$AA$11,$G96=$AA$13,($G96=$AA$14),$G96=$AA$15),$AE96+$AG96+$AI96+$AK96+$AQ96,0) -> 0 | AU96: =IF(OR($G96=$AA$11,$G96=$AA$13,($G96=$AA$14),$G96=$AA$15),$AF96+$AH96+$AJ96+AL96+AR96,0) -> 0 | AV96: =IF($G96=$AA$12,$AE96+$AG96+$AI96+AK96+AQ96,0) -> 0 | AW96: =IF($G96=$AA$12,$AF96+$AH96+$AJ96+AL96+AR96,0) -> 0 | AY96: =IF(UPPER($I96) =$AB$12,IF($G96=$AA$12,$AV96,0),0) -> 0 | AZ96: =IF(UPPER($I96) =$AB$12,IF($G96<>$AA$12,$AT96,0),0) -> 0 | BA96: =IF(UPPER($I96) =$AB$12,IF($G96=$AA$12,$AW96,0),0) -> 0 | BB96: =IF(UPPER($I96) =$AB$12,IF($G96<>$AA$12,$AU96,0),0) -> 0 | BC96: =IF(UPPER($J96) =$AB$12,IF($G96=$AA$12,$AV96,0),0) -> 0 | BD96: =IF(UPPER($J96) =$AB$12,IF($G96<>$AA$12,$AT96,0),0) -> 0 | BE96: =IF(UPPER($J96) =$AB$12,IF($G96=$AA$12,$AW96,0),0) -> 0 | BF96: =IF(UPPER($J96) =$AB$12,IF($G96<>$AA$12,$AU96,0),0) -> 0 | BG96: =IF(UPPER($K96) =$AB$12,IF($G96=$AA$12,$AV96,0),0) -> 0 | BH96: =IF(UPPER($K96) =$AB$12,IF($G96<>$AA$12,$AT96,0),0) -> 0 | BI96: =IF(UPPER($K96) =$AB$12,IF($G96=$AA$12,$AW96,0),0) -> 0 | BJ96: =IF(UPPER($K96) =$AB$12,IF($G96<>$AA$12,$AU96,0),0) -> 0 | BL96: =IF(($E96+$F96>0), IF($G96=$AA$10,1,0),0) -> 0 | BM96: =IF(($E96+$F96<=0), IF($G96<>$AA$10,1,0),0) -> 0 | BN96: =IF(($E96+$F96>0), IF($C96=$AA$10,1,0),0) -> 0
A97: 84 | AE97: =IF($C97=$Z$11,$E97,0) -> 0 | AF97: =IF($C97=$Z$11,$F97,0) -> 0 | AG97: =IF($C97=$Z$12,$E97,0) -> 0 | AH97: =IF($C97=$Z$12,$F97,0) -> 0 | AI97: =IF($C97=$Z$13,$E97,0) -> 0 | AJ97: =IF($C97=$Z$13,$F97,0) -> 0 | AK97: =IF($C97=$Z$14,$E97,0) -> 0 | AL97: =IF($C97=$Z$14,$F97,0) -> 0 | AM97: =IF($C97=$Z$15,$E97,0) -> 0 | AN97: =IF($C97=$Z$15,$F97,0) -> 0 | AO97: =IF($C97=$Z$16,$E97,0) -> 0 | AP97: =IF($C97=$Z$16,$F97,0) -> 0 | AQ97: =IF($C97=$Z$17,$E97,0) -> 0 | AR97: =IF($C97=$Z$17,$F97,0) -> 0 | AT97: =IF(OR($G97=$AA$11,$G97=$AA$13,($G97=$AA$14),$G97=$AA$15),$AE97+$AG97+$AI97+$AK97+$AQ97,0) -> 0 | AU97: =IF(OR($G97=$AA$11,$G97=$AA$13,($G97=$AA$14),$G97=$AA$15),$AF97+$AH97+$AJ97+AL97+AR97,0) -> 0 | AV97: =IF($G97=$AA$12,$AE97+$AG97+$AI97+AK97+AQ97,0) -> 0 | AW97: =IF($G97=$AA$12,$AF97+$AH97+$AJ97+AL97+AR97,0) -> 0 | AY97: =IF(UPPER($I97) =$AB$12,IF($G97=$AA$12,$AV97,0),0) -> 0 | AZ97: =IF(UPPER($I97) =$AB$12,IF($G97<>$AA$12,$AT97,0),0) -> 0 | BA97: =IF(UPPER($I97) =$AB$12,IF($G97=$AA$12,$AW97,0),0) -> 0 | BB97: =IF(UPPER($I97) =$AB$12,IF($G97<>$AA$12,$AU97,0),0) -> 0 | BC97: =IF(UPPER($J97) =$AB$12,IF($G97=$AA$12,$AV97,0),0) -> 0 | BD97: =IF(UPPER($J97) =$AB$12,IF($G97<>$AA$12,$AT97,0),0) -> 0 | BE97: =IF(UPPER($J97) =$AB$12,IF($G97=$AA$12,$AW97,0),0) -> 0 | BF97: =IF(UPPER($J97) =$AB$12,IF($G97<>$AA$12,$AU97,0),0) -> 0 | BG97: =IF(UPPER($K97) =$AB$12,IF($G97=$AA$12,$AV97,0),0) -> 0 | BH97: =IF(UPPER($K97) =$AB$12,IF($G97<>$AA$12,$AT97,0),0) -> 0 | BI97: =IF(UPPER($K97) =$AB$12,IF($G97=$AA$12,$AW97,0),0) -> 0 | BJ97: =IF(UPPER($K97) =$AB$12,IF($G97<>$AA$12,$AU97,0),0) -> 0 | BL97: =IF(($E97+$F97>0), IF($G97=$AA$10,1,0),0) -> 0 | BM97: =IF(($E97+$F97<=0), IF($G97<>$AA$10,1,0),0) -> 0 | BN97: =IF(($E97+$F97>0), IF($C97=$AA$10,1,0),0) -> 0
A98: 85 | AE98: =IF($C98=$Z$11,$E98,0) -> 0 | AF98: =IF($C98=$Z$11,$F98,0) -> 0 | AG98: =IF($C98=$Z$12,$E98,0) -> 0 | AH98: =IF($C98=$Z$12,$F98,0) -> 0 | AI98: =IF($C98=$Z$13,$E98,0) -> 0 | AJ98: =IF($C98=$Z$13,$F98,0) -> 0 | AK98: =IF($C98=$Z$14,$E98,0) -> 0 | AL98: =IF($C98=$Z$14,$F98,0) -> 0 | AM98: =IF($C98=$Z$15,$E98,0) -> 0 | AN98: =IF($C98=$Z$15,$F98,0) -> 0 | AO98: =IF($C98=$Z$16,$E98,0) -> 0 | AP98: =IF($C98=$Z$16,$F98,0) -> 0 | AQ98: =IF($C98=$Z$17,$E98,0) -> 0 | AR98: =IF($C98=$Z$17,$F98,0) -> 0 | AT98: =IF(OR($G98=$AA$11,$G98=$AA$13,($G98=$AA$14),$G98=$AA$15),$AE98+$AG98+$AI98+$AK98+$AQ98,0) -> 0 | AU98: =IF(OR($G98=$AA$11,$G98=$AA$13,($G98=$AA$14),$G98=$AA$15),$AF98+$AH98+$AJ98+AL98+AR98,0) -> 0 | AV98: =IF($G98=$AA$12,$AE98+$AG98+$AI98+AK98+AQ98,0) -> 0 | AW98: =IF($G98=$AA$12,$AF98+$AH98+$AJ98+AL98+AR98,0) -> 0 | AY98: =IF(UPPER($I98) =$AB$12,IF($G98=$AA$12,$AV98,0),0) -> 0 | AZ98: =IF(UPPER($I98) =$AB$12,IF($G98<>$AA$12,$AT98,0),0) -> 0 | BA98: =IF(UPPER($I98) =$AB$12,IF($G98=$AA$12,$AW98,0),0) -> 0 | BB98: =IF(UPPER($I98) =$AB$12,IF($G98<>$AA$12,$AU98,0),0) -> 0 | BC98: =IF(UPPER($J98) =$AB$12,IF($G98=$AA$12,$AV98,0),0) -> 0 | BD98: =IF(UPPER($J98) =$AB$12,IF($G98<>$AA$12,$AT98,0),0) -> 0 | BE98: =IF(UPPER($J98) =$AB$12,IF($G98=$AA$12,$AW98,0),0) -> 0 | BF98: =IF(UPPER($J98) =$AB$12,IF($G98<>$AA$12,$AU98,0),0) -> 0 | BG98: =IF(UPPER($K98) =$AB$12,IF($G98=$AA$12,$AV98,0),0) -> 0 | BH98: =IF(UPPER($K98) =$AB$12,IF($G98<>$AA$12,$AT98,0),0) -> 0 | BI98: =IF(UPPER($K98) =$AB$12,IF($G98=$AA$12,$AW98,0),0) -> 0 | BJ98: =IF(UPPER($K98) =$AB$12,IF($G98<>$AA$12,$AU98,0),0) -> 0 | BL98: =IF(($E98+$F98>0), IF($G98=$AA$10,1,0),0) -> 0 | BM98: =IF(($E98+$F98<=0), IF($G98<>$AA$10,1,0),0) -> 0 | BN98: =IF(($E98+$F98>0), IF($C98=$AA$10,1,0),0) -> 0
A99: 86 | AE99: =IF($C99=$Z$11,$E99,0) -> 0 | AF99: =IF($C99=$Z$11,$F99,0) -> 0 | AG99: =IF($C99=$Z$12,$E99,0) -> 0 | AH99: =IF($C99=$Z$12,$F99,0) -> 0 | AI99: =IF($C99=$Z$13,$E99,0) -> 0 | AJ99: =IF($C99=$Z$13,$F99,0) -> 0 | AK99: =IF($C99=$Z$14,$E99,0) -> 0 | AL99: =IF($C99=$Z$14,$F99,0) -> 0 | AM99: =IF($C99=$Z$15,$E99,0) -> 0 | AN99: =IF($C99=$Z$15,$F99,0) -> 0 | AO99: =IF($C99=$Z$16,$E99,0) -> 0 | AP99: =IF($C99=$Z$16,$F99,0) -> 0 | AQ99: =IF($C99=$Z$17,$E99,0) -> 0 | AR99: =IF($C99=$Z$17,$F99,0) -> 0 | AT99: =IF(OR($G99=$AA$11,$G99=$AA$13,($G99=$AA$14),$G99=$AA$15),$AE99+$AG99+$AI99+$AK99+$AQ99,0) -> 0 | AU99: =IF(OR($G99=$AA$11,$G99=$AA$13,($G99=$AA$14),$G99=$AA$15),$AF99+$AH99+$AJ99+AL99+AR99,0) -> 0 | AV99: =IF($G99=$AA$12,$AE99+$AG99+$AI99+AK99+AQ99,0) -> 0 | AW99: =IF($G99=$AA$12,$AF99+$AH99+$AJ99+AL99+AR99,0) -> 0 | AY99: =IF(UPPER($I99) =$AB$12,IF($G99=$AA$12,$AV99,0),0) -> 0 | AZ99: =IF(UPPER($I99) =$AB$12,IF($G99<>$AA$12,$AT99,0),0) -> 0 | BA99: =IF(UPPER($I99) =$AB$12,IF($G99=$AA$12,$AW99,0),0) -> 0 | BB99: =IF(UPPER($I99) =$AB$12,IF($G99<>$AA$12,$AU99,0),0) -> 0 | BC99: =IF(UPPER($J99) =$AB$12,IF($G99=$AA$12,$AV99,0),0) -> 0 | BD99: =IF(UPPER($J99) =$AB$12,IF($G99<>$AA$12,$AT99,0),0) -> 0 | BE99: =IF(UPPER($J99) =$AB$12,IF($G99=$AA$12,$AW99,0),0) -> 0 | BF99: =IF(UPPER($J99) =$AB$12,IF($G99<>$AA$12,$AU99,0),0) -> 0 | BG99: =IF(UPPER($K99) =$AB$12,IF($G99=$AA$12,$AV99,0),0) -> 0 | BH99: =IF(UPPER($K99) =$AB$12,IF($G99<>$AA$12,$AT99,0),0) -> 0 | BI99: =IF(UPPER($K99) =$AB$12,IF($G99=$AA$12,$AW99,0),0) -> 0 | BJ99: =IF(UPPER($K99) =$AB$12,IF($G99<>$AA$12,$AU99,0),0) -> 0 | BL99: =IF(($E99+$F99>0), IF($G99=$AA$10,1,0),0) -> 0 | BM99: =IF(($E99+$F99<=0), IF($G99<>$AA$10,1,0),0) -> 0 | BN99: =IF(($E99+$F99>0), IF($C99=$AA$10,1,0),0) -> 0
A100: 87 | AE100: =IF($C100=$Z$11,$E100,0) -> 0 | AF100: =IF($C100=$Z$11,$F100,0) -> 0 | AG100: =IF($C100=$Z$12,$E100,0) -> 0 | AH100: =IF($C100=$Z$12,$F100,0) -> 0 | AI100: =IF($C100=$Z$13,$E100,0) -> 0 | AJ100: =IF($C100=$Z$13,$F100,0) -> 0 | AK100: =IF($C100=$Z$14,$E100,0) -> 0 | AL100: =IF($C100=$Z$14,$F100,0) -> 0 | AM100: =IF($C100=$Z$15,$E100,0) -> 0 | AN100: =IF($C100=$Z$15,$F100,0) -> 0 | AO100: =IF($C100=$Z$16,$E100,0) -> 0 | AP100: =IF($C100=$Z$16,$F100,0) -> 0 | AQ100: =IF($C100=$Z$17,$E100,0) -> 0 | AR100: =IF($C100=$Z$17,$F100,0) -> 0 | AT100: =IF(OR($G100=$AA$11,$G100=$AA$13,($G100=$AA$14),$G100=$AA$15),$AE100+$AG100+$AI100+$AK100+$AQ100,0) -> 0 | AU100: =IF(OR($G100=$AA$11,$G100=$AA$13,($G100=$AA$14),$G100=$AA$15),$AF100+$AH100+$AJ100+AL100+AR100,0) -> 0 | AV100: =IF($G100=$AA$12,$AE100+$AG100+$AI100+AK100+AQ100,0) -> 0 | AW100: =IF($G100=$AA$12,$AF100+$AH100+$AJ100+AL100+AR100,0) -> 0 | AY100: =IF(UPPER($I100) =$AB$12,IF($G100=$AA$12,$AV100,0),0) -> 0 | AZ100: =IF(UPPER($I100) =$AB$12,IF($G100<>$AA$12,$AT100,0),0) -> 0 | BA100: =IF(UPPER($I100) =$AB$12,IF($G100=$AA$12,$AW100,0),0) -> 0 | BB100: =IF(UPPER($I100) =$AB$12,IF($G100<>$AA$12,$AU100,0),0) -> 0 | BC100: =IF(UPPER($J100) =$AB$12,IF($G100=$AA$12,$AV100,0),0) -> 0 | BD100: =IF(UPPER($J100) =$AB$12,IF($G100<>$AA$12,$AT100,0),0) -> 0 | BE100: =IF(UPPER($J100) =$AB$12,IF($G100=$AA$12,$AW100,0),0) -> 0 | BF100: =IF(UPPER($J100) =$AB$12,IF($G100<>$AA$12,$AU100,0),0) -> 0 | BG100: =IF(UPPER($K100) =$AB$12,IF($G100=$AA$12,$AV100,0),0) -> 0 | BH100: =IF(UPPER($K100) =$AB$12,IF($G100<>$AA$12,$AT100,0),0) -> 0 | BI100: =IF(UPPER($K100) =$AB$12,IF($G100=$AA$12,$AW100,0),0) -> 0 | BJ100: =IF(UPPER($K100) =$AB$12,IF($G100<>$AA$12,$AU100,0),0) -> 0 | BL100: =IF(($E100+$F100>0), IF($G100=$AA$10,1,0),0) -> 0 | BM100: =IF(($E100+$F100<=0), IF($G100<>$AA$10,1,0),0) -> 0 | BN100: =IF(($E100+$F100>0), IF($C100=$AA$10,1,0),0) -> 0
A101: 88 | AE101: =IF($C101=$Z$11,$E101,0) -> 0 | AF101: =IF($C101=$Z$11,$F101,0) -> 0 | AG101: =IF($C101=$Z$12,$E101,0) -> 0 | AH101: =IF($C101=$Z$12,$F101,0) -> 0 | AI101: =IF($C101=$Z$13,$E101,0) -> 0 | AJ101: =IF($C101=$Z$13,$F101,0) -> 0 | AK101: =IF($C101=$Z$14,$E101,0) -> 0 | AL101: =IF($C101=$Z$14,$F101,0) -> 0 | AM101: =IF($C101=$Z$15,$E101,0) -> 0 | AN101: =IF($C101=$Z$15,$F101,0) -> 0 | AO101: =IF($C101=$Z$16,$E101,0) -> 0 | AP101: =IF($C101=$Z$16,$F101,0) -> 0 | AQ101: =IF($C101=$Z$17,$E101,0) -> 0 | AR101: =IF($C101=$Z$17,$F101,0) -> 0 | AT101: =IF(OR($G101=$AA$11,$G101=$AA$13,($G101=$AA$14),$G101=$AA$15),$AE101+$AG101+$AI101+$AK101+$AQ101,0) -> 0 | AU101: =IF(OR($G101=$AA$11,$G101=$AA$13,($G101=$AA$14),$G101=$AA$15),$AF101+$AH101+$AJ101+AL101+AR101,0) -> 0 | AV101: =IF($G101=$AA$12,$AE101+$AG101+$AI101+AK101+AQ101,0) -> 0 | AW101: =IF($G101=$AA$12,$AF101+$AH101+$AJ101+AL101+AR101,0) -> 0 | AY101: =IF(UPPER($I101) =$AB$12,IF($G101=$AA$12,$AV101,0),0) -> 0 | AZ101: =IF(UPPER($I101) =$AB$12,IF($G101<>$AA$12,$AT101,0),0) -> 0 | BA101: =IF(UPPER($I101) =$AB$12,IF($G101=$AA$12,$AW101,0),0) -> 0 | BB101: =IF(UPPER($I101) =$AB$12,IF($G101<>$AA$12,$AU101,0),0) -> 0 | BC101: =IF(UPPER($J101) =$AB$12,IF($G101=$AA$12,$AV101,0),0) -> 0 | BD101: =IF(UPPER($J101) =$AB$12,IF($G101<>$AA$12,$AT101,0),0) -> 0 | BE101: =IF(UPPER($J101) =$AB$12,IF($G101=$AA$12,$AW101,0),0) -> 0 | BF101: =IF(UPPER($J101) =$AB$12,IF($G101<>$AA$12,$AU101,0),0) -> 0 | BG101: =IF(UPPER($K101) =$AB$12,IF($G101=$AA$12,$AV101,0),0) -> 0 | BH101: =IF(UPPER($K101) =$AB$12,IF($G101<>$AA$12,$AT101,0),0) -> 0 | BI101: =IF(UPPER($K101) =$AB$12,IF($G101=$AA$12,$AW101,0),0) -> 0 | BJ101: =IF(UPPER($K101) =$AB$12,IF($G101<>$AA$12,$AU101,0),0) -> 0 | BL101: =IF(($E101+$F101>0), IF($G101=$AA$10,1,0),0) -> 0 | BM101: =IF(($E101+$F101<=0), IF($G101<>$AA$10,1,0),0) -> 0 | BN101: =IF(($E101+$F101>0), IF($C101=$AA$10,1,0),0) -> 0
... A113: 100 | AE113: =IF($C113=$Z$11,$E113,0) -> 0 | AF113: =IF($C113=$Z$11,$F113,0) -> 0 | AG113: =IF($C113=$Z$12,$E113,0) -> 0 | AH113: =IF($C113=$Z$12,$F113,0) -> 0 | AI113: =IF($C113=$Z$13,$E113,0) -> 0 | AJ113: =IF($C113=$Z$13,$F113,0) -> 0 | AK113: =IF($C113=$Z$14,$E113,0) -> 0 | AL113: =IF($C113=$Z$14,$F113,0) -> 0 | AM113: =IF($C113=$Z$15,$E113,0) -> 0 | AN113: =IF($C113=$Z$15,$F113,0) -> 0 | AO113: =IF($C113=$Z$16,$E113,0) -> 0 | AP113: =IF($C113=$Z$16,$F113,0) -> 0 | AQ113: =IF($C113=$Z$17,$E113,0) -> 0 | AR113: =IF($C113=$Z$17,$F113,0) -> 0 | AT113: =IF(OR($G113=$AA$11,$G113=$AA$13,($G113=$AA$14),$G113=$AA$15),$AE113+$AG113+$AI113+$AK113+$AQ113,0) -> 0 | AU113: =IF(OR($G113=$AA$11,$G113=$AA$13,($G113=$AA$14),$G113=$AA$15),$AF113+$AH113+$AJ113+AL113+AR113,0) -> 0 | AV113: =IF($G113=$AA$12,$AE113+$AG113+$AI113+AK113+AQ113,0) -> 0 | AW113: =IF($G113=$AA$12,$AF113+$AH113+$AJ113+AL113+AR113,0) -> 0 | AY113: =IF(UPPER($I113) =$AB$12,IF($G113=$AA$12,$AV113,0),0) -> 0 | AZ113: =IF(UPPER($I113) =$AB$12,IF($G113<>$AA$12,$AT113,0),0) -> 0 | BA113: =IF(UPPER($I113) =$AB$12,IF($G113=$AA$12,$AW113,0),0) -> 0 | BB113: =IF(UPPER($I113) =$AB$12,IF($G113<>$AA$12,$AU113,0),0) -> 0 | BC113: =IF(UPPER($J113) =$AB$12,IF($G113=$AA$12,$AV113,0),0) -> 0 | BD113: =IF(UPPER($J113) =$AB$12,IF($G113<>$AA$12,$AT113,0),0) -> 0 | BE113: =IF(UPPER($J113) =$AB$12,IF($G113=$AA$12,$AW113,0),0) -> 0 | BF113: =IF(UPPER($J113) =$AB$12,IF($G113<>$AA$12,$AU113,0),0) -> 0 | BG113: =IF(UPPER($K113) =$AB$12,IF($G113=$AA$12,$AV113,0),0) -> 0 | BH113: =IF(UPPER($K113) =$AB$12,IF($G113<>$AA$12,$AT113,0),0) -> 0 | BI113: =IF(UPPER($K113) =$AB$12,IF($G113=$AA$12,$AW113,0),0) -> 0 | BJ113: =IF(UPPER($K113) =$AB$12,IF($G113<>$AA$12,$AU113,0),0) -> 0 | BL113: =IF(($E113+$F113>0), IF($G113=$AA$10,1,0),0) -> 0 | BM113: =IF(($E113+$F113<=0), IF($G113<>$AA$10,1,0),0) -> 0 | BN113: =IF(($E113+$F113>0), IF($C113=$AA$10,1,0),0) -> 0
AE114: =IF($C114=$Z$11,$E114,0) -> 0 | AF114: =IF($C114=$Z$11,$F114,0) -> 0 | AG114: =IF($C114=$Z$12,$E114,0) -> 0 | AH114: =IF($C114=$Z$12,$F114,0) -> 0 | AI114: =IF($C114=$Z$13,$E114,0) -> 0 | AJ114: =IF($C114=$Z$13,$F114,0) -> 0 | AK114: =IF($C114=$Z$14,$E114,0) -> 0 | AL114: =IF($C114=$Z$14,$F114,0) -> 0 | AM114: =IF($C114=$Z$15,$E114,0) -> 0 | AN114: =IF($C114=$Z$15,$F114,0) -> 0 | AO114: =IF($C114=$Z$16,$E114,0) -> 0 | AP114: =IF($C114=$Z$16,$F114,0) -> 0 | AQ114: =IF($C114=$Z$17,$E114,0) -> 0 | AR114: =IF($C114=$Z$17,$F114,0) -> 0 | AT114: =IF(OR($G114=$AA$11,$G114=$AA$13,($G114=$AA$14),$G114=$AA$15),$AE114+$AG114+$AI114+$AK114+$AQ114,0) -> 0 | AU114: =IF(OR($G114=$AA$11,$G114=$AA$13,($G114=$AA$14),$G114=$AA$15),$AF114+$AH114+$AJ114+AL114+AR114,0) -> 0 | AV114: =IF($G114=$AA$12,$AE114+$AG114+$AI114+AK114+AQ114,0) -> 0 | AW114: =IF($G114=$AA$12,$AF114+$AH114+$AJ114+AL114+AR114,0) -> 0 | AY114: =IF(UPPER($I114) =$AB$12,IF($G114=$AA$12,$AV114,0),0) -> 0 | AZ114: =IF(UPPER($I114) =$AB$12,IF($G114<>$AA$12,$AT114,0),0) -> 0 | BA114: =IF(UPPER($I114) =$AB$12,IF($G114=$AA$12,$AW114,0),0) -> 0 | BB114: =IF(UPPER($I114) =$AB$12,IF($G114<>$AA$12,$AU114,0),0) -> 0 | BC114: =IF(UPPER($J114) =$AB$12,IF($G114=$AA$12,$AV114,0),0) -> 0 | BD114: =IF(UPPER($J114) =$AB$12,IF($G114<>$AA$12,$AT114,0),0) -> 0 | BE114: =IF(UPPER($J114) =$AB$12,IF($G114=$AA$12,$AW114,0),0) -> 0 | BF114: =IF(UPPER($J114) =$AB$12,IF($G114<>$AA$12,$AU114,0),0) -> 0 | BG114: =IF(UPPER($K114) =$AB$12,IF($G114=$AA$12,$AV114,0),0) -> 0 | BH114: =IF(UPPER($K114) =$AB$12,IF($G114<>$AA$12,$AT114,0),0) -> 0 | BI114: =IF(UPPER($K114) =$AB$12,IF($G114=$AA$12,$AW114,0),0) -> 0 | BJ114: =IF(UPPER($K114) =$AB$12,IF($G114<>$AA$12,$AU114,0),0) -> 0 | BL114: =IF(($E114+$F114>0), IF($G114=$AA$10,1,0),0) -> 0 | BM114: =IF(($E114+$F114<=0), IF($G114<>$AA$10,1,0),0) -> 0 | BN114: =IF(($E114+$F114>0), IF($C114=$AA$10,1,0),0) -> 0
A115: 101 | L115: PAGINA 5
A116: 102 | AE116: =IF($C116=$Z$11,$E116,0) -> 0 | AF116: =IF($C116=$Z$11,$F116,0) -> 0 | AG116: =IF($C116=$Z$12,$E116,0) -> 0 | AH116: =IF($C116=$Z$12,$F116,0) -> 0 | AI116: =IF($C116=$Z$13,$E116,0) -> 0 | AJ116: =IF($C116=$Z$13,$F116,0) -> 0 | AK116: =IF($C116=$Z$14,$E116,0) -> 0 | AL116: =IF($C116=$Z$14,$F116,0) -> 0 | AM116: =IF($C116=$Z$15,$E116,0) -> 0 | AN116: =IF($C116=$Z$15,$F116,0) -> 0 | AO116: =IF($C116=$Z$16,$E116,0) -> 0 | AP116: =IF($C116=$Z$16,$F116,0) -> 0 | AQ116: =IF($C116=$Z$17,$E116,0) -> 0 | AR116: =IF($C116=$Z$17,$F116,0) -> 0 | AT116: =IF(OR($G116=$AA$11,$G116=$AA$13,($G116=$AA$14),$G116=$AA$15),$AE116+$AG116+$AI116+$AK116+$AQ116,0) -> 0 | AU116: =IF(OR($G116=$AA$11,$G116=$AA$13,($G116=$AA$14),$G116=$AA$15),$AF116+$AH116+$AJ116+AL116+AR116,0) -> 0 | AV116: =IF($G116=$AA$12,$AE116+$AG116+$AI116+AK116+AQ116,0) -> 0 | AW116: =IF($G116=$AA$12,$AF116+$AH116+$AJ116+AL116+AR116,0) -> 0 | AY116: =IF(UPPER($I116) =$AB$12,IF($G116=$AA$12,$AV116,0),0) -> 0 | AZ116: =IF(UPPER($I116) =$AB$12,IF($G116<>$AA$12,$AT116,0),0) -> 0 | BA116: =IF(UPPER($I116) =$AB$12,IF($G116=$AA$12,$AW116,0),0) -> 0 | BB116: =IF(UPPER($I116) =$AB$12,IF($G116<>$AA$12,$AU116,0),0) -> 0 | BC116: =IF(UPPER($J116) =$AB$12,IF($G116=$AA$12,$AV116,0),0) -> 0 | BD116: =IF(UPPER($J116) =$AB$12,IF($G116<>$AA$12,$AT116,0),0) -> 0 | BE116: =IF(UPPER($J116) =$AB$12,IF($G116=$AA$12,$AW116,0),0) -> 0 | BF116: =IF(UPPER($J116) =$AB$12,IF($G116<>$AA$12,$AU116,0),0) -> 0 | BG116: =IF(UPPER($K116) =$AB$12,IF($G116=$AA$12,$AV116,0),0) -> 0 | BH116: =IF(UPPER($K116) =$AB$12,IF($G116<>$AA$12,$AT116,0),0) -> 0 | BI116: =IF(UPPER($K116) =$AB$12,IF($G116=$AA$12,$AW116,0),0) -> 0 | BJ116: =IF(UPPER($K116) =$AB$12,IF($G116<>$AA$12,$AU116,0),0) -> 0 | BL116: =IF(($E116+$F116>0), IF($G116=$AA$10,1,0),0) -> 0 | BM116: =IF(($E116+$F116<=0), IF($G116<>$AA$10,1,0),0) -> 0 | BN116: =IF(($E116+$F116>0), IF($C116=$AA$10,1,0),0) -> 0
A117: 103 | AE117: =IF($C117=$Z$11,$E117,0) -> 0 | AF117: =IF($C117=$Z$11,$F117,0) -> 0 | AG117: =IF($C117=$Z$12,$E117,0) -> 0 | AH117: =IF($C117=$Z$12,$F117,0) -> 0 | AI117: =IF($C117=$Z$13,$E117,0) -> 0 | AJ117: =IF($C117=$Z$13,$F117,0) -> 0 | AK117: =IF($C117=$Z$14,$E117,0) -> 0 | AL117: =IF($C117=$Z$14,$F117,0) -> 0 | AM117: =IF($C117=$Z$15,$E117,0) -> 0 | AN117: =IF($C117=$Z$15,$F117,0) -> 0 | AO117: =IF($C117=$Z$16,$E117,0) -> 0 | AP117: =IF($C117=$Z$16,$F117,0) -> 0 | AQ117: =IF($C117=$Z$17,$E117,0) -> 0 | AR117: =IF($C117=$Z$17,$F117,0) -> 0 | AT117: =IF(OR($G117=$AA$11,$G117=$AA$13,($G117=$AA$14),$G117=$AA$15),$AE117+$AG117+$AI117+$AK117+$AQ117,0) -> 0 | AU117: =IF(OR($G117=$AA$11,$G117=$AA$13,($G117=$AA$14),$G117=$AA$15),$AF117+$AH117+$AJ117+AL117+AR117,0) -> 0 | AV117: =IF($G117=$AA$12,$AE117+$AG117+$AI117+AK117+AQ117,0) -> 0 | AW117: =IF($G117=$AA$12,$AF117+$AH117+$AJ117+AL117+AR117,0) -> 0 | AY117: =IF(UPPER($I117) =$AB$12,IF($G117=$AA$12,$AV117,0),0) -> 0 | AZ117: =IF(UPPER($I117) =$AB$12,IF($G117<>$AA$12,$AT117,0),0) -> 0 | BA117: =IF(UPPER($I117) =$AB$12,IF($G117=$AA$12,$AW117,0),0) -> 0 | BB117: =IF(UPPER($I117) =$AB$12,IF($G117<>$AA$12,$AU117,0),0) -> 0 | BC117: =IF(UPPER($J117) =$AB$12,IF($G117=$AA$12,$AV117,0),0) -> 0 | BD117: =IF(UPPER($J117) =$AB$12,IF($G117<>$AA$12,$AT117,0),0) -> 0 | BE117: =IF(UPPER($J117) =$AB$12,IF($G117=$AA$12,$AW117,0),0) -> 0 | BF117: =IF(UPPER($J117) =$AB$12,IF($G117<>$AA$12,$AU117,0),0) -> 0 | BG117: =IF(UPPER($K117) =$AB$12,IF($G117=$AA$12,$AV117,0),0) -> 0 | BH117: =IF(UPPER($K117) =$AB$12,IF($G117<>$AA$12,$AT117,0),0) -> 0 | BI117: =IF(UPPER($K117) =$AB$12,IF($G117=$AA$12,$AW117,0),0) -> 0 | BJ117: =IF(UPPER($K117) =$AB$12,IF($G117<>$AA$12,$AU117,0),0) -> 0 | BL117: =IF(($E117+$F117>0), IF($G117=$AA$10,1,0),0) -> 0 | BM117: =IF(($E117+$F117<=0), IF($G117<>$AA$10,1,0),0) -> 0 | BN117: =IF(($E117+$F117>0), IF($C117=$AA$10,1,0),0) -> 0
A118: 104 | AE118: =IF($C118=$Z$11,$E118,0) -> 0 | AF118: =IF($C118=$Z$11,$F118,0) -> 0 | AG118: =IF($C118=$Z$12,$E118,0) -> 0 | AH118: =IF($C118=$Z$12,$F118,0) -> 0 | AI118: =IF($C118=$Z$13,$E118,0) -> 0 | AJ118: =IF($C118=$Z$13,$F118,0) -> 0 | AK118: =IF($C118=$Z$14,$E118,0) -> 0 | AL118: =IF($C118=$Z$14,$F118,0) -> 0 | AM118: =IF($C118=$Z$15,$E118,0) -> 0 | AN118: =IF($C118=$Z$15,$F118,0) -> 0 | AO118: =IF($C118=$Z$16,$E118,0) -> 0 | AP118: =IF($C118=$Z$16,$F118,0) -> 0 | AQ118: =IF($C118=$Z$17,$E118,0) -> 0 | AR118: =IF($C118=$Z$17,$F118,0) -> 0 | AT118: =IF(OR($G118=$AA$11,$G118=$AA$13,($G118=$AA$14),$G118=$AA$15),$AE118+$AG118+$AI118+$AK118+$AQ118,0) -> 0 | AU118: =IF(OR($G118=$AA$11,$G118=$AA$13,($G118=$AA$14),$G118=$AA$15),$AF118+$AH118+$AJ118+AL118+AR118,0) -> 0 | AV118: =IF($G118=$AA$12,$AE118+$AG118+$AI118+AK118+AQ118,0) -> 0 | AW118: =IF($G118=$AA$12,$AF118+$AH118+$AJ118+AL118+AR118,0) -> 0 | AY118: =IF(UPPER($I118) =$AB$12,IF($G118=$AA$12,$AV118,0),0) -> 0 | AZ118: =IF(UPPER($I118) =$AB$12,IF($G118<>$AA$12,$AT118,0),0) -> 0 | BA118: =IF(UPPER($I118) =$AB$12,IF($G118=$AA$12,$AW118,0),0) -> 0 | BB118: =IF(UPPER($I118) =$AB$12,IF($G118<>$AA$12,$AU118,0),0) -> 0 | BC118: =IF(UPPER($J118) =$AB$12,IF($G118=$AA$12,$AV118,0),0) -> 0 | BD118: =IF(UPPER($J118) =$AB$12,IF($G118<>$AA$12,$AT118,0),0) -> 0 | BE118: =IF(UPPER($J118) =$AB$12,IF($G118=$AA$12,$AW118,0),0) -> 0 | BF118: =IF(UPPER($J118) =$AB$12,IF($G118<>$AA$12,$AU118,0),0) -> 0 | BG118: =IF(UPPER($K118) =$AB$12,IF($G118=$AA$12,$AV118,0),0) -> 0 | BH118: =IF(UPPER($K118) =$AB$12,IF($G118<>$AA$12,$AT118,0),0) -> 0 | BI118: =IF(UPPER($K118) =$AB$12,IF($G118=$AA$12,$AW118,0),0) -> 0 | BJ118: =IF(UPPER($K118) =$AB$12,IF($G118<>$AA$12,$AU118,0),0) -> 0 | BL118: =IF(($E118+$F118>0), IF($G118=$AA$10,1,0),0) -> 0 | BM118: =IF(($E118+$F118<=0), IF($G118<>$AA$10,1,0),0) -> 0 | BN118: =IF(($E118+$F118>0), IF($C118=$AA$10,1,0),0) -> 0
A119: 105 | AE119: =IF($C119=$Z$11,$E119,0) -> 0 | AF119: =IF($C119=$Z$11,$F119,0) -> 0 | AG119: =IF($C119=$Z$12,$E119,0) -> 0 | AH119: =IF($C119=$Z$12,$F119,0) -> 0 | AI119: =IF($C119=$Z$13,$E119,0) -> 0 | AJ119: =IF($C119=$Z$13,$F119,0) -> 0 | AK119: =IF($C119=$Z$14,$E119,0) -> 0 | AL119: =IF($C119=$Z$14,$F119,0) -> 0 | AM119: =IF($C119=$Z$15,$E119,0) -> 0 | AN119: =IF($C119=$Z$15,$F119,0) -> 0 | AO119: =IF($C119=$Z$16,$E119,0) -> 0 | AP119: =IF($C119=$Z$16,$F119,0) -> 0 | AQ119: =IF($C119=$Z$17,$E119,0) -> 0 | AR119: =IF($C119=$Z$17,$F119,0) -> 0 | AT119: =IF(OR($G119=$AA$11,$G119=$AA$13,($G119=$AA$14),$G119=$AA$15),$AE119+$AG119+$AI119+$AK119+$AQ119,0) -> 0 | AU119: =IF(OR($G119=$AA$11,$G119=$AA$13,($G119=$AA$14),$G119=$AA$15),$AF119+$AH119+$AJ119+AL119+AR119,0) -> 0 | AV119: =IF($G119=$AA$12,$AE119+$AG119+$AI119+AK119+AQ119,0) -> 0 | AW119: =IF($G119=$AA$12,$AF119+$AH119+$AJ119+AL119+AR119,0) -> 0 | AY119: =IF(UPPER($I119) =$AB$12,IF($G119=$AA$12,$AV119,0),0) -> 0 | AZ119: =IF(UPPER($I119) =$AB$12,IF($G119<>$AA$12,$AT119,0),0) -> 0 | BA119: =IF(UPPER($I119) =$AB$12,IF($G119=$AA$12,$AW119,0),0) -> 0 | BB119: =IF(UPPER($I119) =$AB$12,IF($G119<>$AA$12,$AU119,0),0) -> 0 | BC119: =IF(UPPER($J119) =$AB$12,IF($G119=$AA$12,$AV119,0),0) -> 0 | BD119: =IF(UPPER($J119) =$AB$12,IF($G119<>$AA$12,$AT119,0),0) -> 0 | BE119: =IF(UPPER($J119) =$AB$12,IF($G119=$AA$12,$AW119,0),0) -> 0 | BF119: =IF(UPPER($J119) =$AB$12,IF($G119<>$AA$12,$AU119,0),0) -> 0 | BG119: =IF(UPPER($K119) =$AB$12,IF($G119=$AA$12,$AV119,0),0) -> 0 | BH119: =IF(UPPER($K119) =$AB$12,IF($G119<>$AA$12,$AT119,0),0) -> 0 | BI119: =IF(UPPER($K119) =$AB$12,IF($G119=$AA$12,$AW119,0),0) -> 0 | BJ119: =IF(UPPER($K119) =$AB$12,IF($G119<>$AA$12,$AU119,0),0) -> 0 | BL119: =IF(($E119+$F119>0), IF($G119=$AA$10,1,0),0) -> 0 | BM119: =IF(($E119+$F119<=0), IF($G119<>$AA$10,1,0),0) -> 0 | BN119: =IF(($E119+$F119>0), IF($C119=$AA$10,1,0),0) -> 0
A120: 106 | AE120: =IF($C120=$Z$11,$E120,0) -> 0 | AF120: =IF($C120=$Z$11,$F120,0) -> 0 | AG120: =IF($C120=$Z$12,$E120,0) -> 0 | AH120: =IF($C120=$Z$12,$F120,0) -> 0 | AI120: =IF($C120=$Z$13,$E120,0) -> 0 | AJ120: =IF($C120=$Z$13,$F120,0) -> 0 | AK120: =IF($C120=$Z$14,$E120,0) -> 0 | AL120: =IF($C120=$Z$14,$F120,0) -> 0 | AM120: =IF($C120=$Z$15,$E120,0) -> 0 | AN120: =IF($C120=$Z$15,$F120,0) -> 0 | AO120: =IF($C120=$Z$16,$E120,0) -> 0 | AP120: =IF($C120=$Z$16,$F120,0) -> 0 | AQ120: =IF($C120=$Z$17,$E120,0) -> 0 | AR120: =IF($C120=$Z$17,$F120,0) -> 0 | AT120: =IF(OR($G120=$AA$11,$G120=$AA$13,($G120=$AA$14),$G120=$AA$15),$AE120+$AG120+$AI120+$AK120+$AQ120,0) -> 0 | AU120: =IF(OR($G120=$AA$11,$G120=$AA$13,($G120=$AA$14),$G120=$AA$15),$AF120+$AH120+$AJ120+AL120+AR120,0) -> 0 | AV120: =IF($G120=$AA$12,$AE120+$AG120+$AI120+AK120+AQ120,0) -> 0 | AW120: =IF($G120=$AA$12,$AF120+$AH120+$AJ120+AL120+AR120,0) -> 0 | AY120: =IF(UPPER($I120) =$AB$12,IF($G120=$AA$12,$AV120,0),0) -> 0 | AZ120: =IF(UPPER($I120) =$AB$12,IF($G120<>$AA$12,$AT120,0),0) -> 0 | BA120: =IF(UPPER($I120) =$AB$12,IF($G120=$AA$12,$AW120,0),0) -> 0 | BB120: =IF(UPPER($I120) =$AB$12,IF($G120<>$AA$12,$AU120,0),0) -> 0 | BC120: =IF(UPPER($J120) =$AB$12,IF($G120=$AA$12,$AV120,0),0) -> 0 | BD120: =IF(UPPER($J120) =$AB$12,IF($G120<>$AA$12,$AT120,0),0) -> 0 | BE120: =IF(UPPER($J120) =$AB$12,IF($G120=$AA$12,$AW120,0),0) -> 0 | BF120: =IF(UPPER($J120) =$AB$12,IF($G120<>$AA$12,$AU120,0),0) -> 0 | BG120: =IF(UPPER($K120) =$AB$12,IF($G120=$AA$12,$AV120,0),0) -> 0 | BH120: =IF(UPPER($K120) =$AB$12,IF($G120<>$AA$12,$AT120,0),0) -> 0 | BI120: =IF(UPPER($K120) =$AB$12,IF($G120=$AA$12,$AW120,0),0) -> 0 | BJ120: =IF(UPPER($K120) =$AB$12,IF($G120<>$AA$12,$AU120,0),0) -> 0 | BL120: =IF(($E120+$F120>0), IF($G120=$AA$10,1,0),0) -> 0 | BM120: =IF(($E120+$F120<=0), IF($G120<>$AA$10,1,0),0) -> 0 | BN120: =IF(($E120+$F120>0), IF($C120=$AA$10,1,0),0) -> 0
A121: 107 | AE121: =IF($C121=$Z$11,$E121,0) -> 0 | AF121: =IF($C121=$Z$11,$F121,0) -> 0 | AG121: =IF($C121=$Z$12,$E121,0) -> 0 | AH121: =IF($C121=$Z$12,$F121,0) -> 0 | AI121: =IF($C121=$Z$13,$E121,0) -> 0 | AJ121: =IF($C121=$Z$13,$F121,0) -> 0 | AK121: =IF($C121=$Z$14,$E121,0) -> 0 | AL121: =IF($C121=$Z$14,$F121,0) -> 0 | AM121: =IF($C121=$Z$15,$E121,0) -> 0 | AN121: =IF($C121=$Z$15,$F121,0) -> 0 | AO121: =IF($C121=$Z$16,$E121,0) -> 0 | AP121: =IF($C121=$Z$16,$F121,0) -> 0 | AQ121: =IF($C121=$Z$17,$E121,0) -> 0 | AR121: =IF($C121=$Z$17,$F121,0) -> 0 | AT121: =IF(OR($G121=$AA$11,$G121=$AA$13,($G121=$AA$14),$G121=$AA$15),$AE121+$AG121+$AI121+$AK121+$AQ121,0) -> 0 | AU121: =IF(OR($G121=$AA$11,$G121=$AA$13,($G121=$AA$14),$G121=$AA$15),$AF121+$AH121+$AJ121+AL121+AR121,0) -> 0 | AV121: =IF($G121=$AA$12,$AE121+$AG121+$AI121+AK121+AQ121,0) -> 0 | AW121: =IF($G121=$AA$12,$AF121+$AH121+$AJ121+AL121+AR121,0) -> 0 | AY121: =IF(UPPER($I121) =$AB$12,IF($G121=$AA$12,$AV121,0),0) -> 0 | AZ121: =IF(UPPER($I121) =$AB$12,IF($G121<>$AA$12,$AT121,0),0) -> 0 | BA121: =IF(UPPER($I121) =$AB$12,IF($G121=$AA$12,$AW121,0),0) -> 0 | BB121: =IF(UPPER($I121) =$AB$12,IF($G121<>$AA$12,$AU121,0),0) -> 0 | BC121: =IF(UPPER($J121) =$AB$12,IF($G121=$AA$12,$AV121,0),0) -> 0 | BD121: =IF(UPPER($J121) =$AB$12,IF($G121<>$AA$12,$AT121,0),0) -> 0 | BE121: =IF(UPPER($J121) =$AB$12,IF($G121=$AA$12,$AW121,0),0) -> 0 | BF121: =IF(UPPER($J121) =$AB$12,IF($G121<>$AA$12,$AU121,0),0) -> 0 | BG121: =IF(UPPER($K121) =$AB$12,IF($G121=$AA$12,$AV121,0),0) -> 0 | BH121: =IF(UPPER($K121) =$AB$12,IF($G121<>$AA$12,$AT121,0),0) -> 0 | BI121: =IF(UPPER($K121) =$AB$12,IF($G121=$AA$12,$AW121,0),0) -> 0 | BJ121: =IF(UPPER($K121) =$AB$12,IF($G121<>$AA$12,$AU121,0),0) -> 0 | BL121: =IF(($E121+$F121>0), IF($G121=$AA$10,1,0),0) -> 0 | BM121: =IF(($E121+$F121<=0), IF($G121<>$AA$10,1,0),0) -> 0 | BN121: =IF(($E121+$F121>0), IF($C121=$AA$10,1,0),0) -> 0
A122: 108 | AE122: =IF($C122=$Z$11,$E122,0) -> 0 | AF122: =IF($C122=$Z$11,$F122,0) -> 0 | AG122: =IF($C122=$Z$12,$E122,0) -> 0 | AH122: =IF($C122=$Z$12,$F122,0) -> 0 | AI122: =IF($C122=$Z$13,$E122,0) -> 0 | AJ122: =IF($C122=$Z$13,$F122,0) -> 0 | AK122: =IF($C122=$Z$14,$E122,0) -> 0 | AL122: =IF($C122=$Z$14,$F122,0) -> 0 | AM122: =IF($C122=$Z$15,$E122,0) -> 0 | AN122: =IF($C122=$Z$15,$F122,0) -> 0 | AO122: =IF($C122=$Z$16,$E122,0) -> 0 | AP122: =IF($C122=$Z$16,$F122,0) -> 0 | AQ122: =IF($C122=$Z$17,$E122,0) -> 0 | AR122: =IF($C122=$Z$17,$F122,0) -> 0 | AT122: =IF(OR($G122=$AA$11,$G122=$AA$13,($G122=$AA$14),$G122=$AA$15),$AE122+$AG122+$AI122+$AK122+$AQ122,0) -> 0 | AU122: =IF(OR($G122=$AA$11,$G122=$AA$13,($G122=$AA$14),$G122=$AA$15),$AF122+$AH122+$AJ122+AL122+AR122,0) -> 0 | AV122: =IF($G122=$AA$12,$AE122+$AG122+$AI122+AK122+AQ122,0) -> 0 | AW122: =IF($G122=$AA$12,$AF122+$AH122+$AJ122+AL122+AR122,0) -> 0 | AY122: =IF(UPPER($I122) =$AB$12,IF($G122=$AA$12,$AV122,0),0) -> 0 | AZ122: =IF(UPPER($I122) =$AB$12,IF($G122<>$AA$12,$AT122,0),0) -> 0 | BA122: =IF(UPPER($I122) =$AB$12,IF($G122=$AA$12,$AW122,0),0) -> 0 | BB122: =IF(UPPER($I122) =$AB$12,IF($G122<>$AA$12,$AU122,0),0) -> 0 | BC122: =IF(UPPER($J122) =$AB$12,IF($G122=$AA$12,$AV122,0),0) -> 0 | BD122: =IF(UPPER($J122) =$AB$12,IF($G122<>$AA$12,$AT122,0),0) -> 0 | BE122: =IF(UPPER($J122) =$AB$12,IF($G122=$AA$12,$AW122,0),0) -> 0 | BF122: =IF(UPPER($J122) =$AB$12,IF($G122<>$AA$12,$AU122,0),0) -> 0 | BG122: =IF(UPPER($K122) =$AB$12,IF($G122=$AA$12,$AV122,0),0) -> 0 | BH122: =IF(UPPER($K122) =$AB$12,IF($G122<>$AA$12,$AT122,0),0) -> 0 | BI122: =IF(UPPER($K122) =$AB$12,IF($G122=$AA$12,$AW122,0),0) -> 0 | BJ122: =IF(UPPER($K122) =$AB$12,IF($G122<>$AA$12,$AU122,0),0) -> 0 | BL122: =IF(($E122+$F122>0), IF($G122=$AA$10,1,0),0) -> 0 | BM122: =IF(($E122+$F122<=0), IF($G122<>$AA$10,1,0),0) -> 0 | BN122: =IF(($E122+$F122>0), IF($C122=$AA$10,1,0),0) -> 0
A123: 109 | AE123: =IF($C123=$Z$11,$E123,0) -> 0 | AF123: =IF($C123=$Z$11,$F123,0) -> 0 | AG123: =IF($C123=$Z$12,$E123,0) -> 0 | AH123: =IF($C123=$Z$12,$F123,0) -> 0 | AI123: =IF($C123=$Z$13,$E123,0) -> 0 | AJ123: =IF($C123=$Z$13,$F123,0) -> 0 | AK123: =IF($C123=$Z$14,$E123,0) -> 0 | AL123: =IF($C123=$Z$14,$F123,0) -> 0 | AM123: =IF($C123=$Z$15,$E123,0) -> 0 | AN123: =IF($C123=$Z$15,$F123,0) -> 0 | AO123: =IF($C123=$Z$16,$E123,0) -> 0 | AP123: =IF($C123=$Z$16,$F123,0) -> 0 | AQ123: =IF($C123=$Z$17,$E123,0) -> 0 | AR123: =IF($C123=$Z$17,$F123,0) -> 0 | AT123: =IF(OR($G123=$AA$11,$G123=$AA$13,($G123=$AA$14),$G123=$AA$15),$AE123+$AG123+$AI123+$AK123+$AQ123,0) -> 0 | AU123: =IF(OR($G123=$AA$11,$G123=$AA$13,($G123=$AA$14),$G123=$AA$15),$AF123+$AH123+$AJ123+AL123+AR123,0) -> 0 | AV123: =IF($G123=$AA$12,$AE123+$AG123+$AI123+AK123+AQ123,0) -> 0 | AW123: =IF($G123=$AA$12,$AF123+$AH123+$AJ123+AL123+AR123,0) -> 0 | AY123: =IF(UPPER($I123) =$AB$12,IF($G123=$AA$12,$AV123,0),0) -> 0 | AZ123: =IF(UPPER($I123) =$AB$12,IF($G123<>$AA$12,$AT123,0),0) -> 0 | BA123: =IF(UPPER($I123) =$AB$12,IF($G123=$AA$12,$AW123,0),0) -> 0 | BB123: =IF(UPPER($I123) =$AB$12,IF($G123<>$AA$12,$AU123,0),0) -> 0 | BC123: =IF(UPPER($J123) =$AB$12,IF($G123=$AA$12,$AV123,0),0) -> 0 | BD123: =IF(UPPER($J123) =$AB$12,IF($G123<>$AA$12,$AT123,0),0) -> 0 | BE123: =IF(UPPER($J123) =$AB$12,IF($G123=$AA$12,$AW123,0),0) -> 0 | BF123: =IF(UPPER($J123) =$AB$12,IF($G123<>$AA$12,$AU123,0),0) -> 0 | BG123: =IF(UPPER($K123) =$AB$12,IF($G123=$AA$12,$AV123,0),0) -> 0 | BH123: =IF(UPPER($K123) =$AB$12,IF($G123<>$AA$12,$AT123,0),0) -> 0 | BI123: =IF(UPPER($K123) =$AB$12,IF($G123=$AA$12,$AW123,0),0) -> 0 | BJ123: =IF(UPPER($K123) =$AB$12,IF($G123<>$AA$12,$AU123,0),0) -> 0 | BL123: =IF(($E123+$F123>0), IF($G123=$AA$10,1,0),0) -> 0 | BM123: =IF(($E123+$F123<=0), IF($G123<>$AA$10,1,0),0) -> 0 | BN123: =IF(($E123+$F123>0), IF($C123=$AA$10,1,0),0) -> 0
A124: 110 | AE124: =IF($C124=$Z$11,$E124,0) -> 0 | AF124: =IF($C124=$Z$11,$F124,0) -> 0 | AG124: =IF($C124=$Z$12,$E124,0) -> 0 | AH124: =IF($C124=$Z$12,$F124,0) -> 0 | AI124: =IF($C124=$Z$13,$E124,0) -> 0 | AJ124: =IF($C124=$Z$13,$F124,0) -> 0 | AK124: =IF($C124=$Z$14,$E124,0) -> 0 | AL124: =IF($C124=$Z$14,$F124,0) -> 0 | AM124: =IF($C124=$Z$15,$E124,0) -> 0 | AN124: =IF($C124=$Z$15,$F124,0) -> 0 | AO124: =IF($C124=$Z$16,$E124,0) -> 0 | AP124: =IF($C124=$Z$16,$F124,0) -> 0 | AQ124: =IF($C124=$Z$17,$E124,0) -> 0 | AR124: =IF($C124=$Z$17,$F124,0) -> 0 | AT124: =IF(OR($G124=$AA$11,$G124=$AA$13,($G124=$AA$14),$G124=$AA$15),$AE124+$AG124+$AI124+$AK124+$AQ124,0) -> 0 | AU124: =IF(OR($G124=$AA$11,$G124=$AA$13,($G124=$AA$14),$G124=$AA$15),$AF124+$AH124+$AJ124+AL124+AR124,0) -> 0 | AV124: =IF($G124=$AA$12,$AE124+$AG124+$AI124+AK124+AQ124,0) -> 0 | AW124: =IF($G124=$AA$12,$AF124+$AH124+$AJ124+AL124+AR124,0) -> 0 | AY124: =IF(UPPER($I124) =$AB$12,IF($G124=$AA$12,$AV124,0),0) -> 0 | AZ124: =IF(UPPER($I124) =$AB$12,IF($G124<>$AA$12,$AT124,0),0) -> 0 | BA124: =IF(UPPER($I124) =$AB$12,IF($G124=$AA$12,$AW124,0),0) -> 0 | BB124: =IF(UPPER($I124) =$AB$12,IF($G124<>$AA$12,$AU124,0),0) -> 0 | BC124: =IF(UPPER($J124) =$AB$12,IF($G124=$AA$12,$AV124,0),0) -> 0 | BD124: =IF(UPPER($J124) =$AB$12,IF($G124<>$AA$12,$AT124,0),0) -> 0 | BE124: =IF(UPPER($J124) =$AB$12,IF($G124=$AA$12,$AW124,0),0) -> 0 | BF124: =IF(UPPER($J124) =$AB$12,IF($G124<>$AA$12,$AU124,0),0) -> 0 | BG124: =IF(UPPER($K124) =$AB$12,IF($G124=$AA$12,$AV124,0),0) -> 0 | BH124: =IF(UPPER($K124) =$AB$12,IF($G124<>$AA$12,$AT124,0),0) -> 0 | BI124: =IF(UPPER($K124) =$AB$12,IF($G124=$AA$12,$AW124,0),0) -> 0 | BJ124: =IF(UPPER($K124) =$AB$12,IF($G124<>$AA$12,$AU124,0),0) -> 0 | BL124: =IF(($E124+$F124>0), IF($G124=$AA$10,1,0),0) -> 0 | BM124: =IF(($E124+$F124<=0), IF($G124<>$AA$10,1,0),0) -> 0 | BN124: =IF(($E124+$F124>0), IF($C124=$AA$10,1,0),0) -> 0
A125: 111 | AE125: =IF($C125=$Z$11,$E125,0) -> 0 | AF125: =IF($C125=$Z$11,$F125,0) -> 0 | AG125: =IF($C125=$Z$12,$E125,0) -> 0 | AH125: =IF($C125=$Z$12,$F125,0) -> 0 | AI125: =IF($C125=$Z$13,$E125,0) -> 0 | AJ125: =IF($C125=$Z$13,$F125,0) -> 0 | AK125: =IF($C125=$Z$14,$E125,0) -> 0 | AL125: =IF($C125=$Z$14,$F125,0) -> 0 | AM125: =IF($C125=$Z$15,$E125,0) -> 0 | AN125: =IF($C125=$Z$15,$F125,0) -> 0 | AO125: =IF($C125=$Z$16,$E125,0) -> 0 | AP125: =IF($C125=$Z$16,$F125,0) -> 0 | AQ125: =IF($C125=$Z$17,$E125,0) -> 0 | AR125: =IF($C125=$Z$17,$F125,0) -> 0 | AT125: =IF(OR($G125=$AA$11,$G125=$AA$13,($G125=$AA$14),$G125=$AA$15),$AE125+$AG125+$AI125+$AK125+$AQ125,0) -> 0 | AU125: =IF(OR($G125=$AA$11,$G125=$AA$13,($G125=$AA$14),$G125=$AA$15),$AF125+$AH125+$AJ125+AL125+AR125,0) -> 0 | AV125: =IF($G125=$AA$12,$AE125+$AG125+$AI125+AK125+AQ125,0) -> 0 | AW125: =IF($G125=$AA$12,$AF125+$AH125+$AJ125+AL125+AR125,0) -> 0 | AY125: =IF(UPPER($I125) =$AB$12,IF($G125=$AA$12,$AV125,0),0) -> 0 | AZ125: =IF(UPPER($I125) =$AB$12,IF($G125<>$AA$12,$AT125,0),0) -> 0 | BA125: =IF(UPPER($I125) =$AB$12,IF($G125=$AA$12,$AW125,0),0) -> 0 | BB125: =IF(UPPER($I125) =$AB$12,IF($G125<>$AA$12,$AU125,0),0) -> 0 | BC125: =IF(UPPER($J125) =$AB$12,IF($G125=$AA$12,$AV125,0),0) -> 0 | BD125: =IF(UPPER($J125) =$AB$12,IF($G125<>$AA$12,$AT125,0),0) -> 0 | BE125: =IF(UPPER($J125) =$AB$12,IF($G125=$AA$12,$AW125,0),0) -> 0 | BF125: =IF(UPPER($J125) =$AB$12,IF($G125<>$AA$12,$AU125,0),0) -> 0 | BG125: =IF(UPPER($K125) =$AB$12,IF($G125=$AA$12,$AV125,0),0) -> 0 | BH125: =IF(UPPER($K125) =$AB$12,IF($G125<>$AA$12,$AT125,0),0) -> 0 | BI125: =IF(UPPER($K125) =$AB$12,IF($G125=$AA$12,$AW125,0),0) -> 0 | BJ125: =IF(UPPER($K125) =$AB$12,IF($G125<>$AA$12,$AU125,0),0) -> 0 | BL125: =IF(($E125+$F125>0), IF($G125=$AA$10,1,0),0) -> 0 | BM125: =IF(($E125+$F125<=0), IF($G125<>$AA$10,1,0),0) -> 0 | BN125: =IF(($E125+$F125>0), IF($C125=$AA$10,1,0),0) -> 0
A126: 112 | AE126: =IF($C126=$Z$11,$E126,0) -> 0 | AF126: =IF($C126=$Z$11,$F126,0) -> 0 | AG126: =IF($C126=$Z$12,$E126,0) -> 0 | AH126: =IF($C126=$Z$12,$F126,0) -> 0 | AI126: =IF($C126=$Z$13,$E126,0) -> 0 | AJ126: =IF($C126=$Z$13,$F126,0) -> 0 | AK126: =IF($C126=$Z$14,$E126,0) -> 0 | AL126: =IF($C126=$Z$14,$F126,0) -> 0 | AM126: =IF($C126=$Z$15,$E126,0) -> 0 | AN126: =IF($C126=$Z$15,$F126,0) -> 0 | AO126: =IF($C126=$Z$16,$E126,0) -> 0 | AP126: =IF($C126=$Z$16,$F126,0) -> 0 | AQ126: =IF($C126=$Z$17,$E126,0) -> 0 | AR126: =IF($C126=$Z$17,$F126,0) -> 0 | AT126: =IF(OR($G126=$AA$11,$G126=$AA$13,($G126=$AA$14),$G126=$AA$15),$AE126+$AG126+$AI126+$AK126+$AQ126,0) -> 0 | AU126: =IF(OR($G126=$AA$11,$G126=$AA$13,($G126=$AA$14),$G126=$AA$15),$AF126+$AH126+$AJ126+AL126+AR126,0) -> 0 | AV126: =IF($G126=$AA$12,$AE126+$AG126+$AI126+AK126+AQ126,0) -> 0 | AW126: =IF($G126=$AA$12,$AF126+$AH126+$AJ126+AL126+AR126,0) -> 0 | AY126: =IF(UPPER($I126) =$AB$12,IF($G126=$AA$12,$AV126,0),0) -> 0 | AZ126: =IF(UPPER($I126) =$AB$12,IF($G126<>$AA$12,$AT126,0),0) -> 0 | BA126: =IF(UPPER($I126) =$AB$12,IF($G126=$AA$12,$AW126,0),0) -> 0 | BB126: =IF(UPPER($I126) =$AB$12,IF($G126<>$AA$12,$AU126,0),0) -> 0 | BC126: =IF(UPPER($J126) =$AB$12,IF($G126=$AA$12,$AV126,0),0) -> 0 | BD126: =IF(UPPER($J126) =$AB$12,IF($G126<>$AA$12,$AT126,0),0) -> 0 | BE126: =IF(UPPER($J126) =$AB$12,IF($G126=$AA$12,$AW126,0),0) -> 0 | BF126: =IF(UPPER($J126) =$AB$12,IF($G126<>$AA$12,$AU126,0),0) -> 0 | BG126: =IF(UPPER($K126) =$AB$12,IF($G126=$AA$12,$AV126,0),0) -> 0 | BH126: =IF(UPPER($K126) =$AB$12,IF($G126<>$AA$12,$AT126,0),0) -> 0 | BI126: =IF(UPPER($K126) =$AB$12,IF($G126=$AA$12,$AW126,0),0) -> 0 | BJ126: =IF(UPPER($K126) =$AB$12,IF($G126<>$AA$12,$AU126,0),0) -> 0 | BL126: =IF(($E126+$F126>0), IF($G126=$AA$10,1,0),0) -> 0 | BM126: =IF(($E126+$F126<=0), IF($G126<>$AA$10,1,0),0) -> 0 | BN126: =IF(($E126+$F126>0), IF($C126=$AA$10,1,0),0) -> 0
A127: 113 | AE127: =IF($C127=$Z$11,$E127,0) -> 0 | AF127: =IF($C127=$Z$11,$F127,0) -> 0 | AG127: =IF($C127=$Z$12,$E127,0) -> 0 | AH127: =IF($C127=$Z$12,$F127,0) -> 0 | AI127: =IF($C127=$Z$13,$E127,0) -> 0 | AJ127: =IF($C127=$Z$13,$F127,0) -> 0 | AK127: =IF($C127=$Z$14,$E127,0) -> 0 | AL127: =IF($C127=$Z$14,$F127,0) -> 0 | AM127: =IF($C127=$Z$15,$E127,0) -> 0 | AN127: =IF($C127=$Z$15,$F127,0) -> 0 | AO127: =IF($C127=$Z$16,$E127,0) -> 0 | AP127: =IF($C127=$Z$16,$F127,0) -> 0 | AQ127: =IF($C127=$Z$17,$E127,0) -> 0 | AR127: =IF($C127=$Z$17,$F127,0) -> 0 | AT127: =IF(OR($G127=$AA$11,$G127=$AA$13,($G127=$AA$14),$G127=$AA$15),$AE127+$AG127+$AI127+$AK127+$AQ127,0) -> 0 | AU127: =IF(OR($G127=$AA$11,$G127=$AA$13,($G127=$AA$14),$G127=$AA$15),$AF127+$AH127+$AJ127+AL127+AR127,0) -> 0 | AV127: =IF($G127=$AA$12,$AE127+$AG127+$AI127+AK127+AQ127,0) -> 0 | AW127: =IF($G127=$AA$12,$AF127+$AH127+$AJ127+AL127+AR127,0) -> 0 | AY127: =IF(UPPER($I127) =$AB$12,IF($G127=$AA$12,$AV127,0),0) -> 0 | AZ127: =IF(UPPER($I127) =$AB$12,IF($G127<>$AA$12,$AT127,0),0) -> 0 | BA127: =IF(UPPER($I127) =$AB$12,IF($G127=$AA$12,$AW127,0),0) -> 0 | BB127: =IF(UPPER($I127) =$AB$12,IF($G127<>$AA$12,$AU127,0),0) -> 0 | BC127: =IF(UPPER($J127) =$AB$12,IF($G127=$AA$12,$AV127,0),0) -> 0 | BD127: =IF(UPPER($J127) =$AB$12,IF($G127<>$AA$12,$AT127,0),0) -> 0 | BE127: =IF(UPPER($J127) =$AB$12,IF($G127=$AA$12,$AW127,0),0) -> 0 | BF127: =IF(UPPER($J127) =$AB$12,IF($G127<>$AA$12,$AU127,0),0) -> 0 | BG127: =IF(UPPER($K127) =$AB$12,IF($G127=$AA$12,$AV127,0),0) -> 0 | BH127: =IF(UPPER($K127) =$AB$12,IF($G127<>$AA$12,$AT127,0),0) -> 0 | BI127: =IF(UPPER($K127) =$AB$12,IF($G127=$AA$12,$AW127,0),0) -> 0 | BJ127: =IF(UPPER($K127) =$AB$12,IF($G127<>$AA$12,$AU127,0),0) -> 0 | BL127: =IF(($E127+$F127>0), IF($G127=$AA$10,1,0),0) -> 0 | BM127: =IF(($E127+$F127<=0), IF($G127<>$AA$10,1,0),0) -> 0 | BN127: =IF(($E127+$F127>0), IF($C127=$AA$10,1,0),0) -> 0
... A139: 125 | AE139: =IF($C139=$Z$11,$E139,0) -> 0 | AF139: =IF($C139=$Z$11,$F139,0) -> 0 | AG139: =IF($C139=$Z$12,$E139,0) -> 0 | AH139: =IF($C139=$Z$12,$F139,0) -> 0 | AI139: =IF($C139=$Z$13,$E139,0) -> 0 | AJ139: =IF($C139=$Z$13,$F139,0) -> 0 | AK139: =IF($C139=$Z$14,$E139,0) -> 0 | AL139: =IF($C139=$Z$14,$F139,0) -> 0 | AM139: =IF($C139=$Z$15,$E139,0) -> 0 | AN139: =IF($C139=$Z$15,$F139,0) -> 0 | AO139: =IF($C139=$Z$16,$E139,0) -> 0 | AP139: =IF($C139=$Z$16,$F139,0) -> 0 | AQ139: =IF($C139=$Z$17,$E139,0) -> 0 | AR139: =IF($C139=$Z$17,$F139,0) -> 0 | AT139: =IF(OR($G139=$AA$11,$G139=$AA$13,($G139=$AA$14),$G139=$AA$15),$AE139+$AG139+$AI139+$AK139+$AQ139,0) -> 0 | AU139: =IF(OR($G139=$AA$11,$G139=$AA$13,($G139=$AA$14),$G139=$AA$15),$AF139+$AH139+$AJ139+AL139+AR139,0) -> 0 | AV139: =IF($G139=$AA$12,$AE139+$AG139+$AI139+AK139+AQ139,0) -> 0 | AW139: =IF($G139=$AA$12,$AF139+$AH139+$AJ139+AL139+AR139,0) -> 0 | AY139: =IF(UPPER($I139) =$AB$12,IF($G139=$AA$12,$AV139,0),0) -> 0 | AZ139: =IF(UPPER($I139) =$AB$12,IF($G139<>$AA$12,$AT139,0),0) -> 0 | BA139: =IF(UPPER($I139) =$AB$12,IF($G139=$AA$12,$AW139,0),0) -> 0 | BB139: =IF(UPPER($I139) =$AB$12,IF($G139<>$AA$12,$AU139,0),0) -> 0 | BC139: =IF(UPPER($J139) =$AB$12,IF($G139=$AA$12,$AV139,0),0) -> 0 | BD139: =IF(UPPER($J139) =$AB$12,IF($G139<>$AA$12,$AT139,0),0) -> 0 | BE139: =IF(UPPER($J139) =$AB$12,IF($G139=$AA$12,$AW139,0),0) -> 0 | BF139: =IF(UPPER($J139) =$AB$12,IF($G139<>$AA$12,$AU139,0),0) -> 0 | BG139: =IF(UPPER($K139) =$AB$12,IF($G139=$AA$12,$AV139,0),0) -> 0 | BH139: =IF(UPPER($K139) =$AB$12,IF($G139<>$AA$12,$AT139,0),0) -> 0 | BI139: =IF(UPPER($K139) =$AB$12,IF($G139=$AA$12,$AW139,0),0) -> 0 | BJ139: =IF(UPPER($K139) =$AB$12,IF($G139<>$AA$12,$AU139,0),0) -> 0 | BL139: =IF(($E139+$F139>0), IF($G139=$AA$10,1,0),0) -> 0 | BM139: =IF(($E139+$F139<=0), IF($G139<>$AA$10,1,0),0) -> 0 | BN139: =IF(($E139+$F139>0), IF($C139=$AA$10,1,0),0) -> 0
A140: 126 | AE140: =IF($C140=$Z$11,$E140,0) -> 0 | AF140: =IF($C140=$Z$11,$F140,0) -> 0 | AG140: =IF($C140=$Z$12,$E140,0) -> 0 | AH140: =IF($C140=$Z$12,$F140,0) -> 0 | AI140: =IF($C140=$Z$13,$E140,0) -> 0 | AJ140: =IF($C140=$Z$13,$F140,0) -> 0 | AK140: =IF($C140=$Z$14,$E140,0) -> 0 | AL140: =IF($C140=$Z$14,$F140,0) -> 0 | AM140: =IF($C140=$Z$15,$E140,0) -> 0 | AN140: =IF($C140=$Z$15,$F140,0) -> 0 | AO140: =IF($C140=$Z$16,$E140,0) -> 0 | AP140: =IF($C140=$Z$16,$F140,0) -> 0 | AQ140: =IF($C140=$Z$17,$E140,0) -> 0 | AR140: =IF($C140=$Z$17,$F140,0) -> 0 | AT140: =IF(OR($G140=$AA$11,$G140=$AA$13,($G140=$AA$14),$G140=$AA$15),$AE140+$AG140+$AI140+$AK140+$AQ140,0) -> 0 | AU140: =IF(OR($G140=$AA$11,$G140=$AA$13,($G140=$AA$14),$G140=$AA$15),$AF140+$AH140+$AJ140+AL140+AR140,0) -> 0 | AV140: =IF($G140=$AA$12,$AE140+$AG140+$AI140+AK140+AQ140,0) -> 0 | AW140: =IF($G140=$AA$12,$AF140+$AH140+$AJ140+AL140+AR140,0) -> 0 | AY140: =IF(UPPER($I140) =$AB$12,IF($G140=$AA$12,$AV140,0),0) -> 0 | AZ140: =IF(UPPER($I140) =$AB$12,IF($G140<>$AA$12,$AT140,0),0) -> 0 | BA140: =IF(UPPER($I140) =$AB$12,IF($G140=$AA$12,$AW140,0),0) -> 0 | BB140: =IF(UPPER($I140) =$AB$12,IF($G140<>$AA$12,$AU140,0),0) -> 0 | BC140: =IF(UPPER($J140) =$AB$12,IF($G140=$AA$12,$AV140,0),0) -> 0 | BD140: =IF(UPPER($J140) =$AB$12,IF($G140<>$AA$12,$AT140,0),0) -> 0 | BE140: =IF(UPPER($J140) =$AB$12,IF($G140=$AA$12,$AW140,0),0) -> 0 | BF140: =IF(UPPER($J140) =$AB$12,IF($G140<>$AA$12,$AU140,0),0) -> 0 | BG140: =IF(UPPER($K140) =$AB$12,IF($G140=$AA$12,$AV140,0),0) -> 0 | BH140: =IF(UPPER($K140) =$AB$12,IF($G140<>$AA$12,$AT140,0),0) -> 0 | BI140: =IF(UPPER($K140) =$AB$12,IF($G140=$AA$12,$AW140,0),0) -> 0 | BJ140: =IF(UPPER($K140) =$AB$12,IF($G140<>$AA$12,$AU140,0),0) -> 0

Sheet RIMBORSO KM
G1: Doc. rimborso KM rev.04
F2: Nota Spese | G2: Elenco tragitti per rimborso km - modulo
A4: ELENCO TRAGITTI PER RIMBORSO KM
E6: Causale:
E7: Autore:
F8: Firma:
A9: N° | B9: Data | C9: Causale | G9: km
A10: 1
A11: 2
A12: 3
A13: 4
A14: 5
A15: 6
A16: 7
A17: 8
A18: 9
A19: 10
A20: 11
A21: 12
... A56: 47
A57: TOTALE DA RIMBORSARE: | D57: =G57*0.3 -> 0 | F57: TOTALE Km : | G57: =SUM(G10:G56) -> 0

Sheet Note di compilazione
A1: NOTE PER LA COMPILAZIONE:
A3: Il modulo deve essere utilizzato da tutto coloro che, per conto dell'azienda, hanno sostenuto delle spese sia in contanti che con carta di credito aziendale.
A5: Il primo foglio " RIEPILOGO RIMBORSO SPESE" va compilato nella parte "dati trasferta" solo in caso di trasferte e spese diverse raggruppabili mensilmente ( scontrini e rimborso km )
A6: Nel secondo foglio " RIMBORSO SPESE" vanno elencati uno per uno gli scontrini e/o fatture riportando il numero sequenziale a penna sul documento
A7: I campi vanno compilati utilizzando la tendina sulla destra di ogni colonna ad esclusione della colonna" D " CAUSALE" dove va inserito il dettaglio della spesa effettuata.
A8: Il campo di cui alla colonna "I" " NON GIUST" va compilato solo nel caso in cui manca il giustificativo della spesa.
A10: Nel terzo foglio " RIMBORSO KM" vanno elencati tutti i tragitti effettuati con la propria auto indicandone il viaggio da/per e i km.
A12: Tutti gli importi inseriti nei fogli "RIMBORSO SPESE" e" RIMBORSO KM" verranno automaticamente riportati nel foglio RIEPILOGO SPESE DI TRASFERTA
A14: Nel caso in cui è previsto solo il rimborso spese e non il rimborso km o viceversa, non è necessario compilare anche il riepilogo
A16: Prima della consegna il modulo va stampato, allegato ai giustificativi, firmato dal dipendente e approvato dal responsabile
A21: 1 OBIETTIVO
A22: Definire regole, comportamenti e modalità operative per il rimborso delle spese effettuate durante le trasferte effettuate dal personale Balance Systems.
... A155: NOTA: Anche in caso di uscita di servizio la nota spese in formato digitale va inviata via mail all’Uff. personale per archiviazione.
